Workbook
Name copyright: About!$B$48
Name var_AAR: Variables!$C$5
Name var_averageCoC: Variables!$C$9
Name var_capRateBump: 'Exit Strategy'!$I$9
Name var_DSCR: Variables!$C$4
Name var_expensePercentage: Variables!$C$7
Name var_IRR: Variables!$C$6
Name var_operatingReserves: Variables!$C$11
Name var_returnCapitalPercentage: Variables!$C$8
Name var_totalLoan: Variables!$C$13
Name year_refi: 'Exit Strategy'!$D$4
Name year_sale: 'Exit Strategy'!$D$5

Sheet Welcome
B1: Welcome | C1: Version 2.9.4
B3: Welcome to the SYNDICATED DEAL ANALYZER software!
B5: I created the Syndicated Deal Analyzer software over many years and continued to improve it with every deal I analyzed. The primary difference between this analyzer and others you may have seen is that it incorporates other investors into all aspects of the deal, from analysis, to closing, to final disposition. It's designed to quickly do the easy things, but it also allows you to customize all of the assumptions and numbers, which is important as you discover new information during due diligence. I purposefully allow you to edit and customize EVERYTHING for two reasons: (1) so that you can understand the formulas to help you to learn and (2) so that you can make it look like you want. My goal with the Syndicated Deal Analyzer is to help you analyze deals faster and more accurately so that you can make more offers and do more deals.
B6: =HYPERLINK("https://courses.themichaelblank.com/users/sign_in","To get started, please watch the training videos, which you can access here.") -> To get started, please watch the training videos, which you can access here.
B7: If you'd like to get support and feedback of your analysis, please consider joining the Deal Maker's Mastermind. To your success!
B8: =HYPERLINK("http://www.themichaelblank.com/dmm","Learn More About the Deal Maker's Mastermind.") -> Learn More About the Deal Maker's Mastermind.
B12: To Your Success!
B18: The Michael Blank Team

Sheet About
B1: About
B3: Deal Readiness Dashboard
B4: Key Metric | C4: Minimum Criteria | D4: Actual | E4: Comments
B5: Debt Coverage Ratio (DCR) | C5: =IF($B$46=Variables!$E$27,Variables!C4,IF($B$46=Variables!$F$26,Variables!C4,Variables!D4)) -> 1.25 | D5: =Summary!D38 -> 0 | E5: =IF(D5=0,"",IF(D5<C5,Variables!E4,Variables!F4))
B6: Average Annual Return (AAR) | C6: =IF($B$46=Variables!$E$27,Variables!C5,IF($B$46=Variables!$F$26,Variables!C5,Variables!D5)) -> 0.15 | D6: =Summary!D48 -> 0 | E6: =IF(D6=0,"",IF(D6<C6,Variables!E5,Variables!F5))
B7: Internal Rate of Return (IRR) | C7: =IF($B$46=Variables!$E$27,Variables!C6,IF($B$46=Variables!$F$26,Variables!C6,Variables!D6)) -> 0.14 | D7: =Summary!D50 -> 0 | E7: =IF(D7=0,"",IF(D7<C7,Variables!E6,Variables!F6))
B8: Expenses | C8: =IF($B$46=Variables!$E$27,Variables!C7,IF($B$46=Variables!$F$26,Variables!C7,Variables!D7)) -> 0.5 | D8: =Summary!C32 -> 0 | E8: =IF(D8=0,"",IF(D8<C8,Variables!E7,Variables!F7))
B9: % of Capital Returned With Refinance | C9: =IF($B$46=Variables!$E$27,Variables!C8,IF($B$46=Variables!$F$26,Variables!C8,Variables!D8)) -> 0.6 | D9: =IF('Exit Strategy'!D4="NA","NA",'Exit Strategy'!D23) -> NA | E9: =IF(OR(D9=0,D9="NA"),"",IF(D9<C9,Variables!E8,Variables!F8))
B10: Cash-on-Cash Return (CoC) | C10: =IF($B$46=Variables!$E$27,Variables!C9,IF($B$46=Variables!$F$26,Variables!C9,Variables!D9)) -> 0.07 | D10: =Summary!D37 -> 0 | E10: =IF(D10=0,"",IF(D10<C10,Variables!E9,Variables!F9))
B11: Replacement Reserves | C11: =IF($B$46=Variables!$E$27,Variables!C10,IF($B$46=Variables!$F$26,Variables!C10,Variables!D10)) -> 0 | D11: ='P&L'!D32 -> 0 | E11: =IF(D5=0,"",IF(D11<C11,Variables!E10,Variables!F10))
B12: Reserves | C12: =IF($B$46=Variables!$E$27,Variables!C11,IF($B$46=Variables!$F$26,Variables!C11,Variables!D11)) -> 0 | D12: =Summary!D21 -> 0 | E12: =IF(D5=0,"",IF(D12<C12,Variables!E11,Variables!F11))
B13: Sale in Year 5 | C13: =IF($B$46=Variables!$E$27,Variables!C12,IF($B$46=Variables!$F$26,Variables!C12,Variables!D12)) -> Yes | D13: =IF('Exit Strategy'!D5=5,"Yes","No") -> Yes | E13: =IF(D5=0,"",IF(D13=C13,Variables!F12,Variables!E12))
B14: Deal Size | C14: =IF($B$46=Variables!$E$27,Variables!C13,IF($B$46=Variables!$F$26,Variables!C13,Variables!D13)) -> 1000000 | D14: =Summary!D10 -> 0 | E14: =IF($D$5=0,"",IF(D14>=C14,Variables!F13,Variables!E13))
B16: Deal Readiness Questionnaire
B17: Before you make a formal offer (LOI or Contract), complete this questionnaire to make sure the deal is ready. It will ensure that you've researched the deal enough to move forward. If you can't answer these questions thoroughly, you may need to do some more work.
B18: Provide an Executive Summary of This Deal If you had 60 seconds to explain this deal to someone else, what would you say?
B20: What City Is This Property In?
B22: Cleary Describe the PROBLEM with this Property and Your SOLUTION.
B23: If rents are low, why are the low? How do you know (i.e. who did you talk to)? What's the plan to raise rents, and what will it take and how much will it cost to achieve the target rents?
B25: Is the property poorly managed? Why? Is it self-managed or some other reason? What makes you think you can manage it better?
B27: Are there any down units? If so, why are they down? What needs to happen to get them rent-ready?
B29: Are vacancies high? If so, why? How do you know this? What needs to happen to achieve the occupancy targets?
B31: Are the expenses high? If so, why? How do you know this? What is your plan for reducing the expenses?
B33: Provide details about your estimated repairs you provided in the "Summary" tab.
B35: How Did You Arrive at the Market Cap Rate?
... B39: Where Are You With the Negotiation?
B40: Click to Select | D40: =IF(B40=Variables!F20, Variables!F21,IF(B40=Variables!G20,Variables!G21,IF(B40=Variables!H20,Variables!H21,IF(B40=Variables!I20,Variables!I21,IF(B40=Variables!J20,Variables!J21,IF(B40=Variables!K20,Variables!K21,IF(B40=Variables!L20,Variables!L21,"")))))))
B41: Did You Visit the Property?
B42: Click to Select | D42: =IF(B42="Yes", Variables!E24,IF(B42="No",Variables!F23,""))
B43: Have You Spoken To a Mortgage Broker/Lender?
B44: Click to Select | D44: =IF(B44="Yes", Variables!E26,IF(B44="No",Variables!F25,""))
B45: Would You Consider this a "Value-Add" or "Stable" Deal? This slightly changes the Minimum Criteria in the Deal Readiness Dashboard.
B46: Click to Select | D46: =IF(B46="Value-Add", Variables!E28,IF(B46="Stable",Variables!F27,""))
B48: ="Copyright © "&YEAR(TODAY())&" Michael Blank." -> Copyright © 2026 Michael Blank.
B49: The information herein is not guaranteed but believed to be accurate.

Sheet Scenarios
B1: Side-by-Side Scenarios
A2: "The 10 Minute Offer"
D3: 1. Marketing Package | G3: 2. My Version | J3: 3. Projected | M3: 4. Offer | P3: 5. Scenario A | S3: 6. Scenario B | V3: 7. Scenario C | Y3: 8. Scenario D
B5: Acquisition | AC5: Target Rent Analysis
B6: Asking Price | D6: 0 | G6: =D6 -> 0 | J6: =G6 -> 0 | M6: =J6 -> 0 | P6: =M6 -> 0 | S6: =P6 -> 0 | V6: =S6 -> 0 | Y6: =V6 -> 0 | AE6: Current Rent | AG6: Target Rent
B7: Purchase | D7: =D6 -> 0 | G7: =G6 -> 0 | J7: =G7 -> 0 | M7: =J7 -> 0 | P7: =M7 -> 0 | S7: =P7 -> 0 | V7: =S7 -> 0 | Y7: =V7 -> 0 | AC7: Type | AD7: # Units | AE7: Average | AF7: Total | AG7: Average | AH7: Total
B8: # Units | D8: 0 | G8: =D8 -> 0 | J8: =G8 -> 0 | M8: =J8 -> 0 | P8: =M8 -> 0 | S8: =P8 -> 0 | V8: =S8 -> 0 | Y8: =V8 -> 0 | AC8: Unit type | AD8: 0 | AE8: 0 | AF8: =AE8*AD8 -> 0 | AG8: 0 | AH8: =AG8*AD8 -> 0
B9: Price Per Unit | D9: =IF(D8=0,0,D7/D8) -> 0 | G9: =IF(G8=0,0,G7/G8) -> 0 | J9: =IF(J8=0,0,J7/J8) -> 0 | M9: =IF(M8=0,0,M7/M8) -> 0 | P9: =IF(P8=0,0,P7/P8) -> 0 | S9: =IF(S8=0,0,S7/S8) -> 0 | V9: =IF(V8=0,0,V7/V8) -> 0 | Y9: =IF(Y8=0,0,Y7/Y8) -> 0 | AC9: Unit type | AD9: 0 | AE9: 0 | AF9: =AE9*AD9 -> 0 | AG9: 0 | AH9: =AG9*AD9 -> 0
B10: Down payment % | D10: 0.25 | G10: =D10 -> 0.25 | J10: =G10 -> 0.25 | M10: =J10 -> 0.25 | P10: =M10 -> 0.25 | S10: =P10 -> 0.25 | V10: =S10 -> 0.25 | Y10: =V10 -> 0.25 | AC10: Unit type | AD10: 0 | AE10: 0 | AF10: =AE10*AD10 -> 0 | AG10: 0 | AH10: =AG10*AD10 -> 0
B11: Down payment $ | D11: =D10*D7 -> 0 | G11: =G10*G7 -> 0 | J11: =J10*J7 -> 0 | M11: =M10*M7 -> 0 | P11: =P10*P7 -> 0 | S11: =S10*S7 -> 0 | V11: =V10*V7 -> 0 | Y11: =Y10*Y7 -> 0 | AC11: Unit type | AD11: 0 | AE11: 0 | AF11: =AE11*AD11 -> 0 | AG11: 0 | AH11: =AG11*AD11 -> 0
B12: Interest Only (in months) | D12: 0 | G12: =D12 -> 0 | J12: =G12 -> 0 | M12: =J12 -> 0 | P12: =M12 -> 0 | S12: =P12 -> 0 | V12: =S12 -> 0 | Y12: =V12 -> 0 | AC12: Unit type | AD12: 0 | AE12: 0 | AF12: =AE12*AD12 -> 0 | AG12: 0 | AH12: =AG12*AD12 -> 0
B13: Loan Balance | D13: =D7-D11 -> 0 | G13: =G7-G11 -> 0 | J13: =J7-J11 -> 0 | M13: =M7-M11 -> 0 | P13: =P7-P11 -> 0 | S13: =S7-S11 -> 0 | V13: =V7-V11 -> 0 | Y13: =Y7-Y11 -> 0 | AC13: Unit type | AD13: 0 | AE13: 0 | AF13: =AE13*AD13 -> 0 | AG13: 0 | AH13: =AG13*AD13 -> 0
B14: Repairs | C14: OFF | D14: =IF($C$14="OFF",0,Repairs!$E$35) -> 0 | G14: =IF($C$14="OFF",D14,Repairs!$E$35) -> 0 | J14: =IF($C$14="OFF",G14,Repairs!$E$35) -> 0 | M14: =IF($C$14="OFF",J14,Repairs!$E$35) -> 0 | P14: =IF($C$14="OFF",M14,Repairs!$E$35) -> 0 | S14: =IF($C$14="OFF",P14,Repairs!$E$35) -> 0 | V14: =IF($C$14="OFF",S14,Repairs!$E$35) -> 0 | Y14: =IF($C$14="OFF",V14,Repairs!$E$35) -> 0 | AC14: Unit type | AD14: 0 | AE14: 0 | AF14: =AE14*AD14 -> 0 | AG14: 0 | AH14: =AG14*AD14 -> 0
B15: Operating Reserves | D15: 0 | G15: =D15 -> 0 | J15: =G15 -> 0 | M15: =J15 -> 0 | P15: =M15 -> 0 | S15: =P15 -> 0 | V15: =S15 -> 0 | Y15: =V15 -> 0 | AC15: Total / Average | AD15: =SUM(AD8:AD14) -> 0 | AE15: =IF(AD15>0,AF15/AD15,0) -> 0 | AF15: =SUM(AF8:AF14) -> 0 | AG15: =IF(AD15>0,AH15/AD15,0) -> 0 | AH15: =SUM(AH8:AH14) -> 0
B16: Estimated closing costs | D16: =Summary!$D$18 -> 0 | G16: =Summary!$D$18 -> 0 | J16: =Summary!$D$18 -> 0 | M16: =Summary!$D$18 -> 0 | P16: =Summary!$D$18 -> 0 | S16: =Summary!$D$18 -> 0 | V16: =Summary!$D$18 -> 0 | Y16: =Summary!$D$18 -> 0
B17: Total Acquisition Cost | D17: =D14+D7+D16+D15 -> 0 | G17: =G14+G7+G16+G15 -> 0 | J17: =J14+J7+J16+J15 -> 0 | M17: =M14+M7+M16+M15 -> 0 | P17: =P14+P7+P16+P15 -> 0 | S17: =S14+S7+S16+S15 -> 0 | V17: =V14+V7+V16+V15 -> 0 | Y17: =Y14+Y7+Y16+Y15 -> 0
B19: Income
B20: Average Monthly Rent | D20: =IF(D21=0,0,D21/12/D8) -> 0 | G20: =IF(G21=0,0,G21/12/G8) -> 0 | J20: =IF(J21=0,0,J21/12/J8) -> 0 | M20: =IF(M21=0,0,M21/12/M8) -> 0 | P20: =IF(P21=0,0,P21/12/P8) -> 0 | S20: =IF(S21=0,0,S21/12/S8) -> 0 | V20: =IF(V21=0,0,V21/12/V8) -> 0 | Y20: =IF(Y21=0,0,Y21/12/Y8) -> 0
B21: Gross Potential Rent | D21: 0 | G21: =D21 -> 0 | J21: =G21 -> 0 | M21: =J21 -> 0 | P21: =M21 -> 0 | S21: =P21 -> 0 | V21: =S21 -> 0 | Y21: =V21 -> 0 | AB21: =CHOOSE(Summary!$G$3,D21,G21,J21,M21,P21,S21,V21,Y21) -> 0 | AC21: Rules of Thumb
B22: - Vacancy | D22: 0 | F22: =IFERROR(-D22/D21,0) -> 0 | G22: =-I22*G21 -> 0 | I22: 0.1 | J22: =-L22*J21 -> 0 | L22: 0.1 | M22: =-O22*M21 -> 0 | O22: 0.1 | P22: =-R22*P21 -> 0 | R22: 0.1 | S22: =-U22*S21 -> 0 | U22: 0.1 | V22: =-X22*V21 -> 0 | X22: 0.1 | Y22: =-AA22*Y21 -> 0 | AA22: 0.1 | AC22: Sales Price | AD22: =M7 -> 0
B23: - Concessions, Loss to Lease, Bad Debt | D23: 0 | F23: =IFERROR(-D23/D21,0) -> 0 | G23: =-I23*G21 -> 0 | I23: 0.05 | J23: =-L23*J21 -> 0 | L23: 0.05 | M23: =-O23*M21 -> 0 | O23: 0.05 | P23: =-R23*P21 -> 0 | R23: 0.05 | S23: =-U23*S21 -> 0 | U23: 0.05 | V23: =-X23*V21 -> 0 | X23: 0.05 | Y23: =-AA23*Y21 -> 0 | AA23: 0.05 | AC23: # Units | AD23: =M8 -> 0
B24: Gross Potential Income | D24: =D21+D22+D23 -> 0 | G24: =SUM(G21:G23) -> 0 | J24: =SUM(J21:J23) -> 0 | M24: =SUM(M21:M23) -> 0 | P24: =SUM(P21:P23) -> 0 | S24: =SUM(S21:S23) -> 0 | V24: =SUM(V21:V23) -> 0 | Y24: =SUM(Y21:Y23) -> 0 | AC24: Effective Gross Income | AD24: =M26 -> 0
B25: Other Income | D25: 0 | G25: =D25 -> 0 | J25: =G25 -> 0 | M25: =J25 -> 0 | P25: =M25 -> 0 | S25: =P25 -> 0 | V25: =S25 -> 0 | Y25: =V25 -> 0 | AB25: =CHOOSE(Summary!$G$3,D25,G25,J25,M25,P25,S25,V25,Y25) -> 0 | AD25: General Rule of Thumb | AG25: From Appraiser | AI25: Other Properties | AK25: My Rule of Thumb
B26: Effective Gross Income | D26: =D24+D25 -> 0 | G26: =G24+G25 -> 0 | J26: =J24+J25 -> 0 | M26: =M24+M25 -> 0 | P26: =P24+P25 -> 0 | S26: =S24+S25 -> 0 | V26: =V24+V25 -> 0 | Y26: =Y24+Y25 -> 0 | AE26: Per Year | AI26: Property 1 | AJ26: Property 2
AC27: EXPENSES | AD27: Comment | AE27: Per Unit | AF27: Total | AG27: Per Unit | AH27: Total | AI27: Per Unit | AJ27: Per Unit | AK27: Per Year | AL27: Comment
B28: Expenses | E28: Per Unit | H28: Per Unit | K28: Per Unit | N28: Per Unit | Q28: Per Unit | T28: Per Unit | W28: Per Unit | Z28: Per Unit | AC28: Real Estate Taxes | AD28: 1% of Sales Price | AE28: =IFERROR(AF28/$AD$23,0) -> 0 | AF28: =0.01*AD22 -> 0 | AK28: =AF28 -> 0
B29: ='P&L'!B19 -> Advertising | D29: 0 | E29: =IF(D29>0,D29/D$8,0) -> 0 | F29: =IF(D$26=0,0,D29/D$26) -> 0 | G29: =D29 -> 0 | H29: =IF(G29>0,G29/G$8,0) -> 0 | I29: =IF(G$26=0,0,G29/G$26) -> 0 | J29: =G29 -> 0 | K29: =IF(J29>0,J29/J$8,0) -> 0 | L29: =IF(J$26=0,0,J29/J$26) -> 0 | M29: =J29 -> 0 | N29: =IF(M29>0,M29/M$8,0) -> 0 | O29: =IF(M$26=0,0,M29/M$26) -> 0 | P29: =M29 -> 0 | Q29: =IF(P29>0,P29/P$8,0) -> 0 | R29: =IF(P$26=0,0,P29/P$26) -> 0 | S29: =P29 -> 0 | T29: =IF(S29>0,S29/S$8,0) -> 0 | U29: =IF(S$26=0,0,S29/S$26) -> 0 | V29: =S29 -> 0 | W29: =IF(V29>0,V29/V$8,0) -> 0 | X29: =IF(V$26=0,0,V29/V$26) -> 0 | Y29: =V29 -> 0 | Z29: =IF(Y29>0,Y29/Y$8,0) -> 0 | AA29: =IF(Y$26=0,0,Y29/Y$26) -> 0 | AC29: Insurance | AD29: 0.007 of sales price | AE29: 400 | AF29: =0.007*AD22 -> 0 | AG29: 450 | AH29: =AG29*$AD$23 -> 0 | AI29: 267 | AJ29: 332 | AK29: =AF29 -> 0
B30: ='P&L'!B20 -> Contract Services | D30: 0 | E30: =IF(D30>0,D30/D$8,0) -> 0 | F30: =IF($D$26=0,0,D30/D$26) -> 0 | G30: =D30 -> 0 | H30: =IF(G30>0,G30/G$8,0) -> 0 | I30: =IF(G$26=0,0,G30/G$26) -> 0 | J30: =G30 -> 0 | K30: =IF(J30>0,J30/J$8,0) -> 0 | L30: =IF(J$26=0,0,J30/J$26) -> 0 | M30: =J30 -> 0 | N30: =IF(M30>0,M30/M$8,0) -> 0 | O30: =IF(M$26=0,0,M30/M$26) -> 0 | P30: =M30 -> 0 | Q30: =IF(P30>0,P30/P$8,0) -> 0 | R30: =IF(P$26=0,0,P30/P$26) -> 0 | S30: =P30 -> 0 | T30: =IF(S30>0,S30/S$8,0) -> 0 | U30: =IF(S$26=0,0,S30/S$26) -> 0 | V30: =S30 -> 0 | W30: =IF(V30>0,V30/V$8,0) -> 0 | X30: =IF(V$26=0,0,V30/V$26) -> 0 | Y30: =V30 -> 0 | Z30: =IF(Y30>0,Y30/Y$8,0) -> 0 | AA30: =IF(Y$26=0,0,Y30/Y$26) -> 0 | AC30: Contract Services | AD30: $200 per unit per year | AE30: 200 | AF30: =AE30*$AD$23 -> 0 | AK30: =AF30 -> 0
B31: ='P&L'!B21 -> Gas & Electric | D31: 0 | E31: =IF(D31>0,D31/D$8,0) -> 0 | F31: =IF($D$26=0,0,D31/D$26) -> 0 | G31: =D31 -> 0 | H31: =IF(G31>0,G31/G$8,0) -> 0 | I31: =IF(G$26=0,0,G31/G$26) -> 0 | J31: =G31 -> 0 | K31: =IF(J31>0,J31/J$8,0) -> 0 | L31: =IF(J$26=0,0,J31/J$26) -> 0 | M31: =J31 -> 0 | N31: =IF(M31>0,M31/M$8,0) -> 0 | O31: =IF(M$26=0,0,M31/M$26) -> 0 | P31: =M31 -> 0 | Q31: =IF(P31>0,P31/P$8,0) -> 0 | R31: =IF(P$26=0,0,P31/P$26) -> 0 | S31: =P31 -> 0 | T31: =IF(S31>0,S31/S$8,0) -> 0 | U31: =IF(S$26=0,0,S31/S$26) -> 0 | V31: =S31 -> 0 | W31: =IF(V31>0,V31/V$8,0) -> 0 | X31: =IF(V$26=0,0,V31/V$26) -> 0 | Y31: =V31 -> 0 | Z31: =IF(Y31>0,Y31/Y$8,0) -> 0 | AA31: =IF(Y$26=0,0,Y31/Y$26) -> 0 | AC31: Trash Removal | AD31: $200 per unit | AE31: 200 | AF31: =AE31*$AD$23 -> 0 | AG31: 125 | AH31: =AG31*$AD$23 -> 0 | AI31: 229 | AJ31: 199 | AK31: =AF31 -> 0
B32: ='P&L'!B22 -> General/Admin | D32: 0 | E32: =IF(D32>0,D32/D$8,0) -> 0 | F32: =IF($D$26=0,0,D32/D$26) -> 0 | G32: =D32 -> 0 | H32: =IF(G32>0,G32/G$8,0) -> 0 | I32: =IF(G$26=0,0,G32/G$26) -> 0 | J32: =G32 -> 0 | K32: =IF(J32>0,J32/J$8,0) -> 0 | L32: =IF(J$26=0,0,J32/J$26) -> 0 | M32: =J32 -> 0 | N32: =IF(M32>0,M32/M$8,0) -> 0 | O32: =IF(M$26=0,0,M32/M$26) -> 0 | P32: =M32 -> 0 | Q32: =IF(P32>0,P32/P$8,0) -> 0 | R32: =IF(P$26=0,0,P32/P$26) -> 0 | S32: =P32 -> 0 | T32: =IF(S32>0,S32/S$8,0) -> 0 | U32: =IF(S$26=0,0,S32/S$26) -> 0 | V32: =S32 -> 0 | W32: =IF(V32>0,V32/V$8,0) -> 0 | X32: =IF(V$26=0,0,V32/V$26) -> 0 | Y32: =V32 -> 0 | Z32: =IF(Y32>0,Y32/Y$8,0) -> 0 | AA32: =IF(Y$26=0,0,Y32/Y$26) -> 0 | AC32: Electric | AD32: $100/unit for common areas | AE32: 100 | AF32: =AE32*$AD$23 -> 0 | AI32: 100 | AJ32: 111 | AK32: =AF32 -> 0
B33: ='P&L'!B23 -> Insurance | D33: 0 | E33: =IF(D33>0,D33/D$8,0) -> 0 | F33: =IF($D$26=0,0,D33/D$26) -> 0 | G33: =D33 -> 0 | H33: =IF(G33>0,G33/G$8,0) -> 0 | I33: =IF(G$26=0,0,G33/G$26) -> 0 | J33: =G33 -> 0 | K33: =IF(J33>0,J33/J$8,0) -> 0 | L33: =IF(J$26=0,0,J33/J$26) -> 0 | M33: =J33 -> 0 | N33: =IF(M33>0,M33/M$8,0) -> 0 | O33: =IF(M$26=0,0,M33/M$26) -> 0 | P33: =M33 -> 0 | Q33: =IF(P33>0,P33/P$8,0) -> 0 | R33: =IF(P$26=0,0,P33/P$26) -> 0 | S33: =P33 -> 0 | T33: =IF(S33>0,S33/S$8,0) -> 0 | U33: =IF(S$26=0,0,S33/S$26) -> 0 | V33: =S33 -> 0 | W33: =IF(V33>0,V33/V$8,0) -> 0 | X33: =IF(V$26=0,0,V33/V$26) -> 0 | Y33: =V33 -> 0 | Z33: =IF(Y33>0,Y33/Y$8,0) -> 0 | AA33: =IF(Y$26=0,0,Y33/Y$26) -> 0 | AC33: Gas | AD33: If owner pays, $100/unit/month | AE33: 100 | AF33: =AE33*$AD$23*12 -> 0 | AK33: =AF33 -> 0
B34: ='P&L'!B24 -> Legal | D34: 0 | E34: =IF(D34>0,D34/D$8,0) -> 0 | F34: =IF($D$26=0,0,D34/D$26) -> 0 | G34: =D34 -> 0 | H34: =IF(G34>0,G34/G$8,0) -> 0 | I34: =IF(G$26=0,0,G34/G$26) -> 0 | J34: =G34 -> 0 | K34: =IF(J34>0,J34/J$8,0) -> 0 | L34: =IF(J$26=0,0,J34/J$26) -> 0 | M34: =J34 -> 0 | N34: =IF(M34>0,M34/M$8,0) -> 0 | O34: =IF(M$26=0,0,M34/M$26) -> 0 | P34: =M34 -> 0 | Q34: =IF(P34>0,P34/P$8,0) -> 0 | R34: =IF(P$26=0,0,P34/P$26) -> 0 | S34: =P34 -> 0 | T34: =IF(S34>0,S34/S$8,0) -> 0 | U34: =IF(S$26=0,0,S34/S$26) -> 0 | V34: =S34 -> 0 | W34: =IF(V34>0,V34/V$8,0) -> 0 | X34: =IF(V$26=0,0,V34/V$26) -> 0 | Y34: =V34 -> 0 | Z34: =IF(Y34>0,Y34/Y$8,0) -> 0 | AA34: =IF(Y$26=0,0,Y34/Y$26) -> 0 | AC34: Water and Sewer | AD34: $400/unit | AE34: 400 | AF34: =AE34*$AD$23 -> 0 | AG34: 500 | AH34: =AG34*$AD$23 -> 0 | AI34: 500 | AJ34: 607 | AK34: =AF34 -> 0
B35: ='P&L'!B25 -> Real Estate Taxes | D35: 0 | E35: =IF(D35>0,D35/D$8,0) -> 0 | F35: =IF($D$26=0,0,D35/D$26) -> 0 | G35: =D35 -> 0 | H35: =IF(G35>0,G35/G$8,0) -> 0 | I35: =IF(G$26=0,0,G35/G$26) -> 0 | J35: =G35 -> 0 | K35: =IF(J35>0,J35/J$8,0) -> 0 | L35: =IF(J$26=0,0,J35/J$26) -> 0 | M35: =J35 -> 0 | N35: =IF(M35>0,M35/M$8,0) -> 0 | O35: =IF(M$26=0,0,M35/M$26) -> 0 | P35: =M35 -> 0 | Q35: =IF(P35>0,P35/P$8,0) -> 0 | R35: =IF(P$26=0,0,P35/P$26) -> 0 | S35: =P35 -> 0 | T35: =IF(S35>0,S35/S$8,0) -> 0 | U35: =IF(S$26=0,0,S35/S$26) -> 0 | V35: =S35 -> 0 | W35: =IF(V35>0,V35/V$8,0) -> 0 | X35: =IF(V$26=0,0,V35/V$26) -> 0 | Y35: =V35 -> 0 | Z35: =IF(Y35>0,Y35/Y$8,0) -> 0 | AA35: =IF(Y$26=0,0,Y35/Y$26) -> 0 | AC35: Legal Fees | AD35: $150 per unit | AE35: =IFERROR(AF35/$AD$23,0) -> 0 | AF35: =150*AD23 -> 0 | AG35: 150 | AH35: =AG35*$AD$23 -> 0 | AK35: =AF35 -> 0
B36: ='P&L'!B26 -> Trash Removal | D36: 0 | E36: =IF(D36>0,D36/D$8,0) -> 0 | F36: =IF($D$26=0,0,D36/D$26) -> 0 | G36: =D36 -> 0 | H36: =IF(G36>0,G36/G$8,0) -> 0 | I36: =IF(G$26=0,0,G36/G$26) -> 0 | J36: =G36 -> 0 | K36: =IF(J36>0,J36/J$8,0) -> 0 | L36: =IF(J$26=0,0,J36/J$26) -> 0 | M36: =J36 -> 0 | N36: =IF(M36>0,M36/M$8,0) -> 0 | O36: =IF(M$26=0,0,M36/M$26) -> 0 | P36: =M36 -> 0 | Q36: =IF(P36>0,P36/P$8,0) -> 0 | R36: =IF(P$26=0,0,P36/P$26) -> 0 | S36: =P36 -> 0 | T36: =IF(S36>0,S36/S$8,0) -> 0 | U36: =IF(S$26=0,0,S36/S$26) -> 0 | V36: =S36 -> 0 | W36: =IF(V36>0,V36/V$8,0) -> 0 | X36: =IF(V$26=0,0,V36/V$26) -> 0 | Y36: =V36 -> 0 | Z36: =IF(Y36>0,Y36/Y$8,0) -> 0 | AA36: =IF(Y$26=0,0,Y36/Y$26) -> 0 | AC36: Management Fees | AD36: 5-10% of Gross Income | AG36: 0.06 | AK36: =AF36 -> 0
B37: ='P&L'!B27 -> Management Fee | D37: 0 | E37: =IF(D37>0,D37/D$8,0) -> 0 | F37: =IF($D$26=0,0,D37/D$26) -> 0 | G37: =I37*G26 -> 0 | H37: =IF(G37>0,G37/G$8,0) -> 0 | I37: 0 | J37: =L37*J26 -> 0 | K37: =IF(J37>0,J37/J$8,0) -> 0 | L37: =I37 -> 0 | M37: =O37*M26 -> 0 | N37: =IF(M37>0,M37/M$8,0) -> 0 | O37: =L37 -> 0 | P37: =R37*P26 -> 0 | Q37: =IF(P37>0,P37/P$8,0) -> 0 | R37: =O37 -> 0 | S37: =U37*S26 -> 0 | T37: =IF(S37>0,S37/S$8,0) -> 0 | U37: =R37 -> 0 | V37: =X37*V26 -> 0 | W37: =IF(V37>0,V37/V$8,0) -> 0 | X37: =U37 -> 0 | Y37: =AA37*Y26 -> 0 | Z37: =IF(Y37>0,Y37/Y$8,0) -> 0 | AA37: =X37 -> 0 | AC37: Repairs and Maintenance | AD37: 10% of Gross Income | AF37: =0.1*AD24 -> 0 | AG37: 1000 | AH37: =AG37*$AD$23 -> 0 | AK37: =AF37 -> 0
B38: ='P&L'!B28 -> Payroll | D38: 0 | E38: =IF(D38>0,D38/D$8,0) -> 0 | F38: =IF($D$26=0,0,D38/D$26) -> 0 | G38: =D38 -> 0 | H38: =IF(G38>0,G38/G$8,0) -> 0 | I38: =IF(G$26=0,0,G38/G$26) -> 0 | J38: =G38 -> 0 | K38: =IF(J38>0,J38/J$8,0) -> 0 | L38: =IF(J$26=0,0,J38/J$26) -> 0 | M38: =J38 -> 0 | N38: =IF(M38>0,M38/M$8,0) -> 0 | O38: =IF(M$26=0,0,M38/M$26) -> 0 | P38: =M38 -> 0 | Q38: =IF(P38>0,P38/P$8,0) -> 0 | R38: =IF(P$26=0,0,P38/P$26) -> 0 | S38: =P38 -> 0 | T38: =IF(S38>0,S38/S$8,0) -> 0 | U38: =IF(S$26=0,0,S38/S$26) -> 0 | V38: =S38 -> 0 | W38: =IF(V38>0,V38/V$8,0) -> 0 | X38: =IF(V$26=0,0,V38/V$26) -> 0 | Y38: =V38 -> 0 | Z38: =IF(Y38>0,Y38/Y$8,0) -> 0 | AA38: =IF(Y$26=0,0,Y38/Y$26) -> 0 | AC38: Advertising | AD38: Varies | AK38: 1700
B39: ='P&L'!B29 -> Repairs and Maintenance | D39: 0 | E39: =IF(D39>0,D39/D$8,0) -> 0 | F39: =IF($D$26=0,0,D39/D$26) -> 0 | G39: =D39 -> 0 | H39: =IF(G39>0,G39/G$8,0) -> 0 | I39: =IF(G$26=0,0,G39/G$26) -> 0 | J39: =G39 -> 0 | K39: =IF(J39>0,J39/J$8,0) -> 0 | L39: =IF(J$26=0,0,J39/J$26) -> 0 | M39: =J39 -> 0 | N39: =IF(M39>0,M39/M$8,0) -> 0 | O39: =IF(M$26=0,0,M39/M$26) -> 0 | P39: =M39 -> 0 | Q39: =IF(P39>0,P39/P$8,0) -> 0 | R39: =IF(P$26=0,0,P39/P$26) -> 0 | S39: =P39 -> 0 | T39: =IF(S39>0,S39/S$8,0) -> 0 | U39: =IF(S$26=0,0,S39/S$26) -> 0 | V39: =S39 -> 0 | W39: =IF(V39>0,V39/V$8,0) -> 0 | X39: =IF(V$26=0,0,V39/V$26) -> 0 | Y39: =V39 -> 0 | Z39: =IF(Y39>0,Y39/Y$8,0) -> 0 | AA39: =IF(Y$26=0,0,Y39/Y$26) -> 0 | AC39: General/Admin | AD39: Varies | AK39: 1700
B40: ='P&L'!B30 -> Turnover | D40: 0 | E40: =IF(D40>0,D40/D$8,0) -> 0 | F40: =IF($D$26=0,0,D40/D$26) -> 0 | G40: =D40 -> 0 | H40: =IF(G40>0,G40/G$8,0) -> 0 | I40: =IF(G$26=0,0,G40/G$26) -> 0 | J40: =G40 -> 0 | K40: =IF(J40>0,J40/J$8,0) -> 0 | L40: =IF(J$26=0,0,J40/J$26) -> 0 | M40: =J40 -> 0 | N40: =IF(M40>0,M40/M$8,0) -> 0 | O40: =IF(M$26=0,0,M40/M$26) -> 0 | P40: =M40 -> 0 | Q40: =IF(P40>0,P40/P$8,0) -> 0 | R40: =IF(P$26=0,0,P40/P$26) -> 0 | S40: =P40 -> 0 | T40: =IF(S40>0,S40/S$8,0) -> 0 | U40: =IF(S$26=0,0,S40/S$26) -> 0 | V40: =S40 -> 0 | W40: =IF(V40>0,V40/V$8,0) -> 0 | X40: =IF(V$26=0,0,V40/V$26) -> 0 | Y40: =V40 -> 0 | Z40: =IF(Y40>0,Y40/Y$8,0) -> 0 | AA40: =IF(Y$26=0,0,Y40/Y$26) -> 0 | AC40: Payroll | AD40: For every 100 units: 1 FT leasing manager and 1 FT maintenance person; confirm with property manager. | AK40: =AF40 -> 0
B41: ='P&L'!B31 -> Water and Sewer | D41: 0 | E41: =IF(D41>0,D41/D$8,0) -> 0 | F41: =IF($D$26=0,0,D41/D$26) -> 0 | G41: =D41 -> 0 | H41: =IF(G41>0,G41/G$8,0) -> 0 | I41: =IF(G$26=0,0,G41/G$26) -> 0 | J41: =G41 -> 0 | K41: =IF(J41>0,J41/J$8,0) -> 0 | L41: =IF(J$26=0,0,J41/J$26) -> 0 | M41: =J41 -> 0 | N41: =IF(M41>0,M41/M$8,0) -> 0 | O41: =IF(M$26=0,0,M41/M$26) -> 0 | P41: =M41 -> 0 | Q41: =IF(P41>0,P41/P$8,0) -> 0 | R41: =IF(P$26=0,0,P41/P$26) -> 0 | S41: =P41 -> 0 | T41: =IF(S41>0,S41/S$8,0) -> 0 | U41: =IF(S$26=0,0,S41/S$26) -> 0 | V41: =S41 -> 0 | W41: =IF(V41>0,V41/V$8,0) -> 0 | X41: =IF(V$26=0,0,V41/V$26) -> 0 | Y41: =V41 -> 0 | Z41: =IF(Y41>0,Y41/Y$8,0) -> 0 | AA41: =IF(Y$26=0,0,Y41/Y$26) -> 0 | AC41: Turnover | AK41: =AF41 -> 0
B42: ='P&L'!B32 -> Deposit to Replacement Reserve | D42: =IF(SUM(D29:D41)=0,0,D8*AE42) -> 0 | E42: =IF(D42>0,D42/D$8,0) -> 0 | F42: =IF($D$26=0,0,D42/D$26) -> 0 | G42: =D42 -> 0 | H42: =IF(G42>0,G42/G$8,0) -> 0 | I42: =IF(G$26=0,0,G42/G$26) -> 0 | J42: =G42 -> 0 | K42: =IF(J42>0,J42/J$8,0) -> 0 | L42: =IF(J$26=0,0,J42/J$26) -> 0 | M42: =J42 -> 0 | N42: =IF(M42>0,M42/M$8,0) -> 0 | O42: =IF(M$26=0,0,M42/M$26) -> 0 | P42: =M42 -> 0 | Q42: =IF(P42>0,P42/P$8,0) -> 0 | R42: =IF(P$26=0,0,P42/P$26) -> 0 | S42: =P42 -> 0 | T42: =IF(S42>0,S42/S$8,0) -> 0 | U42: =IF(S$26=0,0,S42/S$26) -> 0 | V42: =S42 -> 0 | W42: =IF(V42>0,V42/V$8,0) -> 0 | X42: =IF(V$26=0,0,V42/V$26) -> 0 | Y42: =V42 -> 0 | Z42: =IF(Y42>0,Y42/Y$8,0) -> 0 | AA42: =IF(Y$26=0,0,Y42/Y$26) -> 0 | AC42: Replacement Reserves | AD42: $250 per unit | AE42: 250 | AF42: =AE42*$AD$23 -> 0 | AG42: 250 | AH42: =AG42*$AD$23 -> 0 | AK42: =AF42 -> 0
B43: Total Expenses (Added) | D43: =SUM(D29:D42) -> 0 | E43: =SUM(E29:E42) -> 0 | F43: =IF($D$26=0,0,D43/D26) -> 0 | G43: =SUM(G29:G42) -> 0 | H43: =SUM(H29:H42) -> 0 | I43: =IF(G$26=0,0,G43/G26) -> 0 | J43: =SUM(J29:J42) -> 0 | K43: =SUM(K29:K42) -> 0 | L43: =IF(J$26=0,0,J43/J26) -> 0 | M43: =SUM(M29:M42) -> 0 | N43: =SUM(N29:N42) -> 0 | O43: =IF(M$26=0,0,M43/M26) -> 0 | P43: =SUM(P29:P42) -> 0 | Q43: =SUM(Q29:Q42) -> 0 | R43: =IF(P$26=0,0,P43/P26) -> 0 | S43: =SUM(S29:S42) -> 0 | T43: =SUM(T29:T42) -> 0 | U43: =IF(S$26=0,0,S43/S26) -> 0 | V43: =SUM(V29:V42) -> 0 | W43: =SUM(W29:W42) -> 0 | X43: =IF(V$26=0,0,V43/V26) -> 0 | Y43: =SUM(Y29:Y42) -> 0 | Z43: =SUM(Z29:Z42) -> 0 | AA43: =IF(Y$26=0,0,Y43/Y26) -> 0
B45: Total Expenses (Manual Override) | D45: 0 | F45: =IF(D45=0,0%,D45/D26) -> 0 | G45: =IF(G43>0,G43,I45*G26) -> 0 | I45: =IF(G43=0,50%,G45/G26) -> 0.5 | J45: =IF(J43>0,J43,L45*J26) -> 0 | L45: =IF(J43=0,50%,J45/J26) -> 0.5 | M45: =IF(M43>0,M43,O45*M26) -> 0 | O45: =IF(M43=0,50%,M45/M26) -> 0.5 | P45: =IF(P43>0,P43,R45*P26) -> 0 | R45: =IF(P43=0,50%,P45/P26) -> 0.5 | S45: =IF(S43>0,S43,U45*S26) -> 0 | U45: =IF(S43=0,50%,S45/S26) -> 0.5 | V45: =IF(V43>0,V43,X45*V26) -> 0 | X45: =IF(V43=0,50%,V45/V26) -> 0.5 | Y45: =IF(Y43>0,Y43,AA45*Y26) -> 0 | AA45: =IF(Y43=0,50%,Y45/Y26) -> 0.5
B46: To Manually Override the Expenses to use %, the dollar summary must be $0 on line 43
B47: Total Expenses | D47: =IF(D45>0,D45,D43) -> 0 | F47: =IF(D26=0,0,D47/D26) -> 0 | G47: =IF(G45>0,G45,G43) -> 0 | I47: =IF(G26=0,0,G47/G26) -> 0 | J47: =IF(J45>0,J45,J43) -> 0 | L47: =IF(J26=0,0,J47/J26) -> 0 | M47: =IF(M45>0,M45,M43) -> 0 | O47: =IF(M26=0,0,M47/M26) -> 0 | P47: =IF(P45>0,P45,P43) -> 0 | R47: =IF(P26=0,0,P47/P26) -> 0 | S47: =IF(S45>0,S45,S43) -> 0 | U47: =IF(S26=0,0,S47/S26) -> 0 | V47: =IF(V45>0,V45,V43) -> 0 | X47: =IF(V26=0,0,V47/V26) -> 0 | Y47: =IF(Y45>0,Y45,Y43) -> 0 | AA47: =IF(Y26=0,0,Y47/Y26) -> 0 | AB47: =CHOOSE(Summary!$G$3,D47,G47,J47,M47,P47,S47,V47,Y47) -> 0
B49: Net Operating Income (NOI) | D49: =D26-D47 -> 0 | G49: =G26-G47 -> 0 | J49: =J26-J47 -> 0 | M49: =M26-M47 -> 0 | P49: =P26-P47 -> 0 | S49: =S26-S47 -> 0 | V49: =V26-V47 -> 0 | Y49: =Y26-Y47 -> 0
B51: Summary
B52: Debt Service | D52: =IF(D12>0,D53*D13,PMT(D53/12,D54*12,-D13)*12) -> 0 | G52: =IF(G12>0,G53*G13,PMT(G53/12,G54*12,-G13)*12) -> 0 | J52: =IF(J12>0,J53*J13,PMT(J53/12,J54*12,-J13)*12) -> 0 | M52: =IF(M12>0,M53*M13,PMT(M53/12,M54*12,-M13)*12) -> 0 | P52: =IF(P12>0,P53*P13,PMT(P53/12,P54*12,-P13)*12) -> 0 | S52: =IF(S12>0,S53*S13,PMT(S53/12,S54*12,-S13)*12) -> 0 | V52: =IF(V12>0,V53*V13,PMT(V53/12,V54*12,-V13)*12) -> 0 | Y52: =IF(Y12>0,Y53*Y13,PMT(Y53/12,Y54*12,-Y13)*12) -> 0
B53: Interest Rate | D53: 0.05 | G53: =D53 -> 0.05 | J53: =G53 -> 0.05 | M53: =J53 -> 0.05 | P53: =M53 -> 0.05 | S53: =P53 -> 0.05 | V53: =S53 -> 0.05 | Y53: =V53 -> 0.05
B54: Amortization (Years) | D54: 30 | G54: =D54 -> 30 | J54: =G54 -> 30 | M54: =J54 -> 30 | P54: =M54 -> 30 | S54: =P54 -> 30 | V54: =S54 -> 30 | Y54: =V54 -> 30
B55: Cash flow after debt service | D55: =D49-D52 -> 0 | G55: =G49-G52 -> 0 | J55: =J49-J52 -> 0 | M55: =M49-M52 -> 0 | P55: =P49-P52 -> 0 | S55: =S49-S52 -> 0 | V55: =V49-V52 -> 0 | Y55: =Y49-Y52 -> 0
B56: Cap Rate (NOI/Sales Price) | D56: =IF(D7=0,0,D49/D7) -> 0 | G56: =IF(G7=0,0,G49/G7) -> 0 | J56: =IF(J7=0,0,J49/J7) -> 0 | M56: =IF(M7=0,0,M49/M7) -> 0 | P56: =IF(P7=0,0,P49/P7) -> 0 | S56: =IF(S7=0,0,S49/S7) -> 0 | V56: =IF(V7=0,0,V49/V7) -> 0 | Y56: =IF(Y7=0,0,Y49/Y7) -> 0
B57: Debt Coverage Ratio | D57: =IF(D52=0,0,D49/D52) -> 0 | G57: =IF(G52=0,0,G49/G52) -> 0 | J57: =IF(J52=0,0,J49/J52) -> 0 | M57: =IF(M52=0,0,M49/M52) -> 0 | P57: =IF(P52=0,0,P49/P52) -> 0 | S57: =IF(S52=0,0,S49/S52) -> 0 | V57: =IF(V52=0,0,V49/V52) -> 0 | Y57: =IF(Y52=0,0,Y49/Y52) -> 0
B59: Market Cap Rate And Value
B60: Market Cap Rate | D60: 0.07 | G60: 0.07 | J60: =G60 -> 0.07 | M60: =J60 -> 0.07 | P60: =M60 -> 0.07 | S60: =P60 -> 0.07 | V60: =S60 -> 0.07 | Y60: =V60 -> 0.07
B61: Fair Market Value (Based on NOI) | D61: =D49/D60 -> 0 | G61: =G49/G60 -> 0 | J61: =J49/J60 -> 0 | M61: =M49/M60 -> 0 | P61: =P49/P60 -> 0 | S61: =S49/S60 -> 0 | V61: =V49/V60 -> 0 | Y61: =Y49/Y60 -> 0
B63: =copyright -> Copyright © 2026 Michael Blank.
B64: The information herein is not guaranteed but believed to be accurate.

Sheet Summary
B1: Executive Summary
B3: PURCHASE | F3: Populate with scenario # | G3: 1 | I3: 1. Marketing Package
B4: # Units | D4: =CHOOSE(Summary!$G$3,Scenarios!D8,Scenarios!G8,Scenarios!J8,Scenarios!M8,Scenarios!P8,Scenarios!S8,Scenarios!V8,Scenarios!Y8) -> 0 | I4: 2. My Version
B5: Asking Price | D5: =CHOOSE(Summary!$G$3,Scenarios!D6,Scenarios!G6,Scenarios!J6,Scenarios!M6,Scenarios!P6,Scenarios!S6,Scenarios!V6,Scenarios!Y6) -> 0 | I5: 3. Projected
B6: Purchase Price | D6: =CHOOSE(Summary!$G$3,Scenarios!D7,Scenarios!G7,Scenarios!J7,Scenarios!M7,Scenarios!P7,Scenarios!S7,Scenarios!V7,Scenarios!Y7) -> 0 | I6: 4. Offer
B7: Price Per Unit | D7: =IF(D4=0,0,D6/D4) -> 0
B8: Earnest Money Deposit (EMD) | C8: 0.01 | D8: =D6*C8 -> 0
B9: Down Payment | C9: =CHOOSE(Summary!$G$3,Scenarios!D10,Scenarios!G10,Scenarios!J10,Scenarios!M10,Scenarios!P10,Scenarios!S10,Scenarios!V10,Scenarios!Y10) -> 0.25 | D9: =IF(D5=0,0,(IF(Loans!C3="Yes",(SUM(Loans!C7:C9)-Loans!E10),(D6*C9)))) -> 0
B10: 1st Mortgage (for LTC, see "Loans" sheet) | D10: =IF(D5=0,0,(IF(Loans!C3="Yes",Loans!E10,D6-D9))) -> 0 | F10: =About!E14
B11: Interest Rate | D11: =CHOOSE(Summary!$G$3,Scenarios!D53,Scenarios!G53,Scenarios!J53,Scenarios!M53,Scenarios!P53,Scenarios!S53,Scenarios!V53,Scenarios!Y53) -> 0.05
B12: Amortization | D12: =CHOOSE(Summary!$G$3,Scenarios!D54,Scenarios!G54,Scenarios!J54,Scenarios!M54,Scenarios!P54,Scenarios!S54,Scenarios!V54,Scenarios!Y54) -> 30
B13: Interest Only (in months) | D13: =CHOOSE(Summary!$G$3,Scenarios!D12,Scenarios!G12,Scenarios!J12,Scenarios!M12,Scenarios!P12,Scenarios!S12,Scenarios!V12,Scenarios!Y12) -> 0
B14: 2nd Mortgage (or Capital Improvement Funding) | D14: 0
B15: Interest Rate | D15: =IF(D14>0,D11,0) -> 0
B16: Amortization | D16: =IF(D14>0,D12,0) -> 0
B17: Interest Only (in months) | D17: 0
B18: Closing Costs | C18: =IF(D6=0,0,D18/D6) -> 0 | D18: =IF(D6=0,0,'Acquisition Costs'!D51) -> 0
B19: Acquisition Fee | C19: 0.02 | D19: =C19*D6 -> 0
B20: Repairs | D20: =CHOOSE(Summary!$G$3,Scenarios!D14,Scenarios!G14,Scenarios!J14,Scenarios!M14,Scenarios!P14,Scenarios!S14,Scenarios!V14,Scenarios!Y14) -> 0
B21: Operating Reserves | D21: =CHOOSE(Summary!$G$3,Scenarios!D15,Scenarios!G15,Scenarios!J15,Scenarios!M15,Scenarios!P15,Scenarios!S15,Scenarios!V15,Scenarios!Y15) -> 0 | F21: =About!E12
B22: Total Member Capital Needed to Close | D22: =IF(D5=0,0,(IF(Loans!C3="No",D18+D9+D20+D19+D21-D14,Loans!E16+D19+D21))) -> 0
B23: Current Market Cap Rate | D23: =CHOOSE(Summary!$G$3,Scenarios!D60,Scenarios!G60,Scenarios!J60,Scenarios!M60,Scenarios!P60,Scenarios!S60,Scenarios!V60,Scenarios!Y60) -> 0.07
B24: INCOME & EXPENSES (Year 1)
B25: Gross Scheduled Income | D25: ='P&L'!D11 -> 0
B26: Average Monthly Rent | D26: ='P&L'!D10 -> 0
B27: - Vacancy | C27: =CHOOSE(Summary!$G$3,Scenarios!F22,Scenarios!I22,Scenarios!L22,Scenarios!O22,Scenarios!R22,Scenarios!U22,Scenarios!X22,Scenarios!AA22) -> 0 | D27: ='P&L'!D12 -> 0
B28: - Concessions, Loss to Lease, Bad Debt | C28: =CHOOSE(Summary!$G$3,Scenarios!F23,Scenarios!I23,Scenarios!L23,Scenarios!O23,Scenarios!R23,Scenarios!U23,Scenarios!X23,Scenarios!AA23) -> 0 | D28: ='P&L'!D13 -> 0
B29: = Effective Rental Income | D29: ='P&L'!D14 -> 0
B30: + Other Income | D30: ='P&L'!D15 -> 0
B31: Total Net Income | D31: ='P&L'!D16 -> 0
B32: Expenses | C32: ='P&L'!E33 -> 0 | D32: ='P&L'!D33 -> 0 | F32: =About!E8
B33: Net Operating Income | D33: ='P&L'!D35 -> 0
B34: Debt Service | D34: ='P&L'!D40 -> 0
B35: Cash Flow After Debt Service | D35: =D33-D34 -> 0
B36: KEY INDICATORS
B37: Cash-on-Cash Return | D37: =Returns!N18 -> 0 | F37: =About!E10
B38: Debt Coverage Ratio (Year 1) | D38: =IF(D6=0,0,'P&L'!D62) -> 0 | F38: =About!E5
B39: Gross Rent Multiplier | D39: =IF(D25=0,0,D6/D25) -> 0
B40: INVESTOR RETURNS
B41: Member Equity | D41: 0.8
B42: Manager Equity | D42: =1-D41 -> 0.2
B43: Preferred Return to Members | D43: 0
B44: Asset Management Fee | D44: 0
B45: Capital Transaction Fee to Mgr | D45: 0
B46: Cash Flow to Members (Year 1) | D46: ='P&L'!D51 -> 0
B47: Member Cash-on-Cash Return (Year 1) | D47: =IF(D6=0,0,D46/D22) -> 0
B48: Average Annual Return | D48: =Returns!N16 -> 0 | F48: =About!E6
B49: Total Return on Investment | D49: =Returns!N15 -> 0
B50: IRR | D50: =Returns!N17 -> 0 | F50: =About!E7
B51: Equity Multiple | D51: =Returns!N19 -> 0
B53: =copyright -> Copyright © 2026 Michael Blank.
B54: The information herein is not guaranteed but believed to be accurate.

Sheet Acquisition Costs
B1: Acquisition Costs
B3: Use of Capital
B4: Purchase Price | D4: =Summary!D6 -> 0
B5: Less Loan Amount | D5: =Summary!D10+Summary!D14 -> 0
B6: Down Payment | D6: =Summary!D9 -> 0
B7: Closing Costs (see below) | D7: =D51 -> 0
B8: Acquisition Fee | D8: =Summary!D19 -> 0
B9: Repairs | D9: =Summary!D20 -> 0
B10: Cash Requirements at Closing / Members Capital | D10: =IF(Loans!C3="No",SUM(D6:D9),Summary!D22) -> 0
B12: Closing Costs and Reimbursable Expenses
B13: Legal Fees (LLC, PPM)* | D13: 0
B14: Property Inspection* | C14: 0 | D14: =C14*Summary!D4 -> 0
B15: Lead Paint Inspection* | C15: 0 | D15: =C15*Summary!D4 -> 0
B17: Lender Fees and 3rd Party Reports
B18: EDR (Environmental) | D18: 0
B19: Appraisal* | D19: 0
B20: Structural Inspection | D20: 0
B21: Lender Legal Fees | D21: 0
B22: Bank Doc Prep Fee | D22: 0
B23: 1st Mortgage Origination Fee | C23: 0 | D23: =C23*Summary!D10 -> 0
B24: 2nd Mortgage Origination Fee | C24: 0 | D24: =C24*Summary!D14 -> 0
B25: Total Lender Fees and Reports | D25: =SUM(D18:D23)+D24 -> 0
B27: Closing Costs
B28: Title Policy | C28: 0 | D28: =C28*D4 -> 0
B29: Survey | D29: 0
B30: Recording | D30: 0
B31: Transfer Taxes | C31: 0 | D31: =C31*D4 -> 0
B32: Title Processing Fee | D32: 0
B33: Title Search | D33: 0
B34: Attorney Fees | D34: 0
B35: Total Closing Costs | D35: =SUM(D28:D34) -> 0
B37: Escrowed at Closing
B38: Lender-held funds | D38: 0
B39: Real Estate Taxes (1) | D39: 0
B40: Insurance | D40: 0
B41: Principal/Interest Escrow
B42: Number of months withheld | C42: 0
B43: Set year-end of P&I escrow return | C43: 0
B44: Total P/I amount (monthly pmnt * months) | D44: ='1st Mortgage 1'!$D$7*$C$42 -> 0
B45: Total Escrows | D45: =SUM(D38:D44) -> 0
B47: Other Costs
B48: Travel (2) | D48: 0
B49: Total Other Costs | D49: =SUM(D48) -> 0
B51: Total Closing and Other Costs | D51: =SUM(D13:D15)+D25+D35+D45+D49 -> 0
B54: Notes:
B55: 1. Click to lookup the Transfer Taxes.
B56: 2. All or part of this expense is typically payable before closing
B59: =copyright -> Copyright © 2026 Michael Blank.
B60: The information herein is not guaranteed but believed to be accurate.

Sheet P&L
B1: Profit & Loss
B5: FINANCIAL ASSUMPTIONS | D5: Year 1 | F5: Year 2 | H5: Year 3 | J5: Year 4 | L5: Year 5 | N5: Year 6 | P5: Year 7 | R5: Year 8 | T5: Year 9 | V5: Year 10
B6: Annual Income Escalator | D6: 0 | F6: 0.02 | H6: =F6 -> 0.02 | J6: =H6 -> 0.02 | L6: =J6 -> 0.02 | N6: =L6 -> 0.02 | P6: =N6 -> 0.02 | R6: =P6 -> 0.02 | T6: =R6 -> 0.02 | V6: =T6 -> 0.02
B7: Annual Expense Escalator | D7: 0 | F7: 0.02 | H7: =F7 -> 0.02 | J7: =H7 -> 0.02 | L7: =J7 -> 0.02 | N7: =L7 -> 0.02 | P7: =N7 -> 0.02 | R7: =P7 -> 0.02 | T7: =R7 -> 0.02 | V7: =T7 -> 0.02
D8: =IF(D9=year_refi,"REFINANCE!",IF(D9=year_sale,"SALE!","")) | F8: =IF(F9=year_refi,"REFINANCE!",IF(F9=year_sale,"SALE!","")) | H8: =IF(H9=year_refi,"REFINANCE!",IF(H9=year_sale,"SALE!","")) | J8: =IF(J9=year_refi,"REFINANCE!",IF(J9=year_sale,"SALE!","")) | L8: =IF(L9=year_refi,"REFINANCE!",IF(L9=year_sale,"SALE!","")) -> SALE! | N8: =IF(N9=year_refi,"REFINANCE!",IF(N9=year_sale,"SALE!","")) | P8: =IF(P9=year_refi,"REFINANCE!",IF(P9=year_sale,"SALE!","")) | R8: =IF(R9=year_refi,"REFINANCE!",IF(R9=year_sale,"SALE!","")) | T8: =IF(T9=year_refi,"REFINANCE!",IF(T9=year_sale,"SALE!","")) | V8: =IF(V9=year_refi,"REFINANCE!",IF(V9=year_sale,"SALE!",""))
B9: INCOME | D9: 1 | F9: =D9+1 -> 2 | H9: =F9+1 -> 3 | J9: =H9+1 -> 4 | L9: =J9+1 -> 5 | N9: =L9+1 -> 6 | P9: =N9+1 -> 7 | R9: =P9+1 -> 8 | T9: =R9+1 -> 9 | V9: =T9+1 -> 10
C10: Average Monthly Rent | D10: =IF(Summary!$D$4=0,0,Scenarios!AB21/Summary!$D$4/12)*(1+D6) -> 0 | F10: =D10*(1+F6) -> 0 | H10: =F10*(1+H6) -> 0 | J10: =H10*(1+J6) -> 0 | L10: =J10*(1+L6) -> 0 | N10: =L10*(1+N6) -> 0 | P10: =N10*(1+P6) -> 0 | R10: =P10*(1+R6) -> 0 | T10: =R10*(1+T6) -> 0 | V10: =T10*(1+V6) -> 0
B11: Gross Potential Rent | D11: =D10*Summary!$D$4*12 -> 0 | F11: =F10*Summary!$D$4*12 -> 0 | H11: =H10*Summary!$D$4*12 -> 0 | J11: =J10*Summary!$D$4*12 -> 0 | L11: =L10*Summary!$D$4*12 -> 0 | N11: =N10*Summary!$D$4*12 -> 0 | P11: =P10*Summary!$D$4*12 -> 0 | R11: =R10*Summary!$D$4*12 -> 0 | T11: =T10*Summary!$D$4*12 -> 0 | V11: =V10*Summary!$D$4*12 -> 0
B12: - Vacancy | D12: =-E12*D11 -> 0 | E12: =Summary!C27 -> 0 | F12: =-G12*F11 -> 0 | G12: =E12 -> 0 | H12: =-I12*H11 -> 0 | I12: =G12 -> 0 | J12: =-K12*J11 -> 0 | K12: =I12 -> 0 | L12: =-M12*L11 -> 0 | M12: =K12 -> 0 | N12: =-O12*N11 -> 0 | O12: =M12 -> 0 | P12: =-Q12*P11 -> 0 | Q12: =O12 -> 0 | R12: =-S12*R11 -> 0 | S12: =Q12 -> 0 | T12: =-U12*T11 -> 0 | U12: =S12 -> 0 | V12: =-W12*V11 -> 0 | W12: =U12 -> 0
B13: - Concessions, Loss to Lease, Bad Debt | D13: =-E13*D11 -> 0 | E13: =Summary!C28 -> 0 | F13: =-G13*F11 -> 0 | G13: =E13 -> 0 | H13: =-I13*H11 -> 0 | I13: =G13 -> 0 | J13: =-K13*J11 -> 0 | K13: =I13 -> 0 | L13: =-M13*L11 -> 0 | M13: =K13 -> 0 | N13: =-O13*N11 -> 0 | O13: =M13 -> 0 | P13: =-Q13*P11 -> 0 | Q13: =O13 -> 0 | R13: =-S13*R11 -> 0 | S13: =Q13 -> 0 | T13: =-U13*T11 -> 0 | U13: =S13 -> 0 | V13: =-W13*V11 -> 0 | W13: =U13 -> 0
B14: Gross Potential Income | D14: =SUM(D11:D13) -> 0 | F14: =SUM(F11:F13) -> 0 | H14: =SUM(H11:H13) -> 0 | J14: =SUM(J11:J13) -> 0 | L14: =SUM(L11:L13) -> 0 | N14: =SUM(N11:N13) -> 0 | P14: =SUM(P11:P13) -> 0 | R14: =SUM(R11:R13) -> 0 | T14: =SUM(T11:T13) -> 0 | V14: =SUM(V11:V13) -> 0
B15: Other Income | D15: =Scenarios!AB25*(1+D6) -> 0 | F15: =D15*(1+F6) -> 0 | H15: =F15*(1+H6) -> 0 | J15: =H15*(1+J6) -> 0 | L15: =J15*(1+L6) -> 0 | N15: =L15*(1+N6) -> 0 | P15: =N15*(1+P6) -> 0 | R15: =P15*(1+R6) -> 0 | T15: =R15*(1+T6) -> 0 | V15: =T15*(1+V6) -> 0
B16: Effective Gross Income | D16: =SUM(D14:D15) -> 0 | F16: =SUM(F14:F15) -> 0 | H16: =SUM(H14:H15) -> 0 | J16: =SUM(J14:J15) -> 0 | L16: =SUM(L14:L15) -> 0 | N16: =SUM(N14:N15) -> 0 | P16: =SUM(P14:P15) -> 0 | R16: =SUM(R14:R15) -> 0 | T16: =SUM(T14:T15) -> 0 | V16: =SUM(V14:V15) -> 0
B18: EXPENSES
B19: Advertising | D19: =CHOOSE(Summary!$G$3,Scenarios!D29,Scenarios!G29,Scenarios!J29,Scenarios!M29,Scenarios!P29,Scenarios!S29,Scenarios!V29,Scenarios!Y29)*(1+$D$7) -> 0 | E19: =IF(D19=0,0,D19/$D$16) -> 0 | F19: =D19*(1+F$7) -> 0 | G19: =IF(F19=0,0,F19/$F$16) -> 0 | H19: =F19*(1+H$7) -> 0 | I19: =IF(H19=0,0,H19/$H$16) -> 0 | J19: =H19*(1+J$7) -> 0 | K19: =IF(J19=0,0,J19/$J$16) -> 0 | L19: =J19*(1+L$7) -> 0 | M19: =IF(L19=0,0,L19/$L$16) -> 0 | N19: =L19*(1+N$7) -> 0 | O19: =IF(N19=0,0,N19/$N$16) -> 0 | P19: =N19*(1+P$7) -> 0 | Q19: =IF(P19=0,0,P19/$P$16) -> 0 | R19: =P19*(1+R$7) -> 0 | S19: =IF(R19=0,0,R19/$R$16) -> 0 | T19: =R19*(1+T$7) -> 0 | U19: =IF(T19=0,0,T19/$T$16) -> 0 | V19: =T19*(1+V$7) -> 0 | W19: =IF(V19=0,0,V19/$V$16) -> 0
B20: Contract Services | D20: =CHOOSE(Summary!$G$3,Scenarios!D30,Scenarios!G30,Scenarios!J30,Scenarios!M30,Scenarios!P30,Scenarios!S30,Scenarios!V30,Scenarios!Y30)*(1+$D$7) -> 0 | E20: =IF(D20=0,0,D20/$D$16) -> 0 | F20: =D20*(1+F$7) -> 0 | G20: =IF(F20=0,0,F20/$F$16) -> 0 | H20: =F20*(1+H$7) -> 0 | I20: =IF(H20=0,0,H20/$H$16) -> 0 | J20: =H20*(1+J$7) -> 0 | K20: =IF(J20=0,0,J20/$J$16) -> 0 | L20: =J20*(1+L$7) -> 0 | M20: =IF(L20=0,0,L20/$L$16) -> 0 | N20: =L20*(1+N$7) -> 0 | O20: =IF(N20=0,0,N20/$N$16) -> 0 | P20: =N20*(1+P$7) -> 0 | Q20: =IF(P20=0,0,P20/$P$16) -> 0 | R20: =P20*(1+R$7) -> 0 | S20: =IF(R20=0,0,R20/$R$16) -> 0 | T20: =R20*(1+T$7) -> 0 | U20: =IF(T20=0,0,T20/$T$16) -> 0 | V20: =T20*(1+V$7) -> 0 | W20: =IF(V20=0,0,V20/$V$16) -> 0
B21: Gas & Electric | D21: =CHOOSE(Summary!$G$3,Scenarios!D31,Scenarios!G31,Scenarios!J31,Scenarios!M31,Scenarios!P31,Scenarios!S31,Scenarios!V31,Scenarios!Y31)*(1+$D$7) -> 0 | E21: =IF(D21=0,0,D21/$D$16) -> 0 | F21: =D21*(1+F$7) -> 0 | G21: =IF(F21=0,0,F21/$F$16) -> 0 | H21: =F21*(1+H$7) -> 0 | I21: =IF(H21=0,0,H21/$H$16) -> 0 | J21: =H21*(1+J$7) -> 0 | K21: =IF(J21=0,0,J21/$J$16) -> 0 | L21: =J21*(1+L$7) -> 0 | M21: =IF(L21=0,0,L21/$L$16) -> 0 | N21: =L21*(1+N$7) -> 0 | O21: =IF(N21=0,0,N21/$N$16) -> 0 | P21: =N21*(1+P$7) -> 0 | Q21: =IF(P21=0,0,P21/$P$16) -> 0 | R21: =P21*(1+R$7) -> 0 | S21: =IF(R21=0,0,R21/$R$16) -> 0 | T21: =R21*(1+T$7) -> 0 | U21: =IF(T21=0,0,T21/$T$16) -> 0 | V21: =T21*(1+V$7) -> 0 | W21: =IF(V21=0,0,V21/$V$16) -> 0
B22: General/Admin | D22: =CHOOSE(Summary!$G$3,Scenarios!D32,Scenarios!G32,Scenarios!J32,Scenarios!M32,Scenarios!P32,Scenarios!S32,Scenarios!V32,Scenarios!Y32)*(1+$D$7) -> 0 | E22: =IF(D22=0,0,D22/$D$16) -> 0 | F22: =D22*(1+F$7) -> 0 | G22: =IF(F22=0,0,F22/$F$16) -> 0 | H22: =F22*(1+H$7) -> 0 | I22: =IF(H22=0,0,H22/$H$16) -> 0 | J22: =H22*(1+J$7) -> 0 | K22: =IF(J22=0,0,J22/$J$16) -> 0 | L22: =J22*(1+L$7) -> 0 | M22: =IF(L22=0,0,L22/$L$16) -> 0 | N22: =L22*(1+N$7) -> 0 | O22: =IF(N22=0,0,N22/$N$16) -> 0 | P22: =N22*(1+P$7) -> 0 | Q22: =IF(P22=0,0,P22/$P$16) -> 0 | R22: =P22*(1+R$7) -> 0 | S22: =IF(R22=0,0,R22/$R$16) -> 0 | T22: =R22*(1+T$7) -> 0 | U22: =IF(T22=0,0,T22/$T$16) -> 0 | V22: =T22*(1+V$7) -> 0 | W22: =IF(V22=0,0,V22/$V$16) -> 0
B23: Insurance | D23: =CHOOSE(Summary!$G$3,Scenarios!D33,Scenarios!G33,Scenarios!J33,Scenarios!M33,Scenarios!P33,Scenarios!S33,Scenarios!V33,Scenarios!Y33)*(1+$D$7) -> 0 | E23: =IF(D23=0,0,D23/$D$16) -> 0 | F23: =D23*(1+F$7) -> 0 | G23: =IF(F23=0,0,F23/$F$16) -> 0 | H23: =F23*(1+H$7) -> 0 | I23: =IF(H23=0,0,H23/$H$16) -> 0 | J23: =H23*(1+J$7) -> 0 | K23: =IF(J23=0,0,J23/$J$16) -> 0 | L23: =J23*(1+L$7) -> 0 | M23: =IF(L23=0,0,L23/$L$16) -> 0 | N23: =L23*(1+N$7) -> 0 | O23: =IF(N23=0,0,N23/$N$16) -> 0 | P23: =N23*(1+P$7) -> 0 | Q23: =IF(P23=0,0,P23/$P$16) -> 0 | R23: =P23*(1+R$7) -> 0 | S23: =IF(R23=0,0,R23/$R$16) -> 0 | T23: =R23*(1+T$7) -> 0 | U23: =IF(T23=0,0,T23/$T$16) -> 0 | V23: =T23*(1+V$7) -> 0 | W23: =IF(V23=0,0,V23/$V$16) -> 0
B24: Legal | D24: =CHOOSE(Summary!$G$3,Scenarios!D34,Scenarios!G34,Scenarios!J34,Scenarios!M34,Scenarios!P34,Scenarios!S34,Scenarios!V34,Scenarios!Y34)*(1+$D$7) -> 0 | E24: =IF(D24=0,0,D24/$D$16) -> 0 | F24: =D24*(1+F$7) -> 0 | G24: =IF(F24=0,0,F24/$F$16) -> 0 | H24: =F24*(1+H$7) -> 0 | I24: =IF(H24=0,0,H24/$H$16) -> 0 | J24: =H24*(1+J$7) -> 0 | K24: =IF(J24=0,0,J24/$J$16) -> 0 | L24: =J24*(1+L$7) -> 0 | M24: =IF(L24=0,0,L24/$L$16) -> 0 | N24: =L24*(1+N$7) -> 0 | O24: =IF(N24=0,0,N24/$N$16) -> 0 | P24: =N24*(1+P$7) -> 0 | Q24: =IF(P24=0,0,P24/$P$16) -> 0 | R24: =P24*(1+R$7) -> 0 | S24: =IF(R24=0,0,R24/$R$16) -> 0 | T24: =R24*(1+T$7) -> 0 | U24: =IF(T24=0,0,T24/$T$16) -> 0 | V24: =T24*(1+V$7) -> 0 | W24: =IF(V24=0,0,V24/$V$16) -> 0
B25: Real Estate Taxes | D25: =CHOOSE(Summary!$G$3,Scenarios!D35,Scenarios!G35,Scenarios!J35,Scenarios!M35,Scenarios!P35,Scenarios!S35,Scenarios!V35,Scenarios!Y35)*(1+$D$7) -> 0 | E25: =IF(D25=0,0,D25/$D$16) -> 0 | F25: =D25*(1+F$7) -> 0 | G25: =IF(F25=0,0,F25/$F$16) -> 0 | H25: =F25*(1+H$7) -> 0 | I25: =IF(H25=0,0,H25/$H$16) -> 0 | J25: =H25*(1+J$7) -> 0 | K25: =IF(J25=0,0,J25/$J$16) -> 0 | L25: =J25*(1+L$7) -> 0 | M25: =IF(L25=0,0,L25/$L$16) -> 0 | N25: =L25*(1+N$7) -> 0 | O25: =IF(N25=0,0,N25/$N$16) -> 0 | P25: =N25*(1+P$7) -> 0 | Q25: =IF(P25=0,0,P25/$P$16) -> 0 | R25: =P25*(1+R$7) -> 0 | S25: =IF(R25=0,0,R25/$R$16) -> 0 | T25: =R25*(1+T$7) -> 0 | U25: =IF(T25=0,0,T25/$T$16) -> 0 | V25: =T25*(1+V$7) -> 0 | W25: =IF(V25=0,0,V25/$V$16) -> 0
B26: Trash Removal | D26: =CHOOSE(Summary!$G$3,Scenarios!D36,Scenarios!G36,Scenarios!J36,Scenarios!M36,Scenarios!P36,Scenarios!S36,Scenarios!V36,Scenarios!Y36)*(1+$D$7) -> 0 | E26: =IF(D26=0,0,D26/$D$16) -> 0 | F26: =D26*(1+F$7) -> 0 | G26: =IF(F26=0,0,F26/$F$16) -> 0 | H26: =F26*(1+H$7) -> 0 | I26: =IF(H26=0,0,H26/$H$16) -> 0 | J26: =H26*(1+J$7) -> 0 | K26: =IF(J26=0,0,J26/$J$16) -> 0 | L26: =J26*(1+L$7) -> 0 | M26: =IF(L26=0,0,L26/$L$16) -> 0 | N26: =L26*(1+N$7) -> 0 | O26: =IF(N26=0,0,N26/$N$16) -> 0 | P26: =N26*(1+P$7) -> 0 | Q26: =IF(P26=0,0,P26/$P$16) -> 0 | R26: =P26*(1+R$7) -> 0 | S26: =IF(R26=0,0,R26/$R$16) -> 0 | T26: =R26*(1+T$7) -> 0 | U26: =IF(T26=0,0,T26/$T$16) -> 0 | V26: =T26*(1+V$7) -> 0 | W26: =IF(V26=0,0,V26/$V$16) -> 0
B27: Management Fee | D27: =E27*D16 -> 0 | E27: =CHOOSE(Summary!$G$3,Scenarios!F37,Scenarios!I37,Scenarios!L37,Scenarios!O37,Scenarios!R37,Scenarios!U37,Scenarios!X37,Scenarios!AA37) -> 0 | F27: =G27*F16 -> 0 | G27: =E27 -> 0 | H27: =I27*H16 -> 0 | I27: =G27 -> 0 | J27: =K27*J16 -> 0 | K27: =I27 -> 0 | L27: =M27*L16 -> 0 | M27: =K27 -> 0 | N27: =O27*N16 -> 0 | O27: =M27 -> 0 | P27: =Q27*P16 -> 0 | Q27: =O27 -> 0 | R27: =S27*R16 -> 0 | S27: =Q27 -> 0 | T27: =U27*T16 -> 0 | U27: =S27 -> 0 | V27: =W27*V16 -> 0 | W27: =U27 -> 0
B28: Payroll | D28: =CHOOSE(Summary!$G$3,Scenarios!D38,Scenarios!G38,Scenarios!J38,Scenarios!M38,Scenarios!P38,Scenarios!S38,Scenarios!V38,Scenarios!Y38)*(1+$D$7) -> 0 | E28: =IF(D28=0,0,D28/$D$16) -> 0 | F28: =D28*(1+F$7) -> 0 | G28: =IF(F28=0,0,F28/$F$16) -> 0 | H28: =F28*(1+H$7) -> 0 | I28: =IF(H28=0,0,H28/$H$16) -> 0 | J28: =H28*(1+J$7) -> 0 | K28: =IF(J28=0,0,J28/$J$16) -> 0 | L28: =J28*(1+L$7) -> 0 | M28: =IF(L28=0,0,L28/$L$16) -> 0 | N28: =L28*(1+N$7) -> 0 | O28: =IF(N28=0,0,N28/$N$16) -> 0 | P28: =N28*(1+P$7) -> 0 | Q28: =IF(P28=0,0,P28/$P$16) -> 0 | R28: =P28*(1+R$7) -> 0 | S28: =IF(R28=0,0,R28/$R$16) -> 0 | T28: =R28*(1+T$7) -> 0 | U28: =IF(T28=0,0,T28/$T$16) -> 0 | V28: =T28*(1+V$7) -> 0 | W28: =IF(V28=0,0,V28/$V$16) -> 0
B29: Repairs and Maintenance | D29: =CHOOSE(Summary!$G$3,Scenarios!D39,Scenarios!G39,Scenarios!J39,Scenarios!M39,Scenarios!P39,Scenarios!S39,Scenarios!V39,Scenarios!Y39)*(1+$D$7) -> 0 | E29: =IF(D29=0,0,D29/$D$16) -> 0 | F29: =D29*(1+F$7) -> 0 | G29: =IF(F29=0,0,F29/$F$16) -> 0 | H29: =F29*(1+H$7) -> 0 | I29: =IF(H29=0,0,H29/$H$16) -> 0 | J29: =H29*(1+J$7) -> 0 | K29: =IF(J29=0,0,J29/$J$16) -> 0 | L29: =J29*(1+L$7) -> 0 | M29: =IF(L29=0,0,L29/$L$16) -> 0 | N29: =L29*(1+N$7) -> 0 | O29: =IF(N29=0,0,N29/$N$16) -> 0 | P29: =N29*(1+P$7) -> 0 | Q29: =IF(P29=0,0,P29/$P$16) -> 0 | R29: =P29*(1+R$7) -> 0 | S29: =IF(R29=0,0,R29/$R$16) -> 0 | T29: =R29*(1+T$7) -> 0 | U29: =IF(T29=0,0,T29/$T$16) -> 0 | V29: =T29*(1+V$7) -> 0 | W29: =IF(V29=0,0,V29/$V$16) -> 0
B30: Turnover | D30: =CHOOSE(Summary!$G$3,Scenarios!D40,Scenarios!G40,Scenarios!J40,Scenarios!M40,Scenarios!P40,Scenarios!S40,Scenarios!V40,Scenarios!Y40)*(1+$D$7) -> 0 | E30: =IF(D30=0,0,D30/$D$16) -> 0 | F30: =D30*(1+F$7) -> 0 | G30: =IF(F30=0,0,F30/$F$16) -> 0 | H30: =F30*(1+H$7) -> 0 | I30: =IF(H30=0,0,H30/$H$16) -> 0 | J30: =H30*(1+J$7) -> 0 | K30: =IF(J30=0,0,J30/$J$16) -> 0 | L30: =J30*(1+L$7) -> 0 | M30: =IF(L30=0,0,L30/$L$16) -> 0 | N30: =L30*(1+N$7) -> 0 | O30: =IF(N30=0,0,N30/$N$16) -> 0 | P30: =N30*(1+P$7) -> 0 | Q30: =IF(P30=0,0,P30/$P$16) -> 0 | R30: =P30*(1+R$7) -> 0 | S30: =IF(R30=0,0,R30/$R$16) -> 0 | T30: =R30*(1+T$7) -> 0 | U30: =IF(T30=0,0,T30/$T$16) -> 0 | V30: =T30*(1+V$7) -> 0 | W30: =IF(V30=0,0,V30/$V$16) -> 0
B31: Water and Sewer | D31: =CHOOSE(Summary!$G$3,Scenarios!D41,Scenarios!G41,Scenarios!J41,Scenarios!M41,Scenarios!P41,Scenarios!S41,Scenarios!V41,Scenarios!Y41)*(1+$D$7) -> 0 | E31: =IF(D31=0,0,D31/$D$16) -> 0 | F31: =D31*(1+F$7) -> 0 | G31: =IF(F31=0,0,F31/$F$16) -> 0 | H31: =F31*(1+H$7) -> 0 | I31: =IF(H31=0,0,H31/$H$16) -> 0 | J31: =H31*(1+J$7) -> 0 | K31: =IF(J31=0,0,J31/$J$16) -> 0 | L31: =J31*(1+L$7) -> 0 | M31: =IF(L31=0,0,L31/$L$16) -> 0 | N31: =L31*(1+N$7) -> 0 | O31: =IF(N31=0,0,N31/$N$16) -> 0 | P31: =N31*(1+P$7) -> 0 | Q31: =IF(P31=0,0,P31/$P$16) -> 0 | R31: =P31*(1+R$7) -> 0 | S31: =IF(R31=0,0,R31/$R$16) -> 0 | T31: =R31*(1+T$7) -> 0 | U31: =IF(T31=0,0,T31/$T$16) -> 0 | V31: =T31*(1+V$7) -> 0 | W31: =IF(V31=0,0,V31/$V$16) -> 0
B32: Deposit to Replacement Reserve | D32: =CHOOSE(Summary!$G$3,Scenarios!D42,Scenarios!G42,Scenarios!J42,Scenarios!M42,Scenarios!P42,Scenarios!S42,Scenarios!V42,Scenarios!Y42) -> 0 | E32: =IF(D32=0,0,D32/$D$16) -> 0 | F32: =D32 -> 0 | G32: =IF(F32=0,0,F32/$F$16) -> 0 | H32: =F32 -> 0 | I32: =IF(H32=0,0,H32/$H$16) -> 0 | J32: =H32 -> 0 | K32: =IF(J32=0,0,J32/$J$16) -> 0 | L32: =J32 -> 0 | M32: =IF(L32=0,0,L32/$L$16) -> 0 | N32: =L32 -> 0 | O32: =IF(N32=0,0,N32/$N$16) -> 0 | P32: =N32 -> 0 | Q32: =IF(P32=0,0,P32/$P$16) -> 0 | R32: =P32 -> 0 | S32: =IF(R32=0,0,R32/$R$16) -> 0 | T32: =R32 -> 0 | U32: =IF(T32=0,0,T32/$T$16) -> 0 | V32: =T32 -> 0 | W32: =IF(V32=0,0,V32/$V$16) -> 0
B33: Total Expenses | D33: =IF(SUM(D19:D32)=0,Scenarios!AB47*(1+D7),SUM(D19:D32)) -> 0 | E33: =IF(D33=0,0,D33/D16) -> 0 | F33: =IF(SUM(F19:F32)=0,D33*(1+F7),SUM(F19:F32)) -> 0 | G33: =IF(F33=0,0,F33/F16) -> 0 | H33: =IF(SUM(H19:H32)=0,F33*(1+H7),SUM(H19:H32)) -> 0 | I33: =IF(H33=0,0,H33/H16) -> 0 | J33: =IF(SUM(J19:J32)=0,H33*(1+J7),SUM(J19:J32)) -> 0 | K33: =IF(J33=0,0,J33/J16) -> 0 | L33: =IF(SUM(L19:L32)=0,J33*(1+L7),SUM(L19:L32)) -> 0 | M33: =IF(L33=0,0,L33/L16) -> 0 | N33: =IF(SUM(N19:N32)=0,L33*(1+N7),SUM(N19:N32)) -> 0 | O33: =IF(N33=0,0,N33/N16) -> 0 | P33: =IF(SUM(P19:P32)=0,N33*(1+P7),SUM(P19:P32)) -> 0 | Q33: =IF(P33=0,0,P33/P16) -> 0 | R33: =IF(SUM(R19:R32)=0,P33*(1+R7),SUM(R19:R32)) -> 0 | S33: =IF(R33=0,0,R33/R16) -> 0 | T33: =IF(SUM(T19:T32)=0,R33*(1+T7),SUM(T19:T32)) -> 0 | U33: =IF(T33=0,0,T33/T16) -> 0 | V33: =IF(SUM(V19:V32)=0,T33*(1+V7),SUM(V19:V32)) -> 0 | W33: =IF(V33=0,0,V33/V16) -> 0
B35: Net Operating Income (NOI) | D35: =D16-D33 -> 0 | F35: =F16-F33 -> 0 | H35: =H16-H33 -> 0 | J35: =J16-J33 -> 0 | L35: =L16-L33 -> 0 | N35: =N16-N33 -> 0 | P35: =P16-P33 -> 0 | R35: =R16-R33 -> 0 | T35: =T16-T33 -> 0 | V35: =V16-V33 -> 0
B37: Debt Service
B38: Principal | D38: =OFFSET(Loans!$H$32,0,(D9-1)) -> 0 | F38: =OFFSET(Loans!$H$32,0,(F9-1)) -> 0 | H38: =OFFSET(Loans!$H$32,0,(H9-1)) -> 0 | J38: =OFFSET(Loans!$H$32,0,(J9-1)) -> 0 | L38: =OFFSET(Loans!$H$32,0,(L9-1)) -> 0 | N38: =OFFSET(Loans!$H$32,0,(N9-1)) -> 0 | P38: =OFFSET(Loans!$H$32,0,(P9-1)) -> 0 | R38: =OFFSET(Loans!$H$32,0,(R9-1)) -> 0 | T38: =OFFSET(Loans!$H$32,0,(T9-1)) -> 0 | V38: =OFFSET(Loans!$H$32,0,(V9-1)) -> 0
B39: Interest | D39: =OFFSET(Loans!$H$30,0,(D9-1)) -> 0 | F39: =OFFSET(Loans!$H$30,0,(F9-1)) -> 0 | H39: =OFFSET(Loans!$H$30,0,(H9-1)) -> 0 | J39: =OFFSET(Loans!$H$30,0,(J9-1)) -> 0 | L39: =OFFSET(Loans!$H$30,0,(L9-1)) -> 0 | N39: =OFFSET(Loans!$H$30,0,(N9-1)) -> 0 | P39: =OFFSET(Loans!$H$30,0,(P9-1)) -> 0 | R39: =OFFSET(Loans!$H$30,0,(R9-1)) -> 0 | T39: =OFFSET(Loans!$H$30,0,(T9-1)) -> 0 | V39: =OFFSET(Loans!$H$30,0,(V9-1)) -> 0
B40: Total Debt Service | D40: =SUM(D38:D39) -> 0 | F40: =SUM(F38:F39) -> 0 | H40: =SUM(H38:H39) -> 0 | J40: =SUM(J38:J39) -> 0 | L40: =SUM(L38:L39) -> 0 | N40: =SUM(N38:N39) -> 0 | P40: =SUM(P38:P39) -> 0 | R40: =SUM(R38:R39) -> 0 | T40: =SUM(T38:T39) -> 0 | V40: =SUM(V38:V39) -> 0
B42: Cash Flow available for Distribution | D42: =D35-D40 -> 0 | F42: =F35-F40 -> 0 | H42: =H35-H40 -> 0 | J42: =J35-J40 -> 0 | L42: =L35-L40 -> 0 | N42: =N35-N40 -> 0 | P42: =P35-P40 -> 0 | R42: =R35-R40 -> 0 | T42: =T35-T40 -> 0 | V42: =V35-V40 -> 0
B44: Distributions from Cash Flow
B45: Asset Mgt Fee | C45: =Summary!D44 -> 0 | D45: =IF(D9<=year_sale,IF($C$45*D$16<D$42,$C$45*D$16,0),0) -> 0 | F45: =IF(F9<=year_sale,IF($C$45*F$16<F$42,$C$45*F$16,0),0) -> 0 | H45: =IF(H9<=year_sale,IF($C$45*H$16<H$42,$C$45*H$16,0),0) -> 0 | J45: =IF(J9<=year_sale,IF($C$45*J$16<J$42,$C$45*J$16,0),0) -> 0 | L45: =IF(L9<=year_sale,IF($C$45*L$16<L$42,$C$45*L$16,0),0) -> 0 | N45: =IF(N9<=year_sale,IF($C$45*N$16<N$42,$C$45*N$16,0),0) -> 0 | P45: =IF(P9<=year_sale,IF($C$45*P$16<P$42,$C$45*P$16,0),0) -> 0 | R45: =IF(R9<=year_sale,IF($C$45*R$16<R$42,$C$45*R$16,0),0) -> 0 | T45: =IF(T9<=year_sale,IF($C$45*T$16<T$42,$C$45*T$16,0),0) -> 0 | V45: =IF(V9<=year_sale,IF($C$45*V$16<V$42,$C$45*V$16,0),0) -> 0
B46: Members Preferred Return Due | D46: =IF(D53=0,0,D$53*$C$48) -> 0 | F46: =IF(F53=0,0,F$53*$C$48+D$47) -> 0 | H46: =IF(H53=0,0,H$53*$C$48+F$47) -> 0 | J46: =IF(J53=0,0,J$53*$C$48+H$47) -> 0 | L46: =IF(L53=0,0,L$53*$C$48+J$47) -> 0 | N46: =IF(N53=0,0,N$53*$C$48+L$47) -> 0 | P46: =IF(P53=0,0,P$53*$C$48+N$47) -> 0 | R46: =IF(R53=0,0,R$53*$C$48+P$47) -> 0 | T46: =IF(T53=0,0,T$53*$C$48+R$47) -> 0 | V46: =IF(V53=0,0,V$53*$C$48+T$47) -> 0
B47: Members Preferred Return Deficiency | D47: =IF(D$46 >0,D$46-D$48,0) -> 0 | F47: =IF(F$46 >0,F$46-F$48,0) -> 0 | H47: =IF(H$46 >0,H$46-H$48,0) -> 0 | J47: =IF(J$46 >0,J$46-J$48,0) -> 0 | L47: =IF(L$46 >0,L$46-L$48,0) -> 0 | N47: =IF(N$46 >0,N$46-N$48,0) -> 0 | P47: =IF(P$46 >0,P$46-P$48,0) -> 0 | R47: =IF(R$46 >0,R$46-R$48,0) -> 0 | T47: =IF(T$46 >0,T$46-T$48,0) -> 0 | V47: =IF(V$46 >0,V$46-V$48,0) -> 0
B48: Members Preferred Return Paid | C48: =Summary!D43 -> 0 | D48: =IF(D$42>0,IF(D$46+D$45>D$42,D$42-D$45,D$46),0) -> 0 | F48: =IF(F$42>0,IF(F$46+F$45>F$42,F$42-F$45,F$46),0) -> 0 | H48: =IF(H$42>0,IF(H$46+H$45>H$42,H$42-H$45,H$46),0) -> 0 | J48: =IF(J$42>0,IF(J$46+J$45>J$42,J$42-J$45,J$46),0) -> 0 | L48: =IF(L$42>0,IF(L$46+L$45>L$42,L$42-L$45,L$46),0) -> 0 | N48: =IF(N$42>0,IF(N$46+N$45>N$42,N$42-N$45,N$46),0) -> 0 | P48: =IF(P$42>0,IF(P$46+P$45>P$42,P$42-P$45,P$46),0) -> 0 | R48: =IF(R$42>0,IF(R$46+R$45>R$42,R$42-R$45,R$46),0) -> 0 | T48: =IF(T$42>0,IF(T$46+T$45>T$42,T$42-T$45,T$46),0) -> 0 | V48: =IF(V$42>0,IF(V$46+V$45>V$42,V$42-V$45,V$46),0) -> 0
B49: Excess Cash Flow to Members | C49: =Summary!D41 -> 0.8 | D49: =IF(D9<=year_sale,IF((D$42-D$45-D$48)*$C$49<0,0,(D$42-D$45-D$48)*$C$49),0) -> 0 | F49: =IF(F9<=year_sale,IF((F$42-F$45-F$48)*$C$49<0,0,(F$42-F$45-F$48)*$C$49),0) -> 0 | H49: =IF(H9<=year_sale,IF((H$42-H$45-H$48)*$C$49<0,0,(H$42-H$45-H$48)*$C$49),0) -> 0 | J49: =IF(J9<=year_sale,IF((J$42-J$45-J$48)*$C$49<0,0,(J$42-J$45-J$48)*$C$49),0) -> 0 | L49: =IF(L9<=year_sale,IF((L$42-L$45-L$48)*$C$49<0,0,(L$42-L$45-L$48)*$C$49),0) -> 0 | N49: =IF(N9<=year_sale,IF((N$42-N$45-N$48)*$C$49<0,0,(N$42-N$45-N$48)*$C$49),0) -> 0 | P49: =IF(P9<=year_sale,IF((P$42-P$45-P$48)*$C$49<0,0,(P$42-P$45-P$48)*$C$49),0) -> 0 | R49: =IF(R9<=year_sale,IF((R$42-R$45-R$48)*$C$49<0,0,(R$42-R$45-R$48)*$C$49),0) -> 0 | T49: =IF(T9<=year_sale,IF((T$42-T$45-T$48)*$C$49<0,0,(T$42-T$45-T$48)*$C$49),0) -> 0 | V49: =IF(V9<=year_sale,IF((V$42-V$45-V$48)*$C$49<0,0,(V$42-V$45-V$48)*$C$49),0) -> 0
B50: Excess Cash Flow to Mgr | C50: =Summary!D42 -> 0.2 | D50: =IF(D9<=year_sale,IF((D$42-D$45-D$48)*$C$50<0,0,(D$42-D$45-D$48)*$C$50),0) -> 0 | F50: =IF(F9<=year_sale,IF((F$42-F$45-F$48)*$C$50<0,0,(F$42-F$45-F$48)*$C$50),0) -> 0 | H50: =IF(H9<=year_sale,IF((H$42-H$45-H$48)*$C$50<0,0,(H$42-H$45-H$48)*$C$50),0) -> 0 | J50: =IF(J9<=year_sale,IF((J$42-J$45-J$48)*$C$50<0,0,(J$42-J$45-J$48)*$C$50),0) -> 0 | L50: =IF(L9<=year_sale,IF((L$42-L$45-L$48)*$C$50<0,0,(L$42-L$45-L$48)*$C$50),0) -> 0 | N50: =IF(N9<=year_sale,IF((N$42-N$45-N$48)*$C$50<0,0,(N$42-N$45-N$48)*$C$50),0) -> 0 | P50: =IF(P9<=year_sale,IF((P$42-P$45-P$48)*$C$50<0,0,(P$42-P$45-P$48)*$C$50),0) -> 0 | R50: =IF(R9<=year_sale,IF((R$42-R$45-R$48)*$C$50<0,0,(R$42-R$45-R$48)*$C$50),0) -> 0 | T50: =IF(T9<=year_sale,IF((T$42-T$45-T$48)*$C$50<0,0,(T$42-T$45-T$48)*$C$50),0) -> 0 | V50: =IF(V9<=year_sale,IF((V$42-V$45-V$48)*$C$50<0,0,(V$42-V$45-V$48)*$C$50),0) -> 0
B51: Total Distributions to Members | D51: =IF(D9>year_sale,0,D49+D48) -> 0 | F51: =IF(F9>year_sale,0,F49+F48) -> 0 | H51: =IF(H9>year_sale,0,H49+H48) -> 0 | J51: =IF(J9>year_sale,0,J49+J48) -> 0 | L51: =IF(L9>year_sale,0,L49+L48) -> 0 | N51: =IF(N9>year_sale,0,N49+N48) -> 0 | P51: =IF(P9>year_sale,0,P49+P48) -> 0 | R51: =IF(R9>year_sale,0,R49+R48) -> 0 | T51: =IF(T9>year_sale,0,T49+T48) -> 0 | V51: =IF(V9>year_sale,0,V49+V48) -> 0
B53: Capital Account Balance (Begin of Year) | D53: =IF(D9>year_sale,0,Returns!C5) -> 0 | F53: =IF(F9>year_sale,0,Returns!D5) -> 0 | H53: =IF(H9>year_sale,0,Returns!E5) -> 0 | J53: =IF(J9>year_sale,0,Returns!F5) -> 0 | L53: =IF(L9>year_sale,0,Returns!G5) -> 0 | N53: =IF(N9>year_sale,0,Returns!H5) -> 0 | P53: =IF(P9>year_sale,0,Returns!I5) -> 0 | R53: =IF(R9>year_sale,0,Returns!J5) -> 0 | T53: =IF(T9>year_sale,0,Returns!K5) -> 0 | V53: =IF(V9>year_sale,0,Returns!L5) -> 0
B55: Member Cash-on-Cash Return | D55: =IF(D53=0,"∞",D51/D53) -> ∞ | F55: =IF(F53=0,"∞",F51/F53) -> ∞ | H55: =IF(H53=0,"∞",H51/H53) -> ∞ | J55: =IF(J53=0,"∞",J51/J53) -> ∞ | L55: =IF(L53=0,"∞",L51/L53) -> ∞ | N55: =IF(N53=0,"∞",N51/N53) -> ∞ | P55: =IF(P53=0,"∞",P51/P53) -> ∞ | R55: =IF(R53=0,"∞",R51/R53) -> ∞ | T55: =IF(T53=0,"∞",T51/T53) -> ∞ | V55: =IF(V53=0,"∞",V51/V53) -> ∞
B56: =Returns!B18 -> Cash-on-Cash Return | D56: =Returns!C8 -> ∞ | F56: =Returns!D8 -> ∞ | H56: =Returns!E8 -> ∞ | J56: =Returns!F8 -> ∞ | L56: =Returns!G8 -> ∞ | N56: =Returns!H8 -> 0 | P56: =Returns!I8 -> 0 | R56: =Returns!J8 -> 0 | T56: =Returns!K8 -> 0 | V56: =Returns!L8 -> 0
B58: Property Value | C58: =C59-1% -> 0.06 | D58: =D35/$C$58 -> 0 | F58: =F35/$C$58 -> 0 | H58: =H35/$C$58 -> 0 | J58: =J35/$C$58 -> 0 | L58: =L35/$C$58 -> 0 | N58: =N35/$C$58 -> 0 | P58: =P35/$C$58 -> 0 | R58: =R35/$C$58 -> 0 | T58: =T35/$C$58 -> 0 | V58: =V35/$C$58 -> 0
C59: =Summary!D23 -> 0.07 | D59: =D35/$C$59 -> 0 | F59: =F35/$C$59 -> 0 | H59: =H35/$C$59 -> 0 | J59: =J35/$C$59 -> 0 | L59: =L35/$C$59 -> 0 | N59: =N35/$C$59 -> 0 | P59: =P35/$C$59 -> 0 | R59: =R35/$C$59 -> 0 | T59: =T35/$C$59 -> 0 | V59: =V35/$C$59 -> 0
C60: =C59+1% -> 0.08 | D60: =D35/$C$60 -> 0 | F60: =F35/$C$60 -> 0 | H60: =H35/$C$60 -> 0 | J60: =J35/$C$60 -> 0 | L60: =L35/$C$60 -> 0 | N60: =N35/$C$60 -> 0 | P60: =P35/$C$60 -> 0 | R60: =R35/$C$60 -> 0 | T60: =T35/$C$60 -> 0 | V60: =V35/$C$60 -> 0
B62: Debt Coverage Ratio | D62: =IF(D40=0,0,D35/D40) -> 0 | F62: =IF(F40=0,0,F35/F40) -> 0 | H62: =IF(H40=0,0,H35/H40) -> 0 | J62: =IF(J40=0,0,J35/J40) -> 0 | L62: =IF(L40=0,0,L35/L40) -> 0 | N62: =IF(N40=0,0,N35/N40) -> 0 | P62: =IF(P40=0,0,P35/P40) -> 0 | R62: =IF(R40=0,0,R35/R40) -> 0 | T62: =IF(T40=0,0,T35/T40) -> 0 | V62: =IF(V40=0,0,V35/V40) -> 0
B64: =copyright -> Copyright © 2026 Michael Blank.
B65: The information herein is not guaranteed but believed to be accurate.

Sheet Exit Strategy
B1: Exit Strategy
B3: Exit Strategy | D3: Year
B4: Cash Out Re-Finance at end of year | D4: NA
B5: Sale / Disposition at end of year | D5: 5
B7: Refinance | D7: =year_refi -> NA | F7: Sale | H7: =year_sale -> 5
B8: Net Operating Income | D8: =IF($D$4="NA",0,OFFSET('P&L'!D35,0,$D$4*2-2)+OFFSET('P&L'!D32,0,$D$4*2-2)) -> 0 | F8: Net Operating Income | H8: =OFFSET('P&L'!D35,0,$D$5*2-2)+OFFSET('P&L'!D32,0,$D$5*2-2) -> 0
B9: Cap Rate at Re-Finance | D9: =IF($D$4="NA",0,Summary!$D$23+(var_capRateBump*$D$4)) -> 0 | F9: Cap Rate | H9: =Summary!$D$23+(var_capRateBump*$D$5) -> 0.075 | I9: 0.001 | J9: Cap rate increase per year
B10: Appraised Value | D10: =IF($D$4="NA",0,D8/D9) -> 0 | F10: Insurance/Tax/Lender Escrows | H10: =SUM('Acquisition Costs'!D38:D40) -> 0
B11: Re-Finance LTV | D11: 0.65 | F11: Operating Reserves remaining | H11: =Summary!$D$21*$I$11 -> 0 | I11: 0.5 | J11: % of remaining funds in the operating account at sale
B12: Interest Rate | D12: =IF($D$4="NA",0,Summary!D11) -> 0 | F12: Sales Price | H12: =H8/H9 -> 0
B13: Term / Amortization (Years) | D13: 25 | F13: Sales Cost | G13: =IF(H12<2000000,4%,3%) -> 0.04 | H13: =-G13*H12 -> 0
B14: Interest Only (in months) | D14: 0 | F14: Outstanding Loan Balance | H14: =-OFFSET(Loans!$H$35,0,$D$5-1) -> 0
B15: Re-Finance Loan Amount | D15: =IF($D$4="NA",0,D11*D10) -> 0 | F15: Prepayment penalty | G15: 0 | H15: =H14*G15 -> 0
B16: - Re-Finance Costs | C16: 0.01 | D16: =IF($D$4="NA",0,-C16*D15) -> 0 | F16: Capital Transaction Fee to Mgr | G16: =Summary!D45 -> 0 | H16: =H12*G16 -> 0
B17: - Prepayment Penalty | D17: 0 | F17: Total Equity | H17: =H12+H13+H14+H15-H16+H10+H11 -> 0
B18: - Repay Outstanding Loan Balance | D18: =IF($D$4="NA",0,-OFFSET(Loans!H35,0,$D$4-1)) -> 0 | F18: - Return of Member Capital | H18: =MIN(INDEX(Returns!C5:L5,1,year_sale)-INDEX(Returns!C12:L12,1,year_sale),H17) -> 0
B19: Gross Proceeds from Re-Finance | D19: =IF($D$4="NA",0,SUM(D15:D18)) -> 0 | F19: - Members Preferred Return Deficiency | H19: =MIN(H17-H18,INDEX('P&L'!$D$47:$V$47,1,(year_sale*2)-1)) -> 0
B20: - Capital Transaction Fee to Mgr | C20: 0 | D20: =IF(C20>0,MIN(D15*C20,D19),0) -> 0 | F20: Net Proceeds/Profit from Sale | H20: =H17-H18-H19 -> 0
B21: - Return of Member Capital | D21: =IF($D$4="NA",0,MIN(D19-D20,INDEX(Returns!C5:L5,1,year_refi)-INDEX(Returns!C12:L12,1,year_refi))) -> 0 | F21: Principal Reduction | H21: =OFFSET(Loans!H33,0,$D$5-1)-D25 -> 0
B22: Capital Account Balance After Re-Fi | D22: =IF($D$4="NA",0,INDEX(Returns!C5:L5,1,year_refi)-D21) -> 0 | F22: Appreciation | H22: =IF(H20<=H21,0,H20-H21) -> 0
B23: % of Initial Investment Returned | D23: =IF($D$4="NA",0,1-(D22/Summary!D22)) -> 0 | F23: Net Proceeds/Profit Paid to Members | G23: =Summary!D41 -> 0.8 | H23: =H20*$G$23 -> 0
B24: Net Proceeds/Profit from Re-Finance | D24: =D19-D20-D21 -> 0 | F24: Net Proceeds/Profit Paid to Manager | G24: =Summary!D42 -> 0.2 | H24: =H20*$G$24 -> 0
B25: Principal Reduction | D25: =IF($D$4="NA",0,OFFSET(Loans!H33,0,$D$4-1)) -> 0 | F25: Total Cash to Members at Sale (Init. Cptl. + Apprec.) | H25: =H23+H18+H19 -> 0
B26: Appreciation | D26: =IF($D$4="NA",0,IF(D24=0,0,IF(D24-D25>0,D24-D25,0))) -> 0
B27: Net Proceeds/Profit Paid to Members | C27: =Summary!D41 -> 0.8 | D27: =D24*C27 -> 0 | F27: After Final Disposition
B28: Net Proceeds/Profit Paid to Manager | C28: =Summary!D42 -> 0.2 | D28: =D24*C28 -> 0 | F28: Total Profits from Appreciation Paid to Members | H28: =D27+H23 -> 0
B29: Total Cash to Members at Refi (Init. Cptl. + Apprec.) | D29: =IF($D$4="NA",0,D27+D21) -> 0 | F29: Total Cash to Members | H29: =D29+H25 -> 0
B30: Ending Capital Account Balance | D30: =IF($D$4="NA","",D22) | F30: Internal Rate of Return (IRR) | H30: =Summary!D50 -> 0 | I30: =About!E7
F31: Cash-on-Cash Return | H31: =Summary!D37 -> 0 | I31: =About!E10
B32: =copyright -> Copyright © 2026 Michael Blank.
B33: The information herein is not guaranteed but believed to be accurate.

Sheet Returns
B1: Projected Returns
C3: =IF(C4=year_refi,"REFINANCE!",IF(C4=year_sale,"SALE!","")) | D3: =IF(D4=year_refi,"REFINANCE!",IF(D4=year_sale,"SALE!","")) | E3: =IF(E4=year_refi,"REFINANCE!",IF(E4=year_sale,"SALE!","")) | F3: =IF(F4=year_refi,"REFINANCE!",IF(F4=year_sale,"SALE!","")) | G3: =IF(G4=year_refi,"REFINANCE!",IF(G4=year_sale,"SALE!","")) -> SALE! | H3: =IF(H4=year_refi,"REFINANCE!",IF(H4=year_sale,"SALE!","")) | I3: =IF(I4=year_refi,"REFINANCE!",IF(I4=year_sale,"SALE!","")) | J3: =IF(J4=year_refi,"REFINANCE!",IF(J4=year_sale,"SALE!","")) | ... L3: =IF(L4=year_refi,"REFINANCE!",IF(L4=year_sale,"SALE!",""))
B4: Projected Member Cash Flows and Returns | C4: 1 | D4: =C4+1 -> 2 | E4: =D4+1 -> 3 | F4: =E4+1 -> 4 | G4: =F4+1 -> 5 | H4: =G4+1 -> 6 | I4: =H4+1 -> 7 | J4: =I4+1 -> 8 | K4: =J4+1 -> 9 | L4: =K4+1 -> 10 | M4: Return $ | N4: Return %
B5: Beginning Member Capital Account Balance | C5: =Summary!$D$22 -> 0 | D5: =C$14 -> 0 | E5: =D$14 -> 0 | F5: =E$14 -> 0 | G5: =F$14 -> 0 | H5: =G$14 -> 0 | I5: =H$14 -> 0 | J5: =I$14 -> 0 | K5: =J$14 -> 0 | L5: =K$14 -> 0
B6: Member Cash Flow | C6: ='P&L'!D$51 -> 0 | D6: ='P&L'!F$51 -> 0 | E6: ='P&L'!H$51 -> 0 | F6: ='P&L'!J$51 -> 0 | G6: ='P&L'!L$51 -> 0 | H6: ='P&L'!N$51 -> 0 | I6: ='P&L'!P$51 -> 0 | J6: ='P&L'!R$51 -> 0 | K6: ='P&L'!T$51 -> 0 | L6: ='P&L'!V$51 -> 0 | M6: =SUM(C6:L6) -> 0
B7: Cash-on-Cash Return | C7: =IF(C$4<=year_sale,IF(C$5=0,"∞",C$6/C$5),0) -> ∞ | D7: =IF(D$4<=year_sale,IF(D$5=0,"∞",D$6/D$5),0) -> ∞ | E7: =IF(E$4<=year_sale,IF(E$5=0,"∞",E$6/E$5),0) -> ∞ | F7: =IF(F$4<=year_sale,IF(F$5=0,"∞",F$6/F$5),0) -> ∞ | G7: =IF(G$4<=year_sale,IF(G$5=0,"∞",G$6/G$5),0) -> ∞ | H7: =IF(H$4<=year_sale,IF(H$5=0,"∞",H$6/H$5),0) -> 0 | I7: =IF(I$4<=year_sale,IF(I$5=0,"∞",I$6/I$5),0) -> 0 | J7: =IF(J$4<=year_sale,IF(J$5=0,"∞",J$6/J$5),0) -> 0 | ... L7: =IF(L$4<=year_sale,IF(L$5=0,"∞",L$6/L$5),0) -> 0
B8: Average Cash-on-Cash Return to Date | C8: =IF(C$4<=year_sale,IF(C7="∞","∞",AVERAGE($C$7:C7)),0) -> ∞ | D8: =IF(D$4<=year_sale,IF(D7="∞","∞",AVERAGE($C$7:D7)),0) -> ∞ | E8: =IF(E$4<=year_sale,IF(E7="∞","∞",AVERAGE($C$7:E7)),0) -> ∞ | F8: =IF(F$4<=year_sale,IF(F7="∞","∞",AVERAGE($C$7:F7)),0) -> ∞ | G8: =IF(G$4<=year_sale,IF(G7="∞","∞",AVERAGE($C$7:G7)),0) -> ∞ | H8: =IF(H$4<=year_sale,IF(H7="∞","∞",AVERAGE($C$7:H7)),0) -> 0 | I8: =IF(I$4<=year_sale,IF(I7="∞","∞",AVERAGE($C$7:I7)),0) -> 0 | J8: =IF(J$4<=year_sale,IF(J7="∞","∞",AVERAGE($C$7:J7)),0) -> 0 | ... L8: =IF(L$4<=year_sale,IF(L7="∞","∞",AVERAGE($C$7:L7)),0) -> 0
B9: Preferred Return Deficiency | C9: =IF(C4=year_sale,'Exit Strategy'!$H$19,0) -> 0 | D9: =IF(D4=year_sale,'Exit Strategy'!$H$19,0) -> 0 | E9: =IF(E4=year_sale,'Exit Strategy'!$H$19,0) -> 0 | F9: =IF(F4=year_sale,'Exit Strategy'!$H$19,0) -> 0 | G9: =IF(G4=year_sale,'Exit Strategy'!$H$19,0) -> 0 | H9: =IF(H4=year_sale,'Exit Strategy'!$H$19,0) -> 0 | I9: =IF(I4=year_sale,'Exit Strategy'!$H$19,0) -> 0 | J9: =IF(J4=year_sale,'Exit Strategy'!$H$19,0) -> 0 | ... L9: =IF(L4=year_sale,'Exit Strategy'!$H$19,0) -> 0 | M9: =SUM(C9:L9) -> 0
B10: Net Proceeds/Profits from Refinance or Sale | C10: =IF(C$4=year_refi,'Exit Strategy'!$D$27,IF(C$4=year_sale,'Exit Strategy'!$H$23,0)) -> 0 | D10: =IF(D$4=year_refi,'Exit Strategy'!$D$27,IF(D$4=year_sale,'Exit Strategy'!$H$23,0)) -> 0 | E10: =IF(E$4=year_refi,'Exit Strategy'!$D$27,IF(E$4=year_sale,'Exit Strategy'!$H$23,0)) -> 0 | F10: =IF(F$4=year_refi,'Exit Strategy'!$D$27,IF(F$4=year_sale,'Exit Strategy'!$H$23,0)) -> 0 | G10: =IF(G$4=year_refi,'Exit Strategy'!$D$27,IF(G$4=year_sale,'Exit Strategy'!$H$23,0)) -> 0 | H10: =IF(H$4=year_refi,'Exit Strategy'!$D$27,IF(H$4=year_sale,'Exit Strategy'!$H$23,0)) -> 0 | I10: =IF(I$4=year_refi,'Exit Strategy'!$D$27,IF(I$4=year_sale,'Exit Strategy'!$H$23,0)) -> 0 | J10: =IF(J$4=year_refi,'Exit Strategy'!$D$27,IF(J$4=year_sale,'Exit Strategy'!$H$23,0)) -> 0 | ... L10: =IF(L$4=year_refi,'Exit Strategy'!$D$27,IF(L$4=year_sale,'Exit Strategy'!$H$23,0)) -> 0 | M10: =SUM(C10:L10) -> 0
B11: Average Annual Return to Date | C11: =IFERROR(IF(C$4<=year_sale,(SUM($C$6:C6)+SUM($C$10:C10)+C9)/$C$5/C$4,0),0) -> 0 | D11: =IFERROR(IF(D$4<=year_sale,(SUM($C$6:D6)+SUM($C$10:D10)+D9)/$C$5/D$4,0),0) -> 0 | E11: =IFERROR(IF(E$4<=year_sale,(SUM($C$6:E6)+SUM($C$10:E10)+E9)/$C$5/E$4,0),0) -> 0 | F11: =IFERROR(IF(F$4<=year_sale,(SUM($C$6:F6)+SUM($C$10:F10)+F9)/$C$5/F$4,0),0) -> 0 | G11: =IFERROR(IF(G$4<=year_sale,(SUM($C$6:G6)+SUM($C$10:G10)+G9)/$C$5/G$4,0),0) -> 0 | H11: =IFERROR(IF(H$4<=year_sale,(SUM($C$6:H6)+SUM($C$10:H10)+H9)/$C$5/H$4,0),0) -> 0 | I11: =IFERROR(IF(I$4<=year_sale,(SUM($C$6:I6)+SUM($C$10:I10)+I9)/$C$5/I$4,0),0) -> 0 | J11: =IFERROR(IF(J$4<=year_sale,(SUM($C$6:J6)+SUM($C$10:J10)+J9)/$C$5/J$4,0),0) -> 0 | ... L11: =IFERROR(IF(L$4<=year_sale,(SUM($C$6:L6)+SUM($C$10:L10)+L9)/$C$5/L$4,0),0) -> 0
B12: Return of Member Capital - P/I Escrow | C12: =IF(C$4>year_sale,0,IF(C$4=IF('Acquisition Costs'!$C$43<=0,year_sale,MIN('Acquisition Costs'!$C$43,year_sale)),'Acquisition Costs'!$D$44,0)) -> 0 | D12: =IF(D$4>year_sale,0,IF(D$4=IF('Acquisition Costs'!$C$43<=0,year_sale,MIN('Acquisition Costs'!$C$43,year_sale)),'Acquisition Costs'!$D$44,0)) -> 0 | E12: =IF(E$4>year_sale,0,IF(E$4=IF('Acquisition Costs'!$C$43<=0,year_sale,MIN('Acquisition Costs'!$C$43,year_sale)),'Acquisition Costs'!$D$44,0)) -> 0 | F12: =IF(F$4>year_sale,0,IF(F$4=IF('Acquisition Costs'!$C$43<=0,year_sale,MIN('Acquisition Costs'!$C$43,year_sale)),'Acquisition Costs'!$D$44,0)) -> 0 | G12: =IF(G$4>year_sale,0,IF(G$4=IF('Acquisition Costs'!$C$43<=0,year_sale,MIN('Acquisition Costs'!$C$43,year_sale)),'Acquisition Costs'!$D$44,0)) -> 0 | H12: =IF(H$4>year_sale,0,IF(H$4=IF('Acquisition Costs'!$C$43<=0,year_sale,MIN('Acquisition Costs'!$C$43,year_sale)),'Acquisition Costs'!$D$44,0)) -> 0 | I12: =IF(I$4>year_sale,0,IF(I$4=IF('Acquisition Costs'!$C$43<=0,year_sale,MIN('Acquisition Costs'!$C$43,year_sale)),'Acquisition Costs'!$D$44,0)) -> 0 | J12: =IF(J$4>year_sale,0,IF(J$4=IF('Acquisition Costs'!$C$43<=0,year_sale,MIN('Acquisition Costs'!$C$43,year_sale)),'Acquisition Costs'!$D$44,0)) -> 0 | ... L12: =IF(L$4>year_sale,0,IF(L$4=IF('Acquisition Costs'!$C$43<=0,year_sale,MIN('Acquisition Costs'!$C$43,year_sale)),'Acquisition Costs'!$D$44,0)) -> 0
B13: Return of Member Capital - Refinance or Sale | C13: =IF(C$4=year_refi,'Exit Strategy'!$D$21,IF(C$4=year_sale,'Exit Strategy'!$H$18,0)) -> 0 | D13: =IF(D$4=year_refi,'Exit Strategy'!$D$21,IF(D$4=year_sale,'Exit Strategy'!$H$18,0)) -> 0 | E13: =IF(E$4=year_refi,'Exit Strategy'!$D$21,IF(E$4=year_sale,'Exit Strategy'!$H$18,0)) -> 0 | F13: =IF(F$4=year_refi,'Exit Strategy'!$D$21,IF(F$4=year_sale,'Exit Strategy'!$H$18,0)) -> 0 | G13: =IF(G$4=year_refi,'Exit Strategy'!$D$21,IF(G$4=year_sale,'Exit Strategy'!$H$18,0)) -> 0 | H13: =IF(H$4=year_refi,'Exit Strategy'!$D$21,IF(H$4=year_sale,'Exit Strategy'!$H$18,0)) -> 0 | I13: =IF(I$4=year_refi,'Exit Strategy'!$D$21,IF(I$4=year_sale,'Exit Strategy'!$H$18,0)) -> 0 | J13: =IF(J$4=year_refi,'Exit Strategy'!$D$21,IF(J$4=year_sale,'Exit Strategy'!$H$18,0)) -> 0 | ... L13: =IF(L$4=year_refi,'Exit Strategy'!$D$21,IF(L$4=year_sale,'Exit Strategy'!$H$18,0)) -> 0
B14: Ending Member Capital Account Balance | C14: =C$5-MAX(C$12,0)-MAX(MIN(C$13,0),C$13) -> 0 | D14: =D$5-MAX(D$12,0)-MAX(MIN(D$13,0),D$13) -> 0 | E14: =E$5-MAX(E$12,0)-MAX(MIN(E$13,0),E$13) -> 0 | F14: =F$5-MAX(F$12,0)-MAX(MIN(F$13,0),F$13) -> 0 | G14: =G$5-MAX(G$12,0)-MAX(MIN(G$13,0),G$13) -> 0 | H14: =H$5-MAX(H$12,0)-MAX(MIN(H$13,0),H$13) -> 0 | I14: =I$5-MAX(I$12,0)-MAX(MIN(I$13,0),I$13) -> 0 | J14: =J$5-MAX(J$12,0)-MAX(MIN(J$13,0),J$13) -> 0 | ... L14: =L$5-MAX(L$12,0)-MAX(MIN(L$13,0),L$13) -> 0
B15: Total Return on Investment | C15: =C$6+C9+MAX(MIN(C$10,0),C$10) -> 0 | D15: =D$6+D9+MAX(MIN(D$10,0),D$10) -> 0 | E15: =E$6+E9+MAX(MIN(E$10,0),E$10) -> 0 | F15: =F$6+F9+MAX(MIN(F$10,0),F$10) -> 0 | G15: =G$6+G9+MAX(MIN(G$10,0),G$10) -> 0 | H15: =H$6+H9+MAX(MIN(H$10,0),H$10) -> 0 | I15: =I$6+I9+MAX(MIN(I$10,0),I$10) -> 0 | J15: =J$6+J9+MAX(MIN(J$10,0),J$10) -> 0 | ... L15: =L$6+L9+MAX(MIN(L$10,0),L$10) -> 0 | M15: =SUM(M5:M14) -> 0 | N15: =IF(C5=0,0,M15/C5) -> 0
B16: =CONCATENATE("Average Annual Return",IF(Variables!$F$18="Yes","","")) -> Average Annual Return | N16: =OFFSET(C$11,0,year_sale-1) -> 0 | O16: =About!E6
B17: IRR | N17: =IRR!$J$58 -> 0 | O17: =About!E7
B18: Cash-on-Cash Return | N18: =IFERROR(AVERAGEIF(C4:L4,"<=" & year_sale,C7:L7),0) -> 0 | O18: =About!E10
B19: Equity Multiple | N19: =IF(C5=0,0,SUM(C6:L6,C9:L9,C10:L10,C12:L13)/C5) -> 0
B21: Projected Manager Cash Flows and Returns | C21: 1 | D21: =C21+1 -> 2 | E21: =D21+1 -> 3 | F21: =E21+1 -> 4 | G21: =F21+1 -> 5 | H21: =G21+1 -> 6 | I21: =H21+1 -> 7 | J21: =I21+1 -> 8 | K21: =J21+1 -> 9 | L21: =K21+1 -> 10 | M21: TOTAL
B22: Manager Compensation
B23: Distributions from Cash Flow | C23: =IF('P&L'!D51=0,0,'P&L'!D50) -> 0 | D23: =IF('P&L'!F51=0,0,'P&L'!F50) -> 0 | E23: =IF('P&L'!H51=0,0,'P&L'!H50) -> 0 | F23: =IF('P&L'!J51=0,0,'P&L'!J50) -> 0 | G23: =IF('P&L'!L51=0,0,'P&L'!L50) -> 0 | H23: =IF('P&L'!N51=0,0,'P&L'!N50) -> 0 | I23: =IF('P&L'!P51=0,0,'P&L'!P50) -> 0 | J23: =IF('P&L'!R51=0,0,'P&L'!R50) -> 0 | K23: =IF('P&L'!T51=0,0,'P&L'!T50) -> 0 | L23: =IF('P&L'!V51=0,0,'P&L'!V50) -> 0 | M23: =SUM(C23:L23) -> 0
B24: Acquisitions Fee | C24: =Summary!D19 -> 0 | M24: =SUM(C24:L24) -> 0
B25: Asset Management Fees | C25: =IF(C$4<=year_sale,'P&L'!D45,0) -> 0 | D25: =IF(D$4<=year_sale,'P&L'!F45,0) -> 0 | E25: =IF(E$4<=year_sale,'P&L'!H45,0) -> 0 | F25: =IF(F$4<=year_sale,'P&L'!J45,0) -> 0 | G25: =IF(G$4<=year_sale,'P&L'!L45,0) -> 0 | H25: =IF(H$4<=year_sale,'P&L'!N45,0) -> 0 | I25: =IF(I$4<=year_sale,'P&L'!P45,0) -> 0 | J25: =IF(J$4<=year_sale,'P&L'!R45,0) -> 0 | K25: =IF(K$4<=year_sale,'P&L'!T45,0) -> 0 | L25: =IF(L$4<=year_sale,'P&L'!V45,0) -> 0 | M25: =SUM(C25:L25) -> 0
B26: Capital Transaction Fee | C26: =IF(C4=year_refi,'Exit Strategy'!$D$20,IF(C4=year_sale,'Exit Strategy'!$H$16,0)) -> 0 | D26: =IF(D4=year_refi,'Exit Strategy'!$D$20,IF(D4=year_sale,'Exit Strategy'!$H$16,0)) -> 0 | E26: =IF(E4=year_refi,'Exit Strategy'!$D$20,IF(E4=year_sale,'Exit Strategy'!$H$16,0)) -> 0 | F26: =IF(F4=year_refi,'Exit Strategy'!$D$20,IF(F4=year_sale,'Exit Strategy'!$H$16,0)) -> 0 | G26: =IF(G4=year_refi,'Exit Strategy'!$D$20,IF(G4=year_sale,'Exit Strategy'!$H$16,0)) -> 0 | H26: =IF(H4=year_refi,'Exit Strategy'!$D$20,IF(H4=year_sale,'Exit Strategy'!$H$16,0)) -> 0 | I26: =IF(I4=year_refi,'Exit Strategy'!$D$20,IF(I4=year_sale,'Exit Strategy'!$H$16,0)) -> 0 | J26: =IF(J4=year_refi,'Exit Strategy'!$D$20,IF(J4=year_sale,'Exit Strategy'!$H$16,0)) -> 0 | ... L26: =IF(L4=year_refi,'Exit Strategy'!$D$20,IF(L4=year_sale,'Exit Strategy'!$H$16,0)) -> 0 | M26: =SUM(C26:L26) -> 0
B27: Net Proceeds from Refinance or Sale | C27: =IF(C4=year_refi,'Exit Strategy'!$D$28,IF(C4=year_sale,'Exit Strategy'!$H$24,0)) -> 0 | D27: =IF(D4=year_refi,'Exit Strategy'!$D$28,IF(D4=year_sale,'Exit Strategy'!$H$24,0)) -> 0 | E27: =IF(E4=year_refi,'Exit Strategy'!$D$28,IF(E4=year_sale,'Exit Strategy'!$H$24,0)) -> 0 | F27: =IF(F4=year_refi,'Exit Strategy'!$D$28,IF(F4=year_sale,'Exit Strategy'!$H$24,0)) -> 0 | G27: =IF(G4=year_refi,'Exit Strategy'!$D$28,IF(G4=year_sale,'Exit Strategy'!$H$24,0)) -> 0 | H27: =IF(H4=year_refi,'Exit Strategy'!$D$28,IF(H4=year_sale,'Exit Strategy'!$H$24,0)) -> 0 | I27: =IF(I4=year_refi,'Exit Strategy'!$D$28,IF(I4=year_sale,'Exit Strategy'!$H$24,0)) -> 0 | J27: =IF(J4=year_refi,'Exit Strategy'!$D$28,IF(J4=year_sale,'Exit Strategy'!$H$24,0)) -> 0 | ... L27: =IF(L4=year_refi,'Exit Strategy'!$D$28,IF(L4=year_sale,'Exit Strategy'!$H$24,0)) -> 0 | M27: =SUM(C27:L27) -> 0
B28: Total Manager Compensation | C28: =SUM(C23:C27) -> 0 | D28: =SUM(D23:D27) -> 0 | E28: =SUM(E23:E27) -> 0 | F28: =SUM(F23:F27) -> 0 | G28: =SUM(G23:G27) -> 0 | H28: =SUM(H23:H27) -> 0 | I28: =SUM(I23:I27) -> 0 | J28: =SUM(J23:J27) -> 0 | ... M28: =SUM(M23:M27) -> 0
B29: =B110 -> Partner 1 | C29: =SUM(C30:C34) -> 0 | D29: =SUM(D30:D34) -> 0 | E29: =SUM(E30:E34) -> 0 | F29: =SUM(F30:F34) -> 0 | G29: =SUM(G30:G34) -> 0 | H29: =SUM(H30:H34) -> 0 | I29: =SUM(I30:I34) -> 0 | J29: =SUM(J30:J34) -> 0 | ... M29: =SUM(M30:M34) -> 0
B30: =B23 -> Distributions from Cash Flow | C30: =C$23*$E$171 -> 0 | D30: =D$23*$E$171 -> 0 | E30: =E$23*$E$171 -> 0 | F30: =F$23*$E$171 -> 0 | G30: =G$23*$E$171 -> 0 | H30: =H$23*$E$171 -> 0 | I30: =I$23*$E$171 -> 0 | J30: =J$23*$E$171 -> 0 | ... M30: =M$23*$E$171 -> 0
B31: =B24 -> Acquisitions Fee | C31: =C$24*$E$171 -> 0 | D31: =D$24*$E$171 -> 0 | E31: =E$24*$E$171 -> 0 | F31: =F$24*$E$171 -> 0 | G31: =G$24*$E$171 -> 0 | H31: =H$24*$E$171 -> 0 | I31: =I$24*$E$171 -> 0 | J31: =J$24*$E$171 -> 0 | ... M31: =M$24*$E$171 -> 0
B32: Asset Management Fees | C32: =C$25*$D$150 -> 0 | D32: =D$25*$D$150 -> 0 | E32: =E$25*$D$150 -> 0 | F32: =F$25*$D$150 -> 0 | G32: =G$25*$D$150 -> 0 | H32: =H$25*$D$150 -> 0 | I32: =I$25*$D$150 -> 0 | J32: =J$25*$D$150 -> 0 | ... M32: =M$25*$D$150 -> 0
B33: =B26 -> Capital Transaction Fee | C33: =C$26*$E$171 -> 0 | D33: =D$26*$E$171 -> 0 | E33: =E$26*$E$171 -> 0 | F33: =F$26*$E$171 -> 0 | G33: =G$26*$E$171 -> 0 | H33: =H$26*$E$171 -> 0 | I33: =I$26*$E$171 -> 0 | J33: =J$26*$E$171 -> 0 | ... M33: =M$26*$E$171 -> 0
B34: =B27 -> Net Proceeds from Refinance or Sale | C34: =C$27*$E$171 -> 0 | D34: =D$27*$E$171 -> 0 | E34: =E$27*$E$171 -> 0 | F34: =F$27*$E$171 -> 0 | G34: =G$27*$E$171 -> 0 | H34: =H$27*$E$171 -> 0 | I34: =I$27*$E$171 -> 0 | J34: =J$27*$E$171 -> 0 | ... M34: =M$27*$E$171 -> 0
B35: =B111 -> Partner 2 | C35: =SUM(C36:C40) -> 0 | D35: =SUM(D36:D40) -> 0 | E35: =SUM(E36:E40) -> 0 | F35: =SUM(F36:F40) -> 0 | G35: =SUM(G36:G40) -> 0 | H35: =SUM(H36:H40) -> 0 | I35: =SUM(I36:I40) -> 0 | J35: =SUM(J36:J40) -> 0 | ... M35: =SUM(M36:M40) -> 0
B36: =B30 -> Distributions from Cash Flow | C36: =C$23*$E$172 -> 0 | D36: =D$23*$E$172 -> 0 | E36: =E$23*$E$172 -> 0 | F36: =F$23*$E$172 -> 0 | G36: =G$23*$E$172 -> 0 | H36: =H$23*$E$172 -> 0 | I36: =I$23*$E$172 -> 0 | J36: =J$23*$E$172 -> 0 | ... M36: =M$23*$E$172 -> 0
B37: =B31 -> Acquisitions Fee | C37: =C$24*$E$172 -> 0 | D37: =D$24*$E$172 -> 0 | E37: =E$24*$E$172 -> 0 | F37: =F$24*$E$172 -> 0 | G37: =G$24*$E$172 -> 0 | H37: =H$24*$E$172 -> 0 | I37: =I$24*$E$172 -> 0 | J37: =J$24*$E$172 -> 0 | ... M37: =M$24*$E$172 -> 0
B38: Asset Management Fees | C38: =C$25*$D$151 -> 0 | D38: =D$25*$D$151 -> 0 | E38: =E$25*$D$151 -> 0 | F38: =F$25*$D$151 -> 0 | G38: =G$25*$D$151 -> 0 | H38: =H$25*$D$151 -> 0 | I38: =I$25*$D$151 -> 0 | J38: =J$25*$D$151 -> 0 | ... M38: =M$25*$D$151 -> 0
B39: Capital Transaction Fee | C39: =C$26*$E$172 -> 0 | D39: =D$26*$E$172 -> 0 | E39: =E$26*$E$172 -> 0 | F39: =F$26*$E$172 -> 0 | G39: =G$26*$E$172 -> 0 | H39: =H$26*$E$172 -> 0 | I39: =I$26*$E$172 -> 0 | J39: =J$26*$E$172 -> 0 | ... M39: =M$26*$E$172 -> 0
B40: Net Proceeds/Profits from Refinance or Sale | C40: =C$27*$E$172 -> 0 | D40: =D$27*$E$172 -> 0 | E40: =E$27*$E$172 -> 0 | F40: =F$27*$E$172 -> 0 | G40: =G$27*$E$172 -> 0 | H40: =H$27*$E$172 -> 0 | I40: =I$27*$E$172 -> 0 | J40: =J$27*$E$172 -> 0 | ... M40: =M$27*$E$172 -> 0
B41: =B112 -> Partner 3 | C41: =SUM(C42:C46) -> 0 | D41: =SUM(D42:D46) -> 0 | E41: =SUM(E42:E46) -> 0 | F41: =SUM(F42:F46) -> 0 | G41: =SUM(G42:G46) -> 0 | H41: =SUM(H42:H46) -> 0 | I41: =SUM(I42:I46) -> 0 | J41: =SUM(J42:J46) -> 0 | ... M41: =SUM(M42:M46) -> 0
B42: =B36 -> Distributions from Cash Flow | C42: =C$23*$E$173 -> 0 | D42: =D$23*$E$173 -> 0 | E42: =E$23*$E$173 -> 0 | F42: =F$23*$E$173 -> 0 | G42: =G$23*$E$173 -> 0 | H42: =H$23*$E$173 -> 0 | I42: =I$23*$E$173 -> 0 | J42: =J$23*$E$173 -> 0 | ... M42: =M$23*$E$173 -> 0
B43: =B37 -> Acquisitions Fee | C43: =C$24*$E$173 -> 0 | D43: =D$24*$E$173 -> 0 | E43: =E$24*$E$173 -> 0 | F43: =F$24*$E$173 -> 0 | G43: =G$24*$E$173 -> 0 | H43: =H$24*$E$173 -> 0 | I43: =I$24*$E$173 -> 0 | J43: =J$24*$E$173 -> 0 | ... M43: =M$24*$E$173 -> 0
B44: Asset Management Fees | C44: =C$25*$D$152 -> 0 | D44: =D$25*$D$152 -> 0 | E44: =E$25*$D$152 -> 0 | F44: =F$25*$D$152 -> 0 | G44: =G$25*$D$152 -> 0 | H44: =H$25*$D$152 -> 0 | I44: =I$25*$D$152 -> 0 | J44: =J$25*$D$152 -> 0 | ... M44: =M$25*$D$152 -> 0
B45: Capital Transaction Fee | C45: =C$26*$E$173 -> 0 | D45: =D$26*$E$173 -> 0 | E45: =E$26*$E$173 -> 0 | F45: =F$26*$E$173 -> 0 | G45: =G$26*$E$173 -> 0 | H45: =H$26*$E$173 -> 0 | I45: =I$26*$E$173 -> 0 | J45: =J$26*$E$173 -> 0 | ... M45: =M$26*$E$173 -> 0
B46: Net Proceeds/Profits from Refinance or Sale | C46: =C$27*$E$173 -> 0 | D46: =D$27*$E$173 -> 0 | E46: =E$27*$E$173 -> 0 | F46: =F$27*$E$173 -> 0 | G46: =G$27*$E$173 -> 0 | H46: =H$27*$E$173 -> 0 | I46: =I$27*$E$173 -> 0 | J46: =J$27*$E$173 -> 0 | ... M46: =M$27*$E$173 -> 0
B47: =B113 -> Partner 4 | C47: =SUM(C48:C52) -> 0 | D47: =SUM(D48:D52) -> 0 | E47: =SUM(E48:E52) -> 0 | F47: =SUM(F48:F52) -> 0 | G47: =SUM(G48:G52) -> 0 | H47: =SUM(H48:H52) -> 0 | I47: =SUM(I48:I52) -> 0 | J47: =SUM(J48:J52) -> 0 | ... M47: =SUM(M48:M52) -> 0
B48: =B42 -> Distributions from Cash Flow | C48: =C$23*$E$174 -> 0 | D48: =D$23*$E$174 -> 0 | E48: =E$23*$E$174 -> 0 | F48: =F$23*$E$174 -> 0 | G48: =G$23*$E$174 -> 0 | H48: =H$23*$E$174 -> 0 | I48: =I$23*$E$174 -> 0 | J48: =J$23*$E$174 -> 0 | ... M48: =M$23*$E$174 -> 0
B49: =B43 -> Acquisitions Fee | C49: =C$24*$E$174 -> 0 | D49: =D$24*$E$174 -> 0 | E49: =E$24*$E$174 -> 0 | F49: =F$24*$E$174 -> 0 | G49: =G$24*$E$174 -> 0 | H49: =H$24*$E$174 -> 0 | I49: =I$24*$E$174 -> 0 | J49: =J$24*$E$174 -> 0 | ... M49: =M$24*$E$174 -> 0
B50: Asset Management Fees | C50: =C$25*$D$153 -> 0 | D50: =D$25*$D$153 -> 0 | E50: =E$25*$D$153 -> 0 | F50: =F$25*$D$153 -> 0 | G50: =G$25*$D$153 -> 0 | H50: =H$25*$D$153 -> 0 | I50: =I$25*$D$153 -> 0 | J50: =J$25*$D$153 -> 0 | ... M50: =M$25*$D$153 -> 0
B51: Capital Transaction Fee | C51: =C$26*$E$174 -> 0 | D51: =D$26*$E$174 -> 0 | E51: =E$26*$E$174 -> 0 | F51: =F$26*$E$174 -> 0 | G51: =G$26*$E$174 -> 0 | H51: =H$26*$E$174 -> 0 | I51: =I$26*$E$174 -> 0 | J51: =J$26*$E$174 -> 0 | ... M51: =M$26*$E$174 -> 0
B52: Net Proceeds/Profits from Refinance or Sale | C52: =C$27*$E$174 -> 0 | D52: =D$27*$E$174 -> 0 | E52: =E$27*$E$174 -> 0 | F52: =F$27*$E$174 -> 0 | G52: =G$27*$E$174 -> 0 | H52: =H$27*$E$174 -> 0 | I52: =I$27*$E$174 -> 0 | J52: =J$27*$E$174 -> 0 | ... M52: =M$27*$E$174 -> 0
B53: =B114 -> Partner 5 | C53: =SUM(C54:C58) -> 0 | D53: =SUM(D54:D58) -> 0 | E53: =SUM(E54:E58) -> 0 | F53: =SUM(F54:F58) -> 0 | G53: =SUM(G54:G58) -> 0 | H53: =SUM(H54:H58) -> 0 | I53: =SUM(I54:I58) -> 0 | J53: =SUM(J54:J58) -> 0 | ... M53: =SUM(M54:M58) -> 0
B54: =B48 -> Distributions from Cash Flow | C54: =C$23*$E$175 -> 0 | D54: =D$23*$E$175 -> 0 | E54: =E$23*$E$175 -> 0 | F54: =F$23*$E$175 -> 0 | G54: =G$23*$E$175 -> 0 | H54: =H$23*$E$175 -> 0 | I54: =I$23*$E$175 -> 0 | J54: =J$23*$E$175 -> 0 | ... M54: =M$23*$E$175 -> 0
B55: =B49 -> Acquisitions Fee | C55: =C$24*$E$175 -> 0 | D55: =D$24*$E$175 -> 0 | E55: =E$24*$E$175 -> 0 | F55: =F$24*$E$175 -> 0 | G55: =G$24*$E$175 -> 0 | H55: =H$24*$E$175 -> 0 | I55: =I$24*$E$175 -> 0 | J55: =J$24*$E$175 -> 0 | ... M55: =M$24*$E$175 -> 0
B56: Asset Management Fees | C56: =C$25*$D$154 -> 0 | D56: =D$25*$D$154 -> 0 | E56: =E$25*$D$154 -> 0 | F56: =F$25*$D$154 -> 0 | G56: =G$25*$D$154 -> 0 | H56: =H$25*$D$154 -> 0 | I56: =I$25*$D$154 -> 0 | J56: =J$25*$D$154 -> 0 | ... M56: =M$25*$D$154 -> 0
B57: Capital Transaction Fee | C57: =C$26*$E$175 -> 0 | D57: =D$26*$E$175 -> 0 | E57: =E$26*$E$175 -> 0 | F57: =F$26*$E$175 -> 0 | G57: =G$26*$E$175 -> 0 | H57: =H$26*$E$175 -> 0 | I57: =I$26*$E$175 -> 0 | J57: =J$26*$E$175 -> 0 | ... M57: =M$26*$E$175 -> 0
B58: Net Proceeds/Profits from Refinance or Sale | C58: =C$27*$E$175 -> 0 | D58: =D$27*$E$175 -> 0 | E58: =E$27*$E$175 -> 0 | F58: =F$27*$E$175 -> 0 | G58: =G$27*$E$175 -> 0 | H58: =H$27*$E$175 -> 0 | I58: =I$27*$E$175 -> 0 | J58: =J$27*$E$175 -> 0 | ... M58: =M$27*$E$175 -> 0
B59: =B115 -> Partner 6 | C59: =SUM(C60:C64) -> 0 | D59: =SUM(D60:D64) -> 0 | E59: =SUM(E60:E64) -> 0 | F59: =SUM(F60:F64) -> 0 | G59: =SUM(G60:G64) -> 0 | H59: =SUM(H60:H64) -> 0 | I59: =SUM(I60:I64) -> 0 | J59: =SUM(J60:J64) -> 0 | ... M59: =SUM(M60:M64) -> 0
B60: =B54 -> Distributions from Cash Flow | C60: =C$23*$E$176 -> 0 | D60: =D$23*$E$176 -> 0 | E60: =E$23*$E$176 -> 0 | F60: =F$23*$E$176 -> 0 | G60: =G$23*$E$176 -> 0 | H60: =H$23*$E$176 -> 0 | I60: =I$23*$E$176 -> 0 | J60: =J$23*$E$176 -> 0 | ... M60: =M$23*$E$176 -> 0
B61: =B55 -> Acquisitions Fee | C61: =C$24*$E$176 -> 0 | D61: =D$24*$E$176 -> 0 | E61: =E$24*$E$176 -> 0 | F61: =F$24*$E$176 -> 0 | G61: =G$24*$E$176 -> 0 | H61: =H$24*$E$176 -> 0 | I61: =I$24*$E$176 -> 0 | J61: =J$24*$E$176 -> 0 | ... M61: =M$24*$E$176 -> 0
B62: Asset Management Fees | C62: =C$25*$D$155 -> 0 | D62: =D$25*$D$155 -> 0 | E62: =E$25*$D$155 -> 0 | F62: =F$25*$D$155 -> 0 | G62: =G$25*$D$155 -> 0 | H62: =H$25*$D$155 -> 0 | I62: =I$25*$D$155 -> 0 | J62: =J$25*$D$155 -> 0 | ... M62: =M$25*$D$155 -> 0
B63: Capital Transaction Fee | C63: =C$26*$E$176 -> 0 | D63: =D$26*$E$176 -> 0 | E63: =E$26*$E$176 -> 0 | F63: =F$26*$E$176 -> 0 | G63: =G$26*$E$176 -> 0 | H63: =H$26*$E$176 -> 0 | I63: =I$26*$E$176 -> 0 | J63: =J$26*$E$176 -> 0 | ... M63: =M$26*$E$176 -> 0
B64: Net Proceeds/Profits from Refinance or Sale | C64: =C$27*$E$176 -> 0 | D64: =D$27*$E$176 -> 0 | E64: =E$27*$E$176 -> 0 | F64: =F$27*$E$176 -> 0 | G64: =G$27*$E$176 -> 0 | H64: =H$27*$E$176 -> 0 | I64: =I$27*$E$176 -> 0 | J64: =J$27*$E$176 -> 0 | ... M64: =M$27*$E$176 -> 0
B65: =B116 -> Partner 7 | C65: =SUM(C66:C70) -> 0 | D65: =SUM(D66:D70) -> 0 | E65: =SUM(E66:E70) -> 0 | F65: =SUM(F66:F70) -> 0 | G65: =SUM(G66:G70) -> 0 | H65: =SUM(H66:H70) -> 0 | I65: =SUM(I66:I70) -> 0 | J65: =SUM(J66:J70) -> 0 | ... M65: =SUM(M66:M70) -> 0
B66: =B60 -> Distributions from Cash Flow | C66: =C$23*$E$177 -> 0 | D66: =D$23*$E$177 -> 0 | E66: =E$23*$E$177 -> 0 | F66: =F$23*$E$177 -> 0 | G66: =G$23*$E$177 -> 0 | H66: =H$23*$E$177 -> 0 | I66: =I$23*$E$177 -> 0 | J66: =J$23*$E$177 -> 0 | ... M66: =M$23*$E$177 -> 0
B67: =B61 -> Acquisitions Fee | C67: =C$24*$E$177 -> 0 | D67: =D$24*$E$177 -> 0 | E67: =E$24*$E$177 -> 0 | F67: =F$24*$E$177 -> 0 | G67: =G$24*$E$177 -> 0 | H67: =H$24*$E$177 -> 0 | I67: =I$24*$E$177 -> 0 | J67: =J$24*$E$177 -> 0 | ... M67: =M$24*$E$177 -> 0
B68: Asset Management Fees | C68: =C$25*$D$156 -> 0 | D68: =D$25*$D$156 -> 0 | E68: =E$25*$D$156 -> 0 | F68: =F$25*$D$156 -> 0 | G68: =G$25*$D$156 -> 0 | H68: =H$25*$D$156 -> 0 | I68: =I$25*$D$156 -> 0 | J68: =J$25*$D$156 -> 0 | ... M68: =M$25*$D$156 -> 0
B69: Capital Transaction Fee | C69: =C$26*$E$177 -> 0 | D69: =D$26*$E$177 -> 0 | E69: =E$26*$E$177 -> 0 | F69: =F$26*$E$177 -> 0 | G69: =G$26*$E$177 -> 0 | H69: =H$26*$E$177 -> 0 | I69: =I$26*$E$177 -> 0 | J69: =J$26*$E$177 -> 0 | ... M69: =M$26*$E$177 -> 0
B70: Net Proceeds/Profits from Refinance or Sale | C70: =C$27*$E$177 -> 0 | D70: =D$27*$E$177 -> 0 | E70: =E$27*$E$177 -> 0 | F70: =F$27*$E$177 -> 0 | G70: =G$27*$E$177 -> 0 | H70: =H$27*$E$177 -> 0 | I70: =I$27*$E$177 -> 0 | J70: =J$27*$E$177 -> 0 | ... M70: =M$27*$E$177 -> 0
B71: =B117 -> Partner 8 | C71: =SUM(C72:C76) -> 0 | D71: =SUM(D72:D76) -> 0 | E71: =SUM(E72:E76) -> 0 | F71: =SUM(F72:F76) -> 0 | G71: =SUM(G72:G76) -> 0 | H71: =SUM(H72:H76) -> 0 | I71: =SUM(I72:I76) -> 0 | J71: =SUM(J72:J76) -> 0 | ... M71: =SUM(M72:M76) -> 0
B72: =B66 -> Distributions from Cash Flow | C72: =C$23*$E$178 -> 0 | D72: =D$23*$E$178 -> 0 | E72: =E$23*$E$178 -> 0 | F72: =F$23*$E$178 -> 0 | G72: =G$23*$E$178 -> 0 | H72: =H$23*$E$178 -> 0 | I72: =I$23*$E$178 -> 0 | J72: =J$23*$E$178 -> 0 | ... M72: =M$23*$E$178 -> 0
B73: =B67 -> Acquisitions Fee | C73: =C$24*$E$178 -> 0 | D73: =D$24*$E$178 -> 0 | E73: =E$24*$E$178 -> 0 | F73: =F$24*$E$178 -> 0 | G73: =G$24*$E$178 -> 0 | H73: =H$24*$E$178 -> 0 | I73: =I$24*$E$178 -> 0 | J73: =J$24*$E$178 -> 0 | ... M73: =M$24*$E$178 -> 0
B74: Asset Management Fees | C74: =C$25*$D$157 -> 0 | D74: =D$25*$D$157 -> 0 | E74: =E$25*$D$157 -> 0 | F74: =F$25*$D$157 -> 0 | G74: =G$25*$D$157 -> 0 | H74: =H$25*$D$157 -> 0 | I74: =I$25*$D$157 -> 0 | J74: =J$25*$D$157 -> 0 | ... M74: =M$25*$D$157 -> 0
B75: Capital Transaction Fee | C75: =C$26*$E$178 -> 0 | D75: =D$26*$E$178 -> 0 | E75: =E$26*$E$178 -> 0 | F75: =F$26*$E$178 -> 0 | G75: =G$26*$E$178 -> 0 | H75: =H$26*$E$178 -> 0 | I75: =I$26*$E$178 -> 0 | J75: =J$26*$E$178 -> 0 | ... M75: =M$26*$E$178 -> 0
B76: Net Proceeds/Profits from Refinance or Sale | C76: =C$27*$E$178 -> 0 | D76: =D$27*$E$178 -> 0 | E76: =E$27*$E$178 -> 0 | F76: =F$27*$E$178 -> 0 | G76: =G$27*$E$178 -> 0 | H76: =H$27*$E$178 -> 0 | I76: =I$27*$E$178 -> 0 | J76: =J$27*$E$178 -> 0 | ... M76: =M$27*$E$178 -> 0
B78: Summary of Combined Cash Flows and Returns | C78: 1 | D78: =C78+1 -> 2 | E78: =D78+1 -> 3 | F78: =E78+1 -> 4 | G78: =F78+1 -> 5 | H78: =G78+1 -> 6 | I78: =H78+1 -> 7 | J78: =I78+1 -> 8 | K78: =J78+1 -> 9 | L78: =K78+1 -> 10 | M78: Return $ | N78: Return %
B79: Total Combined Cash flow | C79: =C6+C23 -> 0 | D79: =D6+D23 -> 0 | E79: =E6+E23 -> 0 | F79: =F6+F23 -> 0 | G79: =G6+G23 -> 0 | H79: =H6+H23 -> 0 | I79: =I6+I23 -> 0 | J79: =J6+J23 -> 0 | ... L79: =L6+L23 -> 0 | M79: =SUM(C79:L79) -> 0
B80: Cash-on-Cash Return | C80: =IF(C$4<=year_sale,IF(C$5=0,"∞",C79/C$5),0) -> ∞ | D80: =IF(D$4<=year_sale,IF(D$5=0,"∞",D79/D$5),0) -> ∞ | E80: =IF(E$4<=year_sale,IF(E$5=0,"∞",E79/E$5),0) -> ∞ | F80: =IF(F$4<=year_sale,IF(F$5=0,"∞",F79/F$5),0) -> ∞ | G80: =IF(G$4<=year_sale,IF(G$5=0,"∞",G79/G$5),0) -> ∞ | H80: =IF(H$4<=year_sale,IF(H$5=0,"∞",H79/H$5),0) -> 0 | I80: =IF(I$4<=year_sale,IF(I$5=0,"∞",I79/I$5),0) -> 0 | J80: =IF(J$4<=year_sale,IF(J$5=0,"∞",J79/J$5),0) -> 0 | ... L80: =IF(L$4<=year_sale,IF(L$5=0,"∞",L79/L$5),0) -> 0
B81: Average Cash-on-Cash Return to Date | C81: =IF(C$4<=year_sale,IF(C80="∞","∞",AVERAGE($C$80:C80)),0) -> ∞ | D81: =IF(D$4<=year_sale,IF(D80="∞","∞",AVERAGE($C$80:D80)),0) -> ∞ | E81: =IF(E$4<=year_sale,IF(E80="∞","∞",AVERAGE($C$80:E80)),0) -> ∞ | F81: =IF(F$4<=year_sale,IF(F80="∞","∞",AVERAGE($C$80:F80)),0) -> ∞ | G81: =IF(G$4<=year_sale,IF(G80="∞","∞",AVERAGE($C$80:G80)),0) -> ∞ | H81: =IF(H$4<=year_sale,IF(H80="∞","∞",AVERAGE($C$80:H80)),0) -> 0 | I81: =IF(I$4<=year_sale,IF(I80="∞","∞",AVERAGE($C$80:I80)),0) -> 0 | J81: =IF(J$4<=year_sale,IF(J80="∞","∞",AVERAGE($C$80:J80)),0) -> 0 | ... L81: =IF(L$4<=year_sale,IF(L80="∞","∞",AVERAGE($C$80:L80)),0) -> 0
B82: Net Proceeds from Refinance or Sale | C82: =SUM(C10,C27) -> 0 | D82: =SUM(D10,D27) -> 0 | E82: =SUM(E10,E27) -> 0 | F82: =SUM(F10,F27) -> 0 | G82: =SUM(G10,G27) -> 0 | H82: =SUM(H10,H27) -> 0 | I82: =SUM(I10,I27) -> 0 | J82: =SUM(J10,J27) -> 0 | ... L82: =SUM(L10,L27) -> 0 | M82: =SUM(C82:L82) -> 0
B83: Average Annual Return to Date | C83: =IFERROR(IF(C78<=year_sale,(SUM($C$85:C85))/$C$5/C78,0),0) -> 0 | D83: =IFERROR(IF(D78<=year_sale,(SUM($C$85:D85))/$C$5/D78,0),0) -> 0 | E83: =IFERROR(IF(E78<=year_sale,(SUM($C$85:E85))/$C$5/E78,0),0) -> 0 | F83: =IFERROR(IF(F78<=year_sale,(SUM($C$85:F85))/$C$5/F78,0),0) -> 0 | G83: =IFERROR(IF(G78<=year_sale,(SUM($C$85:G85))/$C$5/G78,0),0) -> 0 | H83: =IFERROR(IF(H78<=year_sale,(SUM($C$85:H85))/$C$5/H78,0),0) -> 0 | I83: =IFERROR(IF(I78<=year_sale,(SUM($C$85:I85))/$C$5/I78,0),0) -> 0 | J83: =IFERROR(IF(J78<=year_sale,(SUM($C$85:J85))/$C$5/J78,0),0) -> 0 | ... L83: =IFERROR(IF(L78<=year_sale,(SUM($C$85:L85))/$C$5/L78,0),0) -> 0
B84: Return of Capital | C84: =IFERROR(C13+C12,"") -> 0 | D84: =IFERROR(D13+D12,"") -> 0 | E84: =IFERROR(E13+E12,"") -> 0 | F84: =IFERROR(F13+F12,"") -> 0 | G84: =IFERROR(G13+G12,"") -> 0 | H84: =IFERROR(H13+H12,"") -> 0 | I84: =IFERROR(I13+I12,"") -> 0 | J84: =IFERROR(J13+J12,"") -> 0 | ... L84: =IFERROR(L13+L12,"") -> 0
B85: Total Return on Investment | C85: =C79+C82 -> 0 | D85: =D79+D82 -> 0 | E85: =E79+E82 -> 0 | F85: =F79+F82 -> 0 | G85: =G79+G82 -> 0 | H85: =H79+H82 -> 0 | I85: =I79+I82 -> 0 | J85: =J79+J82 -> 0 | ... L85: =L79+L82 -> 0 | M85: =SUM(C85:L85) -> 0 | N85: =IF(C5=0,0,M85/C5) -> 0
B86: =B16 -> Average Annual Return | N86: =OFFSET(C83,0,year_sale-1) -> 0
B87: IRR | N87: =IRR!J115 -> 0
B88: =B18 -> Cash-on-Cash Return | N88: =IFERROR(AVERAGEIF(C4:L4,"<=" & year_sale,C80:L80),0) -> 0
B89: Equity Multiple | N89: =IF(C5=0,0,SUM(C84:L85)/C5) -> 0
B91: Member Returns Based On Specific $ Invested | C91: 1 | D91: =C91+1 -> 2 | E91: =D91+1 -> 3 | F91: =E91+1 -> 4 | G91: =F91+1 -> 5 | H91: =G91+1 -> 6 | I91: =H91+1 -> 7 | J91: =I91+1 -> 8 | K91: =J91+1 -> 9 | L91: =K91+1 -> 10 | M91: Return $ | N91: Return %
B92: Beginning Member Capital Account Balance | C92: 100000 | D92: =IF(D91<=year_sale,C100,0) -> 100000 | E92: =IF(E91<=year_sale,D100,0) -> 100000 | F92: =IF(F91<=year_sale,E100,0) -> 100000 | G92: =IF(G91<=year_sale,F100,0) -> 100000 | H92: =IF(H91<=year_sale,G100,0) -> 0 | I92: =IF(I91<=year_sale,H100,0) -> 0 | J92: =IF(J91<=year_sale,I100,0) -> 0 | K92: =IF(K91<=year_sale,J100,0) -> 0 | L92: =IF(L91<=year_sale,K100,0) -> 0
B93: % of Overall Membership Ownership for $ Invested | C93: =IFERROR($C$92/$C$5,"") | D93: =IFERROR($C$92/$C$5,"") | E93: =IFERROR($C$92/$C$5,"") | F93: =IFERROR($C$92/$C$5,"") | G93: =IFERROR($C$92/$C$5,"") | H93: =IFERROR($C$92/$C$5,"") | I93: =IFERROR($C$92/$C$5,"") | J93: =IFERROR($C$92/$C$5,"") | ... L93: =IFERROR($C$92/$C$5,"")
B94: Member Cashflow | C94: =IFERROR($C$93*C6,"") | D94: =IFERROR($C$93*D6,"") | E94: =IFERROR($C$93*E6,"") | F94: =IFERROR($C$93*F6,"") | G94: =IFERROR($C$93*G6,"") | H94: =IFERROR($C$93*H6,"") | I94: =IFERROR($C$93*I6,"") | J94: =IFERROR($C$93*J6,"") | ... L94: =IFERROR($C$93*L6,"") | M94: =SUM(C94:L94) -> 0
B95: Cash-on-Cash Return | C95: =C7 -> ∞ | D95: =D7 -> ∞ | E95: =E7 -> ∞ | F95: =F7 -> ∞ | G95: =G7 -> ∞ | H95: =H7 -> 0 | I95: =I7 -> 0 | J95: =J7 -> 0 | ... L95: =L7 -> 0
B96: Average Cash-on-Cash Return to Date | C96: =C8 -> ∞ | D96: =D8 -> ∞ | E96: =E8 -> ∞ | F96: =F8 -> ∞ | G96: =G8 -> ∞ | H96: =H8 -> 0 | I96: =I8 -> 0 | J96: =J8 -> 0 | ... L96: =L8 -> 0
B97: Net Proceeds from Refinance or Sale | C97: =IFERROR(IF(C91=year_refi,'Exit Strategy'!$D$27*C93,IF(C91=year_sale,'Exit Strategy'!$H$23*C93,0)),0) -> 0 | D97: =IFERROR(IF(D91=year_refi,'Exit Strategy'!$D$27*D93,IF(D91=year_sale,'Exit Strategy'!$H$23*D93,0)),0) -> 0 | E97: =IFERROR(IF(E91=year_refi,'Exit Strategy'!$D$27*E93,IF(E91=year_sale,'Exit Strategy'!$H$23*E93,0)),0) -> 0 | F97: =IFERROR(IF(F91=year_refi,'Exit Strategy'!$D$27*F93,IF(F91=year_sale,'Exit Strategy'!$H$23*F93,0)),0) -> 0 | G97: =IFERROR(IF(G91=year_refi,'Exit Strategy'!$D$27*G93,IF(G91=year_sale,'Exit Strategy'!$H$23*G93,0)),0) -> 0 | H97: =IFERROR(IF(H91=year_refi,'Exit Strategy'!$D$27*H93,IF(H91=year_sale,'Exit Strategy'!$H$23*H93,0)),0) -> 0 | I97: =IFERROR(IF(I91=year_refi,'Exit Strategy'!$D$27*I93,IF(I91=year_sale,'Exit Strategy'!$H$23*I93,0)),0) -> 0 | J97: =IFERROR(IF(J91=year_refi,'Exit Strategy'!$D$27*J93,IF(J91=year_sale,'Exit Strategy'!$H$23*J93,0)),0) -> 0 | ... L97: =IFERROR(IF(L91=year_refi,'Exit Strategy'!$D$27*L93,IF(L91=year_sale,'Exit Strategy'!$H$23*L93,0)),0) -> 0 | M97: =SUM(C97:L97) -> 0
B98: Average Annual Return to Date | C98: =C11 -> 0 | D98: =D11 -> 0 | E98: =E11 -> 0 | F98: =F11 -> 0 | G98: =G11 -> 0 | H98: =H11 -> 0 | I98: =I11 -> 0 | J98: =J11 -> 0 | ... L98: =L11 -> 0
B99: Return of Member Capital | C99: =IFERROR(C84*C93,0) -> 0 | D99: =IFERROR(D84*D93,0) -> 0 | E99: =IFERROR(E84*E93,0) -> 0 | F99: =IFERROR(F84*F93,0) -> 0 | G99: =IFERROR(G84*G93,0) -> 0 | H99: =IFERROR(H84*H93,0) -> 0 | I99: =IFERROR(I84*I93,0) -> 0 | J99: =IFERROR(J84*J93,0) -> 0 | ... L99: =IFERROR(L84*L93,0) -> 0
B100: Ending Member Capital Account Balance | C100: =IFERROR(C92-C99,"") -> 100000 | D100: =IFERROR(D92-D99,"") -> 100000 | E100: =IFERROR(E92-E99,"") -> 100000 | F100: =IFERROR(F92-F99,"") -> 100000 | G100: =IFERROR(G92-G99,"") -> 100000 | H100: =IFERROR(H92-H99,"") -> 0 | I100: =IFERROR(I92-I99,"") -> 0 | J100: =IFERROR(J92-J99,"") -> 0 | ... L100: =IFERROR(L92-L99,"") -> 0
B101: Total Return in Investment | C101: =IFERROR(C94+C97,"") | D101: =IFERROR(D94+D97,"") | E101: =IFERROR(E94+E97,"") | F101: =IFERROR(F94+F97,"") | G101: =IFERROR(G94+G97,"") | H101: =IFERROR(H94+H97,"") | I101: =IFERROR(I94+I97,"") | J101: =IFERROR(J94+J97,"") | ... L101: =IFERROR(L94+L97,"") | M101: =SUM(C101:L101) -> 0 | N101: =IF(C92=0,0,M101/C92) -> 0
B102: =B86 -> Average Annual Return | N102: =OFFSET(C98,0,year_sale-1) -> 0
B103: IRR | N103: =IRR!$J$58 -> 0
B104: =B88 -> Cash-on-Cash Return | N104: =N18 -> 0
...

Sheet IRR
A1: Internal Rate of Return (IRR)
B4: Summary of Projected Member Cash Flows and Returns
B5: Year | C5: Quarter | D5: XIRR Dates | E5: Member Contribution | F5: Cash Flow Distribution | G5: XIRR Cash Flow | H5: Proceeds from Refinance or Sale | I5: Return of P/I escrow | J5: Total
B6: 0 | D6: 29220 | E6: =-Summary!D22 -> 0 | F6: 0 | G6: =E6 -> 0 | J6: =H6+F6+E6 -> 0
B7: 1 | F7: =IF(B7<=year_sale,'P&L'!D51,0) -> 0 | H7: =IF(B7=year_refi,'Exit Strategy'!$D$29,IF(B7=year_sale,'Exit Strategy'!$H$25,"")) | I7: =Returns!C12 -> 0 | J7: =IFERROR(SUM(E7:I7),0) -> 0
C8: Q1 | D8: 29311 | G8: =IFERROR(F7/4,0) -> 0 | J8: =IFERROR(SUM(E8:I8),0) -> 0
C9: Q2 | D9: 29402 | G9: =G8 -> 0 | J9: =IFERROR(SUM(E9:I9),0) -> 0
C10: Q3 | D10: 29494 | G10: =G9 -> 0 | J10: =IFERROR(SUM(E10:I10),0) -> 0
C11: Q4 | D11: 29586 | G11: =SUM(G10,H7,I7) -> 0 | J11: =IFERROR(SUM(E11:I11),0) -> 0
B12: 2 | F12: =IF(B12<=year_sale,'P&L'!F51,0) -> 0 | H12: =IF(B12=year_refi,'Exit Strategy'!$D$29,IF(B12=year_sale,'Exit Strategy'!$H$25,"")) | I12: =Returns!D12 -> 0 | J12: =IFERROR(SUM(E12:I12),0) -> 0
C13: Q1 | D13: 29676 | G13: =IFERROR(F12/4,0) -> 0 | J13: =IFERROR(SUM(E13:I13),0) -> 0
C14: Q2 | D14: 29767 | G14: =G13 -> 0 | J14: =IFERROR(SUM(E14:I14),0) -> 0
C15: Q3 | D15: 29859 | G15: =G14 -> 0 | J15: =IFERROR(SUM(E15:I15),0) -> 0
C16: Q4 | D16: 29951 | G16: =SUM(G15,H12,I12) -> 0 | J16: =IFERROR(SUM(E16:I16),0) -> 0
B17: 3 | F17: =IF(B17<=year_sale,'P&L'!H51,0) -> 0 | H17: =IF(B17=year_refi,'Exit Strategy'!$D$29,IF(B17=year_sale,'Exit Strategy'!$H$25,"")) | I17: =Returns!E12 -> 0 | J17: =IFERROR(SUM(E17:I17),0) -> 0
C18: Q1 | D18: 30041 | G18: =IFERROR(F17/4,0) -> 0 | J18: =IFERROR(SUM(E18:I18),0) -> 0
C19: Q2 | D19: 30132 | G19: =G18 -> 0 | J19: =IFERROR(SUM(E19:I19),0) -> 0
C20: Q3 | D20: 30224 | G20: =G19 -> 0 | J20: =IFERROR(SUM(E20:I20),0) -> 0
C21: Q4 | D21: 30316 | G21: =SUM(G20,H17,I17) -> 0 | J21: =IFERROR(SUM(E21:I21),0) -> 0
B22: 4 | F22: =IF(B22<=year_sale,'P&L'!J51,0) -> 0 | H22: =IF(B22=year_refi,'Exit Strategy'!$D$29,IF(B22=year_sale,'Exit Strategy'!$H$25,"")) | I22: =Returns!F12 -> 0 | J22: =IFERROR(SUM(E22:I22),0) -> 0
C23: Q1 | D23: 30406 | G23: =IFERROR(F22/4,0) -> 0 | J23: =IFERROR(SUM(E23:I23),0) -> 0
C24: Q2 | D24: 30497 | G24: =G23 -> 0 | J24: =IFERROR(SUM(E24:I24),0) -> 0
C25: Q3 | D25: 30589 | G25: =G24 -> 0 | J25: =IFERROR(SUM(E25:I25),0) -> 0
C26: Q4 | D26: 30681 | G26: =SUM(G25,H22,I22) -> 0 | J26: =IFERROR(SUM(E26:I26),0) -> 0
B27: 5 | F27: =IF(B27<=year_sale,'P&L'!L51,0) -> 0 | H27: =IF(B27=year_refi,'Exit Strategy'!$D$29,IF(B27=year_sale,'Exit Strategy'!$H$25,"")) -> 0 | I27: =Returns!G12 -> 0 | J27: =IFERROR(SUM(E27:I27),0) -> 0
C28: Q1 | D28: 30772 | G28: =IFERROR(F27/4,0) -> 0 | J28: =IFERROR(SUM(E28:I28),0) -> 0
C29: Q2 | D29: 30863 | G29: =G28 -> 0 | J29: =IFERROR(SUM(E29:I29),0) -> 0
C30: Q3 | D30: 30955 | G30: =G29 -> 0 | J30: =IFERROR(SUM(E30:I30),0) -> 0
C31: Q4 | D31: 31047 | G31: =SUM(G30,H27,I27) -> 0 | J31: =IFERROR(SUM(E31:I31),0) -> 0
B32: =B27+1 -> 6 | F32: =IF(B32<=year_sale,'P&L'!N51,0) -> 0 | H32: =IF(B32=year_refi,'Exit Strategy'!$D$29,IF(B32=year_sale,'Exit Strategy'!$H$25,"")) | I32: =Returns!H12 -> 0 | J32: =IFERROR(SUM(E32:I32),0) -> 0
C33: Q1 | D33: 31137 | G33: =IFERROR(F32/4,0) -> 0 | J33: =IFERROR(SUM(E33:I33),0) -> 0
C34: Q2 | D34: 31228 | G34: =G33 -> 0 | J34: =IFERROR(SUM(E34:I34),0) -> 0
C35: Q3 | D35: 31320 | G35: =G34 -> 0 | J35: =IFERROR(SUM(E35:I35),0) -> 0
C36: Q4 | D36: 31412 | G36: =SUM(G35,H32,I32) -> 0 | J36: =IFERROR(SUM(E36:I36),0) -> 0
B37: =B32+1 -> 7 | F37: =IF(B37<=year_sale,'P&L'!P51,0) -> 0 | H37: =IF(B37=year_refi,'Exit Strategy'!$D$29,IF(B37=year_sale,'Exit Strategy'!$H$25,"")) | I37: =Returns!I12 -> 0 | J37: =IFERROR(SUM(E37:I37),0) -> 0
C38: Q1 | D38: 31502 | G38: =IFERROR(F37/4,0) -> 0 | J38: =IFERROR(SUM(E38:I38),0) -> 0
C39: Q2 | D39: 31593 | G39: =G38 -> 0 | J39: =IFERROR(SUM(E39:I39),0) -> 0
C40: Q3 | D40: 31685 | G40: =G39 -> 0 | J40: =IFERROR(SUM(E40:I40),0) -> 0
C41: Q4 | D41: 31777 | G41: =SUM(G40,H37,I37) -> 0 | J41: =IFERROR(SUM(E41:I41),0) -> 0
B42: =B37+1 -> 8 | F42: =IF(B42<=year_sale,'P&L'!R51,0) -> 0 | H42: =IF(B42=year_refi,'Exit Strategy'!$D$29,IF(B42=year_sale,'Exit Strategy'!$H$25,"")) | I42: =Returns!J12 -> 0 | J42: =IFERROR(SUM(E42:I42),0) -> 0
C43: Q1 | D43: 31867 | G43: =IFERROR(F42/4,0) -> 0 | J43: =IFERROR(SUM(E43:I43),0) -> 0
C44: Q2 | D44: 31958 | G44: =G43 -> 0 | J44: =IFERROR(SUM(E44:I44),0) -> 0
C45: Q3 | D45: 32050 | G45: =G44 -> 0 | J45: =IFERROR(SUM(E45:I45),0) -> 0
C46: Q4 | D46: 32142 | G46: =SUM(G45,H42,I42) -> 0 | J46: =IFERROR(SUM(E46:I46),0) -> 0
B47: =B42+1 -> 9 | F47: =IF(B47<=year_sale,'P&L'!T51,0) -> 0 | H47: =IF(B47=year_refi,'Exit Strategy'!$D$29,IF(B47=year_sale,'Exit Strategy'!$H$25,"")) | I47: =Returns!K12 -> 0 | J47: =IFERROR(SUM(E47:I47),0) -> 0
C48: Q1 | D48: 32233 | G48: =IFERROR(F47/4,0) -> 0 | J48: =IFERROR(SUM(E48:I48),0) -> 0
C49: Q2 | D49: 32324 | G49: =G48 -> 0 | J49: =IFERROR(SUM(E49:I49),0) -> 0
C50: Q3 | D50: 32416 | G50: =G49 -> 0 | J50: =IFERROR(SUM(E50:I50),0) -> 0
C51: Q4 | D51: 32508 | G51: =SUM(G50,H47,I47) -> 0 | J51: =IFERROR(SUM(E51:I51),0) -> 0
B52: =B47+1 -> 10 | F52: =IF(B52<=year_sale,'P&L'!V51,0) -> 0 | H52: =IF(B52=year_refi,'Exit Strategy'!$D$29,IF(B52=year_sale,'Exit Strategy'!$H$25,"")) | I52: =Returns!L12 -> 0 | J52: =IFERROR(SUM(E52:I52),0) -> 0
C53: Q1 | D53: 32598 | G53: =IFERROR(F52/4,0) -> 0 | J53: =IFERROR(SUM(E53:I53),0) -> 0
C54: Q2 | D54: 32689 | G54: =G53 -> 0 | J54: =IFERROR(SUM(E54:I54),0) -> 0
C55: Q3 | D55: 32781 | G55: =G54 -> 0 | J55: =IFERROR(SUM(E55:I55),0) -> 0
C56: Q4 | D56: 32873 | G56: =SUM(G55,H52,I52) -> 0 | J56: =IFERROR(SUM(E56:I56),0) -> 0
B57: Total | E57: =SUM(E6:E52) -> 0 | F57: =SUM(F6:F52) -> 0 | H57: =SUM(H6:H52) -> 0 | I57: =SUM(I6:I52) -> 0 | J57: =IFERROR(SUM(E57:I57),0) -> 0
B58: IRR | J58: =IF(E6=0,0,XIRR(G6:G56,D6:D56)) -> 0 | K58: =About!E7
B61: Summary of Total Projected Cash Flows and Returns
B62: Year | C62: Quarter | E62: Member Contribution | F62: Cash Flow Distribution | G62: XIRR Cash Flow | H62: Proceeds from Refinance or Sale | I62: Return of P/I escrow | J62: Total
B63: 0 | D63: 29220 | E63: =E6 -> 0 | F63: 0 | G63: =E63 -> 0 | J63: =H63+F63+E63 -> 0
B64: 1 | F64: =IF(B64<=year_sale,'P&L'!D51+'P&L'!D50,0) -> 0 | H64: =SUM(Returns!C82,Returns!C84) -> 0 | I64: =Returns!C12 -> 0 | J64: =SUM(E64:I64) -> 0
C65: Q1 | D65: 29311 | G65: =IFERROR(F64/4,0) -> 0 | J65: =SUM(E65:I65) -> 0
C66: Q2 | D66: 29402 | G66: =G65 -> 0 | J66: =SUM(E66:I66) -> 0
C67: Q3 | D67: 29494 | G67: =G66 -> 0 | J67: =SUM(E67:I67) -> 0
C68: Q4 | D68: 29586 | G68: =SUM(G67,H64,I64) -> 0 | J68: =SUM(E68:I68) -> 0
B69: 2 | F69: =IF(B69<=year_sale,'P&L'!F51+'P&L'!F50,0) -> 0 | H69: =SUM(Returns!D82,Returns!D84) -> 0 | I69: =Returns!D12 -> 0 | J69: =SUM(E69:I69) -> 0
C70: Q1 | D70: 29676 | G70: =IFERROR(F69/4,0) -> 0 | J70: =SUM(E70:I70) -> 0
C71: Q2 | D71: 29767 | G71: =G70 -> 0 | J71: =SUM(E71:I71) -> 0
C72: Q3 | D72: 29859 | G72: =G71 -> 0 | J72: =SUM(E72:I72) -> 0
C73: Q4 | D73: 29951 | G73: =SUM(G72,H69,I69) -> 0 | J73: =SUM(E73:I73) -> 0
B74: 3 | F74: =IF(B74<=year_sale,'P&L'!H51+'P&L'!H50,0) -> 0 | H74: =SUM(Returns!E82,Returns!E84) -> 0 | I74: =Returns!E12 -> 0 | J74: =SUM(E74:I74) -> 0
C75: Q1 | D75: 30041 | G75: =IFERROR(F74/4,0) -> 0 | J75: =SUM(E75:I75) -> 0
C76: Q2 | D76: 30132 | G76: =G75 -> 0 | J76: =SUM(E76:I76) -> 0
C77: Q3 | D77: 30224 | G77: =G76 -> 0 | J77: =SUM(E77:I77) -> 0
C78: Q4 | D78: 30316 | G78: =SUM(G77,H74,I74) -> 0 | J78: =SUM(E78:I78) -> 0
B79: 4 | F79: =IF(B79<=year_sale,'P&L'!J51+'P&L'!J50,0) -> 0 | H79: =SUM(Returns!F82,Returns!F84) -> 0 | I79: =Returns!F12 -> 0 | J79: =SUM(E79:I79) -> 0
C80: Q1 | D80: 30406 | G80: =IFERROR(F79/4,0) -> 0 | J80: =SUM(E80:I80) -> 0
C81: Q2 | D81: 30497 | G81: =G80 -> 0 | J81: =SUM(E81:I81) -> 0
C82: Q3 | D82: 30589 | G82: =G81 -> 0 | J82: =SUM(E82:I82) -> 0
C83: Q4 | D83: 30681 | G83: =SUM(G82,H79,I79) -> 0 | J83: =SUM(E83:I83) -> 0
B84: 5 | F84: =IF(B84<=year_sale,'P&L'!L51+'P&L'!L50,0) -> 0 | H84: =SUM(Returns!G82,Returns!G84) -> 0 | I84: =Returns!G12 -> 0 | J84: =SUM(E84:I84) -> 0
C85: Q1 | D85: 30772 | G85: =IFERROR(F84/4,0) -> 0 | J85: =SUM(E85:I85) -> 0
C86: Q2 | D86: 30863 | G86: =G85 -> 0 | J86: =SUM(E86:I86) -> 0
C87: Q3 | D87: 30955 | G87: =G86 -> 0 | J87: =SUM(E87:I87) -> 0
C88: Q4 | D88: 31047 | G88: =SUM(G87,H84,I84) -> 0 | J88: =SUM(E88:I88) -> 0
B89: =B84+1 -> 6 | F89: =IF(B89<=year_sale,'P&L'!N51+'P&L'!N50,0) -> 0 | H89: =SUM(Returns!H82,Returns!H84) -> 0 | I89: =Returns!H12 -> 0 | J89: =SUM(E89:I89) -> 0
C90: Q1 | D90: 31137 | G90: =IFERROR(F89/4,0) -> 0 | J90: =SUM(E90:I90) -> 0
C91: Q2 | D91: 31228 | G91: =G90 -> 0 | J91: =SUM(E91:I91) -> 0
C92: Q3 | D92: 31320 | G92: =G91 -> 0 | J92: =SUM(E92:I92) -> 0
C93: Q4 | D93: 31412 | G93: =SUM(G92,H89,I89) -> 0 | J93: =SUM(E93:I93) -> 0
B94: =B89+1 -> 7 | F94: =IF(B94<=year_sale,'P&L'!P51+'P&L'!P50,0) -> 0 | H94: =SUM(Returns!I82,Returns!I84) -> 0 | I94: =Returns!I12 -> 0 | J94: =SUM(E94:I94) -> 0
C95: Q1 | D95: 31502 | G95: =IFERROR(F94/4,0) -> 0 | J95: =SUM(E95:I95) -> 0
C96: Q2 | D96: 31593 | G96: =G95 -> 0 | J96: =SUM(E96:I96) -> 0
C97: Q3 | D97: 31685 | G97: =G96 -> 0 | J97: =SUM(E97:I97) -> 0
C98: Q4 | D98: 31777 | G98: =SUM(G97,H94,I94) -> 0 | J98: =SUM(E98:I98) -> 0
B99: =B94+1 -> 8 | F99: =IF(B99<=year_sale,'P&L'!R51+'P&L'!R50,0) -> 0 | H99: =SUM(Returns!J82,Returns!J84) -> 0 | I99: =Returns!J12 -> 0 | J99: =SUM(E99:I99) -> 0
C100: Q1 | D100: 31867 | G100: =IFERROR(F99/4,0) -> 0 | J100: =SUM(E100:I100) -> 0
C101: Q2 | D101: 31958 | G101: =G100 -> 0 | J101: =SUM(E101:I101) -> 0
C102: Q3 | D102: 32050 | G102: =G101 -> 0 | J102: =SUM(E102:I102) -> 0
C103: Q4 | D103: 32142 | G103: =SUM(G102,H99,I99) -> 0 | J103: =SUM(E103:I103) -> 0
B104: =B99+1 -> 9 | F104: =IF(B104<=year_sale,'P&L'!T51+'P&L'!T50,0) -> 0 | H104: =SUM(Returns!K82,Returns!K84) -> 0 | I104: =Returns!K12 -> 0 | J104: =SUM(E104:I104) -> 0
...

Sheet Loans
B1: Loans
B3: Using Loan to Cost? | C3: No
H4: =IF(H5=year_refi,"REFINANCE!",IF(H5=year_sale,"SALE!","")) | I4: =IF(I5=year_refi,"REFINANCE!",IF(I5=year_sale,"SALE!","")) | J4: =IF(J5=year_refi,"REFINANCE!",IF(J5=year_sale,"SALE!","")) | K4: =IF(K5=year_refi,"REFINANCE!",IF(K5=year_sale,"SALE!","")) | L4: =IF(L5=year_refi,"REFINANCE!",IF(L5=year_sale,"SALE!","")) -> SALE! | M4: =IF(M5=year_refi,"REFINANCE!",IF(M5=year_sale,"SALE!","")) | N4: =IF(N5=year_refi,"REFINANCE!",IF(N5=year_sale,"SALE!","")) | O4: =IF(O5=year_refi,"REFINANCE!",IF(O5=year_sale,"SALE!","")) | ... Q4: =IF(Q5=year_refi,"REFINANCE!",IF(Q5=year_sale,"SALE!",""))
B5: Loan-To-Cost Worksheet | G5: Year | H5: 1 | I5: =H5+1 -> 2 | J5: =I5+1 -> 3 | K5: =J5+1 -> 4 | L5: =K5+1 -> 5 | M5: =L5+1 -> 6 | N5: =M5+1 -> 7 | O5: =N5+1 -> 8 | P5: =O5+1 -> 9 | Q5: =P5+1 -> 10
C6: Total | D6: % Financed | E6: $ Financed
B7: Purchase Price | C7: =($C$3="Yes")*Summary!D6 -> 0 | D7: =1-Summary!C9 -> 0.75 | E7: =C7*D7 -> 0 | G7: 1st Mortgage | H7: =Summary!D10 -> 0
B8: Repairs | C8: =($C$3="Yes")*Summary!D20 -> 0 | D8: 1 | E8: =C8*D8 -> 0 | G8: Beginning Balance | H8: =H7 -> 0 | I8: =IF(year_refi="NA",H12,IF(I$5-year_refi-1>=0,0,H12)) -> 0 | J8: =IF(year_refi="NA",I12,IF(J$5-year_refi-1>=0,0,I12)) -> 0 | K8: =IF(year_refi="NA",J12,IF(K$5-year_refi-1>=0,0,J12)) -> 0 | L8: =IF(year_refi="NA",K12,IF(L$5-year_refi-1>=0,0,K12)) -> 0 | M8: =IF(year_refi="NA",L12,IF(M$5-year_refi-1>=0,0,L12)) -> 0 | N8: =IF(year_refi="NA",M12,IF(N$5-year_refi-1>=0,0,M12)) -> 0 | O8: =IF(year_refi="NA",N12,IF(O$5-year_refi-1>=0,0,N12)) -> 0 | P8: =IF(year_refi="NA",O12,IF(P$5-year_refi-1>=0,0,O12)) -> 0 | Q8: =IF(year_refi="NA",P12,IF(Q$5-year_refi-1>=0,0,P12)) -> 0
B9: Closing Costs (less Reserves/Travel) | C9: =($C$3="Yes")*('Acquisition Costs'!D51-'Acquisition Costs'!D49-'Acquisition Costs'!D45) -> 0 | D9: 0 | E9: =C9*D9 -> 0 | G9: Principal Paid | H9: =IF(year_refi="NA",'1st Mortgage 1'!C12,IF(H$5-year_refi-1>=0,0,'1st Mortgage 1'!C12)) -> 0 | I9: =IF(year_refi="NA",'1st Mortgage 1'!D12,IF(I$5-year_refi-1>=0,0,'1st Mortgage 1'!D12)) -> 0 | J9: =IF(year_refi="NA",'1st Mortgage 1'!E12,IF(J$5-year_refi-1>=0,0,'1st Mortgage 1'!E12)) -> 0 | K9: =IF(year_refi="NA",'1st Mortgage 1'!F12,IF(K$5-year_refi-1>=0,0,'1st Mortgage 1'!F12)) -> 0 | L9: =IF(year_refi="NA",'1st Mortgage 1'!G12,IF(L$5-year_refi-1>=0,0,'1st Mortgage 1'!G12)) -> 0 | M9: =IF(year_refi="NA",'1st Mortgage 1'!H12,IF(M$5-year_refi-1>=0,0,'1st Mortgage 1'!H12)) -> 0 | N9: =IF(year_refi="NA",'1st Mortgage 1'!I12,IF(N$5-year_refi-1>=0,0,'1st Mortgage 1'!I12)) -> 0 | O9: =IF(year_refi="NA",'1st Mortgage 1'!J12,IF(O$5-year_refi-1>=0,0,'1st Mortgage 1'!J12)) -> 0 | ... Q9: =IF(year_refi="NA",'1st Mortgage 1'!L12,IF(Q$5-year_refi-1>=0,0,'1st Mortgage 1'!L12)) -> 0
B10: Total LTC Financed | E10: =IF($C$3="Yes",(E7+E8+D9*(SUM('Acquisition Costs'!D13:D15)+SUM('Acquisition Costs'!D18:D22)+'Acquisition Costs'!D35)+D9*'Acquisition Costs'!$C$24*Summary!$D$14)/(1-D9*'Acquisition Costs'!$C$23),0) -> 0 | G10: Interest Paid | H10: =IF(year_refi="NA",'1st Mortgage 1'!C13,IF(H$5-year_refi-1>=0,0,'1st Mortgage 1'!C13)) -> 0 | I10: =IF(year_refi="NA",'1st Mortgage 1'!D13,IF(I$5-year_refi-1>=0,0,'1st Mortgage 1'!D13)) -> 0 | J10: =IF(year_refi="NA",'1st Mortgage 1'!E13,IF(J$5-year_refi-1>=0,0,'1st Mortgage 1'!E13)) -> 0 | K10: =IF(year_refi="NA",'1st Mortgage 1'!F13,IF(K$5-year_refi-1>=0,0,'1st Mortgage 1'!F13)) -> 0 | L10: =IF(year_refi="NA",'1st Mortgage 1'!G13,IF(L$5-year_refi-1>=0,0,'1st Mortgage 1'!G13)) -> 0 | M10: =IF(year_refi="NA",'1st Mortgage 1'!H13,IF(M$5-year_refi-1>=0,0,'1st Mortgage 1'!H13)) -> 0 | N10: =IF(year_refi="NA",'1st Mortgage 1'!I13,IF(N$5-year_refi-1>=0,0,'1st Mortgage 1'!I13)) -> 0 | O10: =IF(year_refi="NA",'1st Mortgage 1'!J13,IF(O$5-year_refi-1>=0,0,'1st Mortgage 1'!J13)) -> 0 | ... Q10: =IF(year_refi="NA",'1st Mortgage 1'!L13,IF(Q$5-year_refi-1>=0,0,'1st Mortgage 1'!L13)) -> 0
G11: Total Debt Service | H11: =H9+H10 -> 0 | I11: =I9+I10 -> 0 | J11: =J9+J10 -> 0 | K11: =K9+K10 -> 0 | L11: =L9+L10 -> 0 | M11: =M9+M10 -> 0 | N11: =N9+N10 -> 0 | O11: =O9+O10 -> 0 | ... Q11: =Q9+Q10 -> 0
B12: Down payment | E12: =C7-E7 -> 0 | G12: Ending Balance | H12: =IF(year_refi="NA",'1st Mortgage 1'!C14,IF(H$5-year_refi-1>=0,0,'1st Mortgage 1'!C14)) -> 0 | I12: =IF(year_refi="NA",'1st Mortgage 1'!D14,IF(I$5-year_refi-1>=0,0,'1st Mortgage 1'!D14)) -> 0 | J12: =IF(year_refi="NA",'1st Mortgage 1'!E14,IF(J$5-year_refi-1>=0,0,'1st Mortgage 1'!E14)) -> 0 | K12: =IF(year_refi="NA",'1st Mortgage 1'!F14,IF(K$5-year_refi-1>=0,0,'1st Mortgage 1'!F14)) -> 0 | L12: =IF(year_refi="NA",'1st Mortgage 1'!G14,IF(L$5-year_refi-1>=0,0,'1st Mortgage 1'!G14)) -> 0 | M12: =IF(year_refi="NA",'1st Mortgage 1'!H14,IF(M$5-year_refi-1>=0,0,'1st Mortgage 1'!H14)) -> 0 | N12: =IF(year_refi="NA",'1st Mortgage 1'!I14,IF(N$5-year_refi-1>=0,0,'1st Mortgage 1'!I14)) -> 0 | O12: =IF(year_refi="NA",'1st Mortgage 1'!J14,IF(O$5-year_refi-1>=0,0,'1st Mortgage 1'!J14)) -> 0 | ... Q12: =IF(year_refi="NA",'1st Mortgage 1'!L14,IF(Q$5-year_refi-1>=0,0,'1st Mortgage 1'!L14)) -> 0
B13: Repairs not financed | E13: =C8-E8 -> 0
B14: Closing costs not financed | E14: =C9-E9 -> 0 | G14: 2nd Mortgage | H14: =Summary!D14 -> 0
B15: Travel/Reserves closing costs | E15: =($C$3="Yes")*('Acquisition Costs'!D51-C9) -> 0 | G15: Beginning Balance | H15: =H14 -> 0 | I15: =IF(year_refi="NA",H19,IF(I$5-year_refi-1>=0,0,H19)) -> 0 | J15: =IF(year_refi="NA",I19,IF(J$5-year_refi-1>=0,0,I19)) -> 0 | K15: =IF(year_refi="NA",J19,IF(K$5-year_refi-1>=0,0,J19)) -> 0 | L15: =IF(year_refi="NA",K19,IF(L$5-year_refi-1>=0,0,K19)) -> 0 | M15: =IF(year_refi="NA",L19,IF(M$5-year_refi-1>=0,0,L19)) -> 0 | N15: =IF(year_refi="NA",M19,IF(N$5-year_refi-1>=0,0,M19)) -> 0 | O15: =IF(year_refi="NA",N19,IF(O$5-year_refi-1>=0,0,N19)) -> 0 | P15: =IF(year_refi="NA",O19,IF(P$5-year_refi-1>=0,0,O19)) -> 0 | Q15: =IF(year_refi="NA",P19,IF(Q$5-year_refi-1>=0,0,P19)) -> 0
B16: LTC Member Captial Needed | E16: =SUM(E12:E15) -> 0 | G16: Principal Paid | H16: =IF(year_refi="NA",'2nd Mortgage 1'!C12,IF(H$5-year_refi-1>=0,0,'2nd Mortgage 1'!C12)) -> 0 | I16: =IF(year_refi="NA",'2nd Mortgage 1'!D12,IF(I$5-year_refi-1>=0,0,'2nd Mortgage 1'!D12)) -> 0 | J16: =IF(year_refi="NA",'2nd Mortgage 1'!E12,IF(J$5-year_refi-1>=0,0,'2nd Mortgage 1'!E12)) -> 0 | K16: =IF(year_refi="NA",'2nd Mortgage 1'!F12,IF(K$5-year_refi-1>=0,0,'2nd Mortgage 1'!F12)) -> 0 | L16: =IF(year_refi="NA",'2nd Mortgage 1'!G12,IF(L$5-year_refi-1>=0,0,'2nd Mortgage 1'!G12)) -> 0 | M16: =IF(year_refi="NA",'2nd Mortgage 1'!H12,IF(M$5-year_refi-1>=0,0,'2nd Mortgage 1'!H12)) -> 0 | N16: =IF(year_refi="NA",'2nd Mortgage 1'!I12,IF(N$5-year_refi-1>=0,0,'2nd Mortgage 1'!I12)) -> 0 | O16: =IF(year_refi="NA",'2nd Mortgage 1'!J12,IF(O$5-year_refi-1>=0,0,'2nd Mortgage 1'!J12)) -> 0 | ... Q16: =IF(year_refi="NA",'2nd Mortgage 1'!L12,IF(Q$5-year_refi-1>=0,0,'2nd Mortgage 1'!L12)) -> 0
G17: Interest Paid | H17: =IF(year_refi="NA",'2nd Mortgage 1'!C13,IF(H$5-year_refi-1>=0,0,'2nd Mortgage 1'!C13)) -> 0 | I17: =IF(year_refi="NA",'2nd Mortgage 1'!D13,IF(I$5-year_refi-1>=0,0,'2nd Mortgage 1'!D13)) -> 0 | J17: =IF(year_refi="NA",'2nd Mortgage 1'!E13,IF(J$5-year_refi-1>=0,0,'2nd Mortgage 1'!E13)) -> 0 | K17: =IF(year_refi="NA",'2nd Mortgage 1'!F13,IF(K$5-year_refi-1>=0,0,'2nd Mortgage 1'!F13)) -> 0 | L17: =IF(year_refi="NA",'2nd Mortgage 1'!G13,IF(L$5-year_refi-1>=0,0,'2nd Mortgage 1'!G13)) -> 0 | M17: =IF(year_refi="NA",'2nd Mortgage 1'!H13,IF(M$5-year_refi-1>=0,0,'2nd Mortgage 1'!H13)) -> 0 | N17: =IF(year_refi="NA",'2nd Mortgage 1'!I13,IF(N$5-year_refi-1>=0,0,'2nd Mortgage 1'!I13)) -> 0 | O17: =IF(year_refi="NA",'2nd Mortgage 1'!J13,IF(O$5-year_refi-1>=0,0,'2nd Mortgage 1'!J13)) -> 0 | ... Q17: =IF(year_refi="NA",'2nd Mortgage 1'!L13,IF(Q$5-year_refi-1>=0,0,'2nd Mortgage 1'!L13)) -> 0
G18: Total Debt Service | H18: =H16+H17 -> 0 | I18: =I16+I17 -> 0 | J18: =J16+J17 -> 0 | K18: =K16+K17 -> 0 | L18: =L16+L17 -> 0 | M18: =M16+M17 -> 0 | N18: =N16+N17 -> 0 | O18: =O16+O17 -> 0 | ... Q18: =Q16+Q17 -> 0
G19: Ending Balance | H19: =IF(year_refi="NA",'2nd Mortgage 1'!C14,IF(H$5-year_refi-1>=0,0,'2nd Mortgage 1'!C14)) -> 0 | I19: =IF(year_refi="NA",'2nd Mortgage 1'!D14,IF(I$5-year_refi-1>=0,0,'2nd Mortgage 1'!D14)) -> 0 | J19: =IF(year_refi="NA",'2nd Mortgage 1'!E14,IF(J$5-year_refi-1>=0,0,'2nd Mortgage 1'!E14)) -> 0 | K19: =IF(year_refi="NA",'2nd Mortgage 1'!F14,IF(K$5-year_refi-1>=0,0,'2nd Mortgage 1'!F14)) -> 0 | L19: =IF(year_refi="NA",'2nd Mortgage 1'!G14,IF(L$5-year_refi-1>=0,0,'2nd Mortgage 1'!G14)) -> 0 | M19: =IF(year_refi="NA",'2nd Mortgage 1'!H14,IF(M$5-year_refi-1>=0,0,'2nd Mortgage 1'!H14)) -> 0 | N19: =IF(year_refi="NA",'2nd Mortgage 1'!I14,IF(N$5-year_refi-1>=0,0,'2nd Mortgage 1'!I14)) -> 0 | O19: =IF(year_refi="NA",'2nd Mortgage 1'!J14,IF(O$5-year_refi-1>=0,0,'2nd Mortgage 1'!J14)) -> 0 | ... Q19: =IF(year_refi="NA",'2nd Mortgage 1'!L14,IF(Q$5-year_refi-1>=0,0,'2nd Mortgage 1'!L14)) -> 0
G21: 1st Mortgage Re-Financed | H21: =IF(year_refi="NA","",IF(H5=year_refi+1,'Exit Strategy'!$D$15,"")) | I21: =IF(year_refi="NA","",IF(I5=year_refi+1,'Exit Strategy'!$D$15,"")) | J21: =IF(year_refi="NA","",IF(J5=year_refi+1,'Exit Strategy'!$D$15,"")) | K21: =IF(year_refi="NA","",IF(K5=year_refi+1,'Exit Strategy'!$D$15,"")) | L21: =IF(year_refi="NA","",IF(L5=year_refi+1,'Exit Strategy'!$D$15,"")) | M21: =IF(year_refi="NA","",IF(M5=year_refi+1,'Exit Strategy'!$D$15,"")) | N21: =IF(year_refi="NA","",IF(N5=year_refi+1,'Exit Strategy'!$D$15,"")) | O21: =IF(year_refi="NA","",IF(O5=year_refi+1,'Exit Strategy'!$D$15,"")) | ... Q21: =IF(year_refi="NA","",IF(Q5=year_refi+1,'Exit Strategy'!$D$15,""))
G22: Beginning Balance | H22: =IF(H21="",0,H21) -> 0 | I22: =IF(I21="",H26,I21) -> 0 | J22: =IF(J21="",I26,J21) -> 0 | K22: =IF(K21="",J26,K21) -> 0 | L22: =IF(L21="",K26,L21) -> 0 | M22: =IF(M21="",L26,M21) -> 0 | N22: =IF(N21="",M26,N21) -> 0 | O22: =IF(O21="",N26,O21) -> 0 | P22: =IF(P21="",O26,P21) -> 0 | Q22: =IF(Q21="",P26,Q21) -> 0
G23: Principal Paid | H23: =IF(year_refi="NA",0,IF(Loans!H$5-year_refi-1<0,0,OFFSET('1st Mortgage Re-Fi'!$C$12,0,Loans!H$5-year_refi-1))) -> 0 | I23: =IF(year_refi="NA",0,IF(Loans!I$5-year_refi-1<0,0,OFFSET('1st Mortgage Re-Fi'!$C$12,0,Loans!I$5-year_refi-1))) -> 0 | J23: =IF(year_refi="NA",0,IF(Loans!J$5-year_refi-1<0,0,OFFSET('1st Mortgage Re-Fi'!$C$12,0,Loans!J$5-year_refi-1))) -> 0 | K23: =IF(year_refi="NA",0,IF(Loans!K$5-year_refi-1<0,0,OFFSET('1st Mortgage Re-Fi'!$C$12,0,Loans!K$5-year_refi-1))) -> 0 | L23: =IF(year_refi="NA",0,IF(Loans!L$5-year_refi-1<0,0,OFFSET('1st Mortgage Re-Fi'!$C$12,0,Loans!L$5-year_refi-1))) -> 0 | M23: =IF(year_refi="NA",0,IF(Loans!M$5-year_refi-1<0,0,OFFSET('1st Mortgage Re-Fi'!$C$12,0,Loans!M$5-year_refi-1))) -> 0 | N23: =IF(year_refi="NA",0,IF(Loans!N$5-year_refi-1<0,0,OFFSET('1st Mortgage Re-Fi'!$C$12,0,Loans!N$5-year_refi-1))) -> 0 | O23: =IF(year_refi="NA",0,IF(Loans!O$5-year_refi-1<0,0,OFFSET('1st Mortgage Re-Fi'!$C$12,0,Loans!O$5-year_refi-1))) -> 0 | ... Q23: =IF(year_refi="NA",0,IF(Loans!Q$5-year_refi-1<0,0,OFFSET('1st Mortgage Re-Fi'!$C$12,0,Loans!Q$5-year_refi-1))) -> 0
G24: Interest Paid | H24: =IF(year_refi="NA",0,IF(Loans!H$5-year_refi-1<0,0,OFFSET('1st Mortgage Re-Fi'!$C$13,0,Loans!H$5-year_refi-1))) -> 0 | I24: =IF(year_refi="NA",0,IF(Loans!I$5-year_refi-1<0,0,OFFSET('1st Mortgage Re-Fi'!$C$13,0,Loans!I$5-year_refi-1))) -> 0 | J24: =IF(year_refi="NA",0,IF(Loans!J$5-year_refi-1<0,0,OFFSET('1st Mortgage Re-Fi'!$C$13,0,Loans!J$5-year_refi-1))) -> 0 | K24: =IF(year_refi="NA",0,IF(Loans!K$5-year_refi-1<0,0,OFFSET('1st Mortgage Re-Fi'!$C$13,0,Loans!K$5-year_refi-1))) -> 0 | L24: =IF(year_refi="NA",0,IF(Loans!L$5-year_refi-1<0,0,OFFSET('1st Mortgage Re-Fi'!$C$13,0,Loans!L$5-year_refi-1))) -> 0 | M24: =IF(year_refi="NA",0,IF(Loans!M$5-year_refi-1<0,0,OFFSET('1st Mortgage Re-Fi'!$C$13,0,Loans!M$5-year_refi-1))) -> 0 | N24: =IF(year_refi="NA",0,IF(Loans!N$5-year_refi-1<0,0,OFFSET('1st Mortgage Re-Fi'!$C$13,0,Loans!N$5-year_refi-1))) -> 0 | O24: =IF(year_refi="NA",0,IF(Loans!O$5-year_refi-1<0,0,OFFSET('1st Mortgage Re-Fi'!$C$13,0,Loans!O$5-year_refi-1))) -> 0 | ... Q24: =IF(year_refi="NA",0,IF(Loans!Q$5-year_refi-1<0,0,OFFSET('1st Mortgage Re-Fi'!$C$13,0,Loans!Q$5-year_refi-1))) -> 0
G25: Total Debt Service | H25: =H23+H24 -> 0 | I25: =I23+I24 -> 0 | J25: =J23+J24 -> 0 | K25: =K23+K24 -> 0 | L25: =L23+L24 -> 0 | M25: =M23+M24 -> 0 | N25: =N23+N24 -> 0 | O25: =O23+O24 -> 0 | ... Q25: =Q23+Q24 -> 0
G26: Ending Balance | H26: =IF(year_refi="NA",0,IF(Loans!H$5-year_refi-1<0,0,OFFSET('1st Mortgage Re-Fi'!$C$14,0,Loans!H$5-year_refi-1))) -> 0 | I26: =IF(year_refi="NA",0,IF(Loans!I$5-year_refi-1<0,0,OFFSET('1st Mortgage Re-Fi'!$C$14,0,Loans!I$5-year_refi-1))) -> 0 | J26: =IF(year_refi="NA",0,IF(Loans!J$5-year_refi-1<0,0,OFFSET('1st Mortgage Re-Fi'!$C$14,0,Loans!J$5-year_refi-1))) -> 0 | K26: =IF(year_refi="NA",0,IF(Loans!K$5-year_refi-1<0,0,OFFSET('1st Mortgage Re-Fi'!$C$14,0,Loans!K$5-year_refi-1))) -> 0 | L26: =IF(year_refi="NA",0,IF(Loans!L$5-year_refi-1<0,0,OFFSET('1st Mortgage Re-Fi'!$C$14,0,Loans!L$5-year_refi-1))) -> 0 | M26: =IF(year_refi="NA",0,IF(Loans!M$5-year_refi-1<0,0,OFFSET('1st Mortgage Re-Fi'!$C$14,0,Loans!M$5-year_refi-1))) -> 0 | N26: =IF(year_refi="NA",0,IF(Loans!N$5-year_refi-1<0,0,OFFSET('1st Mortgage Re-Fi'!$C$14,0,Loans!N$5-year_refi-1))) -> 0 | O26: =IF(year_refi="NA",0,IF(Loans!O$5-year_refi-1<0,0,OFFSET('1st Mortgage Re-Fi'!$C$14,0,Loans!O$5-year_refi-1))) -> 0 | ... Q26: =IF(year_refi="NA",0,IF(Loans!Q$5-year_refi-1<0,0,OFFSET('1st Mortgage Re-Fi'!$C$14,0,Loans!Q$5-year_refi-1))) -> 0
G28: TOTALS
G29: Beginning Balance | H29: =H8+H15+H22 -> 0 | I29: =I8+I15+I22 -> 0 | J29: =J8+J15+J22 -> 0 | K29: =K8+K15+K22 -> 0 | L29: =L8+L15+L22 -> 0 | M29: =M8+M15+M22 -> 0 | N29: =N8+N15+N22 -> 0 | O29: =O8+O15+O22 -> 0 | ... Q29: =Q8+Q15+Q22 -> 0
G30: Interest Paid | H30: =H10+H17+H24 -> 0 | I30: =I10+I17+I24 -> 0 | J30: =J10+J17+J24 -> 0 | K30: =K10+K17+K24 -> 0 | L30: =L10+L17+L24 -> 0 | M30: =M10+M17+M24 -> 0 | N30: =N10+N17+N24 -> 0 | O30: =O10+O17+O24 -> 0 | ... Q30: =Q10+Q17+Q24 -> 0
G31: Cumulative Interest | H31: =H30 -> 0 | I31: =I30+H31 -> 0 | J31: =J30+I31 -> 0 | K31: =K30+J31 -> 0 | L31: =L30+K31 -> 0 | M31: =M30+L31 -> 0 | N31: =N30+M31 -> 0 | O31: =O30+N31 -> 0 | P31: =P30+O31 -> 0 | Q31: =Q30+P31 -> 0
G32: Principal Paid | H32: =H9+H16+H23 -> 0 | I32: =I9+I16+I23 -> 0 | J32: =J9+J16+J23 -> 0 | K32: =K9+K16+K23 -> 0 | L32: =L9+L16+L23 -> 0 | M32: =M9+M16+M23 -> 0 | N32: =N9+N16+N23 -> 0 | O32: =O9+O16+O23 -> 0 | ... Q32: =Q9+Q16+Q23 -> 0
G33: Cumulative Principal | H33: =H32 -> 0 | I33: =I32+H33 -> 0 | J33: =J32+I33 -> 0 | K33: =K32+J33 -> 0 | L33: =L32+K33 -> 0 | M33: =M32+L33 -> 0 | N33: =N32+M33 -> 0 | O33: =O32+N33 -> 0 | P33: =P32+O33 -> 0 | Q33: =Q32+P33 -> 0
G34: Total Debt Service | H34: =H11+H18+H25 -> 0 | I34: =I11+I18+I25 -> 0 | J34: =J11+J18+J25 -> 0 | K34: =K11+K18+K25 -> 0 | L34: =L11+L18+L25 -> 0 | M34: =M11+M18+M25 -> 0 | N34: =N11+N18+N25 -> 0 | O34: =O11+O18+O25 -> 0 | ... Q34: =Q11+Q18+Q25 -> 0
G35: Ending Balance | H35: =H12+H19+H26 -> 0 | I35: =I12+I19+I26 -> 0 | J35: =J12+J19+J26 -> 0 | K35: =K12+K19+K26 -> 0 | L35: =L12+L19+L26 -> 0 | M35: =M12+M19+M26 -> 0 | N35: =N12+N19+N26 -> 0 | O35: =O12+O19+O26 -> 0 | ... Q35: =Q12+Q19+Q26 -> 0
B37: =copyright -> Copyright © 2026 Michael Blank.
B38: The information herein is not guaranteed but believed to be accurate.

Sheet 1st Mortgage 1
A1: Simple Interest Loan Amortization Table - 1st Mortgage
B3: Loan Amount | D3: =Summary!D10 -> 0 | E3: Use drop down menu to | H3: Option 1
B4: Interest Rate | D4: =Summary!D11 -> 0.05 | E4: select option for amortization schedule | H4: Amortlization schedule based on full number of years, including any interest-only period
B5: Number of Years | D5: =Summary!D12 -> 30 | H5: Ex. 25 year tern, 2 years of I/O = 25-year amortization schedule
B6: Interest-Only (Months) | D6: =Summary!D13 -> 0 | F6: Option 1
B7: Monthly Payment | D7: =IF($F$6="Option 1",PMT(D4/12,(D5*12),-D3),PMT(D4/12,(D5*12)-D6,-D3)) -> 0 | H7: Option 2
B8: Total Interest Paid | D8: =SUM(D17:D378) -> 0 | H8: Amortlization schedule based on number of years after any interest-only period
B9: Annual Debt Service | D9: =SUM(C18:C29) -> 0 | H9: Ex. 25 year term, 2 years of I/O = 23-year amortization schedule
B11: End of Year | C11: 1 | D11: =C11+1 -> 2 | E11: =D11+1 -> 3 | F11: =E11+1 -> 4 | G11: =F11+1 -> 5 | H11: =G11+1 -> 6 | I11: =H11+1 -> 7 | J11: =I11+1 -> 8 | K11: =J11+1 -> 9 | L11: =K11+1 -> 10
B12: Principal | C12: =OFFSET($G$17,12*C11,0) -> 0 | D12: =IF(D11<=Summary!$D$12,OFFSET($G$17,12*D11,0)-SUM(A12:C12),0) -> 0 | E12: =IF(E11<=Summary!$D$12,OFFSET($G$17,12*E11,0)-SUM(B12:D12),0) -> 0 | F12: =IF(F11<=Summary!$D$12,OFFSET($G$17,12*F11,0)-SUM(C12:E12),0) -> 0 | G12: =IF(G11<=Summary!$D$12,OFFSET($G$17,12*G11,0)-SUM(A12:F12),0) -> 0 | H12: =IF(H11<=Summary!$D$12,OFFSET($G$17,12*H11,0)-SUM(B12:G12),0) -> 0 | I12: =IF(I11<=Summary!$D$12,OFFSET($G$17,12*I11,0)-SUM(C12:H12),0) -> 0 | J12: =IF(J11<=Summary!$D$12,OFFSET($G$17,12*J11,0)-SUM(A12:I12),0) -> 0 | K12: =IF(K11<=Summary!$D$12,OFFSET($G$17,12*K11,0)-SUM(B12:J12),0) -> 0 | L12: =IF(L11<=Summary!$D$12,OFFSET($G$17,12*L11,0)-SUM(C12:K12),0) -> 0
B13: Interest | C13: =OFFSET($E$17,12*C11,0) -> 0 | D13: =IF(D11<=Summary!$D$12,OFFSET($E$17,12*D11,0)-SUM(A13:C13),0) -> 0 | E13: =IF(E11<=Summary!$D$12,OFFSET($E$17,12*E11,0)-SUM(B13:D13),0) -> 0 | F13: =IF(F11<=Summary!$D$12,OFFSET($E$17,12*F11,0)-SUM(C13:E13),0) -> 0 | G13: =IF(G11<=Summary!$D$12,OFFSET($E$17,12*G11,0)-SUM(A13:F13),0) -> 0 | H13: =IF(H11<=Summary!$D$12,OFFSET($E$17,12*H11,0)-SUM(B13:G13),0) -> 0 | I13: =IF(I11<=Summary!$D$12,OFFSET($E$17,12*I11,0)-SUM(C13:H13),0) -> 0 | J13: =IF(J11<=Summary!$D$12,OFFSET($E$17,12*J11,0)-SUM(A13:I13),0) -> 0 | K13: =IF(K11<=Summary!$D$12,OFFSET($E$17,12*K11,0)-SUM(B13:J13),0) -> 0 | L13: =IF(L11<=Summary!$D$12,OFFSET($E$17,12*L11,0)-SUM(C13:K13),0) -> 0
B14: Balance | C14: =OFFSET($H$17,C11*12,0) -> 0 | D14: =IF(D11<=Summary!$D$12,OFFSET($H$17,D11*12,0),0) -> 0 | E14: =IF(E11<=Summary!$D$12,OFFSET($H$17,E11*12,0),0) -> 0 | F14: =IF(F11<=Summary!$D$12,OFFSET($H$17,F11*12,0),0) -> 0 | G14: =IF(G11<=Summary!$D$12,OFFSET($H$17,G11*12,0),0) -> 0 | H14: =IF(H11<=Summary!$D$12,OFFSET($H$17,H11*12,0),0) -> 0 | I14: =IF(I11<=Summary!$D$12,OFFSET($H$17,I11*12,0),0) -> 0 | J14: =IF(J11<=Summary!$D$12,OFFSET($H$17,J11*12,0),0) -> 0 | K14: =IF(K11<=Summary!$D$12,OFFSET($H$17,K11*12,0),0) -> 0 | L14: =IF(L11<=Summary!$D$12,OFFSET($H$17,L11*12,0),0) -> 0
B16: Month | C16: Payment Amount | D16: Interest | E16: Cumulative Interest | F16: Principal | G16: Principal Paid | H16: Balance
H17: =D3 -> 0
B18: =IF(B17>=$D$5*12+$D$6,"",B17+1) -> 1 | C18: =IF(B18="","-",IF(B18<=$D$6,D18, $D$7)) -> 0 | D18: =IF(B18="","-",$D$4/12*H17) -> 0 | E18: =IF(B18="","-",SUM($D$18:D18)) -> 0 | F18: =IF(B18="","-",C18-D18) -> 0 | G18: =IF(B18="","-",SUM($F$18:F18)) -> 0 | H18: =IF(B18="","-",H17-F18) -> 0
B19: =IF(B18>=$D$5*12+$D$6,"",B18+1) -> 2 | C19: =IF(B19="","-",IF(B19<=$D$6,D19, $D$7)) -> 0 | D19: =IF(B19="","-",$D$4/12*H18) -> 0 | E19: =IF(B19="","-",SUM($D$18:D19)) -> 0 | F19: =IF(B19="","-",C19-D19) -> 0 | G19: =IF(B19="","-",SUM($F$18:F19)) -> 0 | H19: =IF(B19="","-",H18-F19) -> 0
B20: =IF(B19>=$D$5*12+$D$6,"",B19+1) -> 3 | C20: =IF(B20="","-",IF(B20<=$D$6,D20, $D$7)) -> 0 | D20: =IF(B20="","-",$D$4/12*H19) -> 0 | E20: =IF(B20="","-",SUM($D$18:D20)) -> 0 | F20: =IF(B20="","-",C20-D20) -> 0 | G20: =IF(B20="","-",SUM($F$18:F20)) -> 0 | H20: =IF(B20="","-",H19-F20) -> 0
B21: =IF(B20>=$D$5*12+$D$6,"",B20+1) -> 4 | C21: =IF(B21="","-",IF(B21<=$D$6,D21, $D$7)) -> 0 | D21: =IF(B21="","-",$D$4/12*H20) -> 0 | E21: =IF(B21="","-",SUM($D$18:D21)) -> 0 | F21: =IF(B21="","-",C21-D21) -> 0 | G21: =IF(B21="","-",SUM($F$18:F21)) -> 0 | H21: =IF(B21="","-",H20-F21) -> 0
B22: =IF(B21>=$D$5*12+$D$6,"",B21+1) -> 5 | C22: =IF(B22="","-",IF(B22<=$D$6,D22, $D$7)) -> 0 | D22: =IF(B22="","-",$D$4/12*H21) -> 0 | E22: =IF(B22="","-",SUM($D$18:D22)) -> 0 | F22: =IF(B22="","-",C22-D22) -> 0 | G22: =IF(B22="","-",SUM($F$18:F22)) -> 0 | H22: =IF(B22="","-",H21-F22) -> 0
B23: =IF(B22>=$D$5*12+$D$6,"",B22+1) -> 6 | C23: =IF(B23="","-",IF(B23<=$D$6,D23, $D$7)) -> 0 | D23: =IF(B23="","-",$D$4/12*H22) -> 0 | E23: =IF(B23="","-",SUM($D$18:D23)) -> 0 | F23: =IF(B23="","-",C23-D23) -> 0 | G23: =IF(B23="","-",SUM($F$18:F23)) -> 0 | H23: =IF(B23="","-",H22-F23) -> 0
B24: =IF(B23>=$D$5*12+$D$6,"",B23+1) -> 7 | C24: =IF(B24="","-",IF(B24<=$D$6,D24, $D$7)) -> 0 | D24: =IF(B24="","-",$D$4/12*H23) -> 0 | E24: =IF(B24="","-",SUM($D$18:D24)) -> 0 | F24: =IF(B24="","-",C24-D24) -> 0 | G24: =IF(B24="","-",SUM($F$18:F24)) -> 0 | H24: =IF(B24="","-",H23-F24) -> 0
B25: =IF(B24>=$D$5*12+$D$6,"",B24+1) -> 8 | C25: =IF(B25="","-",IF(B25<=$D$6,D25, $D$7)) -> 0 | D25: =IF(B25="","-",$D$4/12*H24) -> 0 | E25: =IF(B25="","-",SUM($D$18:D25)) -> 0 | F25: =IF(B25="","-",C25-D25) -> 0 | G25: =IF(B25="","-",SUM($F$18:F25)) -> 0 | H25: =IF(B25="","-",H24-F25) -> 0
B26: =IF(B25>=$D$5*12+$D$6,"",B25+1) -> 9 | C26: =IF(B26="","-",IF(B26<=$D$6,D26, $D$7)) -> 0 | D26: =IF(B26="","-",$D$4/12*H25) -> 0 | E26: =IF(B26="","-",SUM($D$18:D26)) -> 0 | F26: =IF(B26="","-",C26-D26) -> 0 | G26: =IF(B26="","-",SUM($F$18:F26)) -> 0 | H26: =IF(B26="","-",H25-F26) -> 0
B27: =IF(B26>=$D$5*12+$D$6,"",B26+1) -> 10 | C27: =IF(B27="","-",IF(B27<=$D$6,D27, $D$7)) -> 0 | D27: =IF(B27="","-",$D$4/12*H26) -> 0 | E27: =IF(B27="","-",SUM($D$18:D27)) -> 0 | F27: =IF(B27="","-",C27-D27) -> 0 | G27: =IF(B27="","-",SUM($F$18:F27)) -> 0 | H27: =IF(B27="","-",H26-F27) -> 0
B28: =IF(B27>=$D$5*12+$D$6,"",B27+1) -> 11 | C28: =IF(B28="","-",IF(B28<=$D$6,D28, $D$7)) -> 0 | D28: =IF(B28="","-",$D$4/12*H27) -> 0 | E28: =IF(B28="","-",SUM($D$18:D28)) -> 0 | F28: =IF(B28="","-",C28-D28) -> 0 | G28: =IF(B28="","-",SUM($F$18:F28)) -> 0 | H28: =IF(B28="","-",H27-F28) -> 0
B29: =IF(B28>=$D$5*12+$D$6,"",B28+1) -> 12 | C29: =IF(B29="","-",IF(B29<=$D$6,D29, $D$7)) -> 0 | D29: =IF(B29="","-",$D$4/12*H28) -> 0 | E29: =IF(B29="","-",SUM($D$18:D29)) -> 0 | F29: =IF(B29="","-",C29-D29) -> 0 | G29: =IF(B29="","-",SUM($F$18:F29)) -> 0 | H29: =IF(B29="","-",H28-F29) -> 0
B30: =IF(B29>=$D$5*12,"",B29+1) -> 13 | C30: =IF(B30="","-",IF(B30<=$D$6,D30, $D$7)) -> 0 | D30: =IF(B30="","-",$D$4/12*H29) -> 0 | E30: =IF(B30="","-",SUM($D$18:D30)) -> 0 | F30: =IF(B30="","-",C30-D30) -> 0 | G30: =IF(B30="","-",SUM($F$18:F30)) -> 0 | H30: =IF(B30="","-",H29-F30) -> 0
B31: =IF(B30>=$D$5*12,"",B30+1) -> 14 | C31: =IF(B31="","-",IF(B31<=$D$6,D31, $D$7)) -> 0 | D31: =IF(B31="","-",$D$4/12*H30) -> 0 | E31: =IF(B31="","-",SUM($D$18:D31)) -> 0 | F31: =IF(B31="","-",C31-D31) -> 0 | G31: =IF(B31="","-",SUM($F$18:F31)) -> 0 | H31: =IF(B31="","-",H30-F31) -> 0
B32: =IF(B31>=$D$5*12,"",B31+1) -> 15 | C32: =IF(B32="","-",IF(B32<=$D$6,D32, $D$7)) -> 0 | D32: =IF(B32="","-",$D$4/12*H31) -> 0 | E32: =IF(B32="","-",SUM($D$18:D32)) -> 0 | F32: =IF(B32="","-",C32-D32) -> 0 | G32: =IF(B32="","-",SUM($F$18:F32)) -> 0 | H32: =IF(B32="","-",H31-F32) -> 0
B33: =IF(B32>=$D$5*12,"",B32+1) -> 16 | C33: =IF(B33="","-",IF(B33<=$D$6,D33, $D$7)) -> 0 | D33: =IF(B33="","-",$D$4/12*H32) -> 0 | E33: =IF(B33="","-",SUM($D$18:D33)) -> 0 | F33: =IF(B33="","-",C33-D33) -> 0 | G33: =IF(B33="","-",SUM($F$18:F33)) -> 0 | H33: =IF(B33="","-",H32-F33) -> 0
B34: =IF(B33>=$D$5*12,"",B33+1) -> 17 | C34: =IF(B34="","-",IF(B34<=$D$6,D34, $D$7)) -> 0 | D34: =IF(B34="","-",$D$4/12*H33) -> 0 | E34: =IF(B34="","-",SUM($D$18:D34)) -> 0 | F34: =IF(B34="","-",C34-D34) -> 0 | G34: =IF(B34="","-",SUM($F$18:F34)) -> 0 | H34: =IF(B34="","-",H33-F34) -> 0
B35: =IF(B34>=$D$5*12,"",B34+1) -> 18 | C35: =IF(B35="","-",IF(B35<=$D$6,D35, $D$7)) -> 0 | D35: =IF(B35="","-",$D$4/12*H34) -> 0 | E35: =IF(B35="","-",SUM($D$18:D35)) -> 0 | F35: =IF(B35="","-",C35-D35) -> 0 | G35: =IF(B35="","-",SUM($F$18:F35)) -> 0 | H35: =IF(B35="","-",H34-F35) -> 0
B36: =IF(B35>=$D$5*12,"",B35+1) -> 19 | C36: =IF(B36="","-",IF(B36<=$D$6,D36, $D$7)) -> 0 | D36: =IF(B36="","-",$D$4/12*H35) -> 0 | E36: =IF(B36="","-",SUM($D$18:D36)) -> 0 | F36: =IF(B36="","-",C36-D36) -> 0 | G36: =IF(B36="","-",SUM($F$18:F36)) -> 0 | H36: =IF(B36="","-",H35-F36) -> 0
B37: =IF(B36>=$D$5*12,"",B36+1) -> 20 | C37: =IF(B37="","-",IF(B37<=$D$6,D37, $D$7)) -> 0 | D37: =IF(B37="","-",$D$4/12*H36) -> 0 | E37: =IF(B37="","-",SUM($D$18:D37)) -> 0 | F37: =IF(B37="","-",C37-D37) -> 0 | G37: =IF(B37="","-",SUM($F$18:F37)) -> 0 | H37: =IF(B37="","-",H36-F37) -> 0
B38: =IF(B37>=$D$5*12,"",B37+1) -> 21 | C38: =IF(B38="","-",IF(B38<=$D$6,D38, $D$7)) -> 0 | D38: =IF(B38="","-",$D$4/12*H37) -> 0 | E38: =IF(B38="","-",SUM($D$18:D38)) -> 0 | F38: =IF(B38="","-",C38-D38) -> 0 | G38: =IF(B38="","-",SUM($F$18:F38)) -> 0 | H38: =IF(B38="","-",H37-F38) -> 0
B39: =IF(B38>=$D$5*12,"",B38+1) -> 22 | C39: =IF(B39="","-",IF(B39<=$D$6,D39, $D$7)) -> 0 | D39: =IF(B39="","-",$D$4/12*H38) -> 0 | E39: =IF(B39="","-",SUM($D$18:D39)) -> 0 | F39: =IF(B39="","-",C39-D39) -> 0 | G39: =IF(B39="","-",SUM($F$18:F39)) -> 0 | H39: =IF(B39="","-",H38-F39) -> 0
B40: =IF(B39>=$D$5*12,"",B39+1) -> 23 | C40: =IF(B40="","-",IF(B40<=$D$6,D40, $D$7)) -> 0 | D40: =IF(B40="","-",$D$4/12*H39) -> 0 | E40: =IF(B40="","-",SUM($D$18:D40)) -> 0 | F40: =IF(B40="","-",C40-D40) -> 0 | G40: =IF(B40="","-",SUM($F$18:F40)) -> 0 | H40: =IF(B40="","-",H39-F40) -> 0
B41: =IF(B40>=$D$5*12,"",B40+1) -> 24 | C41: =IF(B41="","-",IF(B41<=$D$6,D41, $D$7)) -> 0 | D41: =IF(B41="","-",$D$4/12*H40) -> 0 | E41: =IF(B41="","-",SUM($D$18:D41)) -> 0 | F41: =IF(B41="","-",C41-D41) -> 0 | G41: =IF(B41="","-",SUM($F$18:F41)) -> 0 | H41: =IF(B41="","-",H40-F41) -> 0
... B257: =IF(B256>=$D$5*12,"",B256+1) -> 240 | C257: =IF(B257="","-",IF(B257<=$D$6,D257, $D$7)) -> 0 | D257: =IF(B257="","-",$D$4/12*H256) -> 0 | E257: =IF(B257="","-",SUM($D$18:D257)) -> 0 | F257: =IF(B257="","-",C257-D257) -> 0 | G257: =IF(B257="","-",SUM($F$18:F257)) -> 0 | H257: =IF(B257="","-",H256-F257) -> 0
B258: =IF(B257>=$D$5*12,"",B257+1) -> 241 | C258: =IF(B258="","-",$D$7) -> 0 | D258: =IF(B258="","-",$D$4/12*H257) -> 0 | E258: =IF(B258="","-",SUM($D$18:D258)) -> 0 | F258: =IF(B258="","-",C258-D258) -> 0 | G258: =IF(B258="","-",SUM($F$18:F258)) -> 0 | H258: =IF(B258="","-",H257-F258) -> 0
B259: =IF(B258>=$D$5*12,"",B258+1) -> 242 | C259: =IF(B259="","-",$D$7) -> 0 | D259: =IF(B259="","-",$D$4/12*H258) -> 0 | E259: =IF(B259="","-",SUM($D$18:D259)) -> 0 | F259: =IF(B259="","-",C259-D259) -> 0 | G259: =IF(B259="","-",SUM($F$18:F259)) -> 0 | H259: =IF(B259="","-",H258-F259) -> 0
B260: =IF(B259>=$D$5*12,"",B259+1) -> 243 | C260: =IF(B260="","-",$D$7) -> 0 | D260: =IF(B260="","-",$D$4/12*H259) -> 0 | E260: =IF(B260="","-",SUM($D$18:D260)) -> 0 | F260: =IF(B260="","-",C260-D260) -> 0 | G260: =IF(B260="","-",SUM($F$18:F260)) -> 0 | H260: =IF(B260="","-",H259-F260) -> 0
B261: =IF(B260>=$D$5*12,"",B260+1) -> 244 | C261: =IF(B261="","-",$D$7) -> 0 | D261: =IF(B261="","-",$D$4/12*H260) -> 0 | E261: =IF(B261="","-",SUM($D$18:D261)) -> 0 | F261: =IF(B261="","-",C261-D261) -> 0 | G261: =IF(B261="","-",SUM($F$18:F261)) -> 0 | H261: =IF(B261="","-",H260-F261) -> 0
B262: =IF(B261>=$D$5*12,"",B261+1) -> 245 | C262: =IF(B262="","-",$D$7) -> 0 | D262: =IF(B262="","-",$D$4/12*H261) -> 0 | E262: =IF(B262="","-",SUM($D$18:D262)) -> 0 | F262: =IF(B262="","-",C262-D262) -> 0 | G262: =IF(B262="","-",SUM($F$18:F262)) -> 0 | H262: =IF(B262="","-",H261-F262) -> 0
B263: =IF(B262>=$D$5*12,"",B262+1) -> 246 | C263: =IF(B263="","-",$D$7) -> 0 | D263: =IF(B263="","-",$D$4/12*H262) -> 0 | E263: =IF(B263="","-",SUM($D$18:D263)) -> 0 | F263: =IF(B263="","-",C263-D263) -> 0 | G263: =IF(B263="","-",SUM($F$18:F263)) -> 0 | H263: =IF(B263="","-",H262-F263) -> 0
B264: =IF(B263>=$D$5*12,"",B263+1) -> 247 | C264: =IF(B264="","-",$D$7) -> 0 | D264: =IF(B264="","-",$D$4/12*H263) -> 0 | E264: =IF(B264="","-",SUM($D$18:D264)) -> 0 | F264: =IF(B264="","-",C264-D264) -> 0 | G264: =IF(B264="","-",SUM($F$18:F264)) -> 0 | H264: =IF(B264="","-",H263-F264) -> 0
B265: =IF(B264>=$D$5*12,"",B264+1) -> 248 | C265: =IF(B265="","-",$D$7) -> 0 | D265: =IF(B265="","-",$D$4/12*H264) -> 0 | E265: =IF(B265="","-",SUM($D$18:D265)) -> 0 | F265: =IF(B265="","-",C265-D265) -> 0 | G265: =IF(B265="","-",SUM($F$18:F265)) -> 0 | H265: =IF(B265="","-",H264-F265) -> 0
B266: =IF(B265>=$D$5*12,"",B265+1) -> 249 | C266: =IF(B266="","-",$D$7) -> 0 | D266: =IF(B266="","-",$D$4/12*H265) -> 0 | E266: =IF(B266="","-",SUM($D$18:D266)) -> 0 | F266: =IF(B266="","-",C266-D266) -> 0 | G266: =IF(B266="","-",SUM($F$18:F266)) -> 0 | H266: =IF(B266="","-",H265-F266) -> 0
B267: =IF(B266>=$D$5*12,"",B266+1) -> 250 | C267: =IF(B267="","-",$D$7) -> 0 | D267: =IF(B267="","-",$D$4/12*H266) -> 0 | E267: =IF(B267="","-",SUM($D$18:D267)) -> 0 | F267: =IF(B267="","-",C267-D267) -> 0 | G267: =IF(B267="","-",SUM($F$18:F267)) -> 0 | H267: =IF(B267="","-",H266-F267) -> 0
B268: =IF(B267>=$D$5*12,"",B267+1) -> 251 | C268: =IF(B268="","-",$D$7) -> 0 | D268: =IF(B268="","-",$D$4/12*H267) -> 0 | E268: =IF(B268="","-",SUM($D$18:D268)) -> 0 | F268: =IF(B268="","-",C268-D268) -> 0 | G268: =IF(B268="","-",SUM($F$18:F268)) -> 0 | H268: =IF(B268="","-",H267-F268) -> 0
B269: =IF(B268>=$D$5*12,"",B268+1) -> 252 | C269: =IF(B269="","-",$D$7) -> 0 | D269: =IF(B269="","-",$D$4/12*H268) -> 0 | E269: =IF(B269="","-",SUM($D$18:D269)) -> 0 | F269: =IF(B269="","-",C269-D269) -> 0 | G269: =IF(B269="","-",SUM($F$18:F269)) -> 0 | H269: =IF(B269="","-",H268-F269) -> 0
... B378: =IF(B377>=$D$5*12,"",B377+1) | C378: =IF(B378="","-",$D$7) -> - | D378: =IF(B378="","-",$D$4/12*H377) -> - | E378: =IF(B378="","-",SUM($D$18:D378)) -> - | F378: =IF(B378="","-",C378-D378) -> - | G378: =IF(B378="","-",SUM($F$18:F378)) -> - | H378: =IF(B378="","-",H377-F378) -> -
B381: =copyright -> Copyright © 2026 Michael Blank.
B382: The information herein is not guaranteed but believed to be accurate.

Sheet 2nd Mortgage 1
A1: Simple Interest Loan Amortization Table - 2nd Mortgage
B3: Loan Amount | D3: =Summary!D14 -> 0 | E3: Use drop down menu to | H3: Option 1
B4: Interest Rate | D4: =Summary!D15 -> 0 | E4: select option for amortization schedule | H4: Amortlization schedule based on full number of years, including any interest-only period
B5: Number of Years | D5: =Summary!D16 -> 0 | H5: Ex. 25 year tern, 2 years of I/O = 25-year amortization schedule
B6: Interest-Only (Months) | D6: =Summary!D17 -> 0 | F6: Option 1
B7: Monthly Payment | D7: =IF(D3=0,0,IF($F$6="Option 1",PMT(D4/12,(D5*12),-D3),PMT(D4/12,(D5*12)-D6,-D3))) -> 0 | H7: Option 2
B8: Total Interest Paid | D8: =SUM(D17:D378) -> 0 | H8: Amortlization schedule based on number of years after any interest-only period
B9: Annual Debt Service | D9: =SUM(C18:C29) -> 0 | H9: Ex. 25 year term, 2 years of I/O = 23-year amortization schedule
B11: End of Year | C11: 1 | D11: =C11+1 -> 2 | E11: =D11+1 -> 3 | F11: =E11+1 -> 4 | G11: =F11+1 -> 5 | H11: =G11+1 -> 6 | I11: =H11+1 -> 7 | J11: =I11+1 -> 8 | K11: =J11+1 -> 9 | L11: =K11+1 -> 10
B12: Principal | C12: =IF(C11<=Summary!$D$16,OFFSET($G$17,12*C11,0),0) -> 0 | D12: =IF(D11<=Summary!$D$16,OFFSET($G$17,12*D11,0)-C12,0) -> 0 | E12: =IF(E11<=Summary!$D$16,OFFSET($G$17,12*E11,0)-SUM(C12:D12),0) -> 0 | F12: =IF(F11<=Summary!$D$16,OFFSET($G$17,12*F11,0)-SUM(C12:E12),0) -> 0 | G12: =IF(G11<=Summary!$D$16,OFFSET($G$17,12*G11,0)-SUM(C12:F12),0) -> 0 | H12: =IF(H11<=Summary!$D$16,OFFSET($G$17,12*H11,0)-SUM(C12:G12),0) -> 0 | I12: =IF(I11<=Summary!$D$16,OFFSET($G$17,12*I11,0)-SUM(C12:H12),0) -> 0 | J12: =IF(J11<=Summary!$D$16,OFFSET($G$17,12*J11,0)-SUM(C12:I12),0) -> 0 | K12: =IF(K11<=Summary!$D$16,OFFSET($G$17,12*K11,0)-SUM(C12:J12),0) -> 0 | L12: =IF(L11<=Summary!$D$16,OFFSET($G$17,12*L11,0)-SUM(C12:K12),0) -> 0
B13: Interest | C13: =IF(C11<=Summary!$D$16,OFFSET($E$17,12*C11,0),0) -> 0 | D13: =IF(D11<=Summary!$D$16,OFFSET($E$17,12*D11,0)-C13,0) -> 0 | E13: =IF(E11<=Summary!$D$16,OFFSET($E$17,12*E11,0)-SUM(C13:D13),0) -> 0 | F13: =IF(F11<=Summary!$D$16,OFFSET($E$17,12*F11,0)-SUM(C13:E13),0) -> 0 | G13: =IF(G11<=Summary!$D$16,OFFSET($E$17,12*G11,0)-SUM(C13:F13),0) -> 0 | H13: =IF(H11<=Summary!$D$16,OFFSET($E$17,12*H11,0)-SUM(C13:G13),0) -> 0 | I13: =IF(I11<=Summary!$D$16,OFFSET($E$17,12*I11,0)-SUM(C13:H13),0) -> 0 | J13: =IF(J11<=Summary!$D$16,OFFSET($E$17,12*J11,0)-SUM(C13:I13),0) -> 0 | K13: =IF(K11<=Summary!$D$16,OFFSET($E$17,12*K11,0)-SUM(C13:J13),0) -> 0 | L13: =IF(L11<=Summary!$D$16,OFFSET($E$17,12*L11,0)-SUM(C13:K13),0) -> 0
B14: Balance | C14: =IF(C11<=Summary!$D$16,OFFSET($H$17,C11*12,0),0) -> 0 | D14: =IF(D11<=Summary!$D$16,OFFSET($H$17,D11*12,0),0) -> 0 | E14: =IF(E11<=Summary!$D$16,OFFSET($H$17,E11*12,0),0) -> 0 | F14: =IF(F11<=Summary!$D$16,OFFSET($H$17,F11*12,0),0) -> 0 | G14: =IF(G11<=Summary!$D$16,OFFSET($H$17,G11*12,0),0) -> 0 | H14: =IF(H11<=Summary!$D$16,OFFSET($H$17,H11*12,0),0) -> 0 | I14: =IF(I11<=Summary!$D$16,OFFSET($H$17,I11*12,0),0) -> 0 | J14: =IF(J11<=Summary!$D$16,OFFSET($H$17,J11*12,0),0) -> 0 | ... L14: =IF(L11<=Summary!$D$16,OFFSET($H$17,L11*12,0),0) -> 0
B16: Month | C16: Payment Amount | D16: Interest | E16: Cumulative Interest | F16: Principal | G16: Principal Paid | H16: Balance
H17: =D3 -> 0
B18: =IF(B17>=$D$5*12+$D$6,"",B17+1) | C18: =IF(B18="","-",IF(B18<=$D$6,D18, $D$7)) -> - | D18: =IF(B18="","-",$D$4/12*H17) -> - | E18: =IF(B18="","-",SUM($D$18:D18)) -> - | F18: =IF(B18="","-",C18-D18) -> - | G18: =IF(B18="","-",SUM($F$18:F18)) -> - | H18: =IF(B18="","-",H17-F18) -> -
B19: =IF(B18>=$D$5*12+$D$6,"",B18+1) | C19: =IF(B19="","-",IF(B19<=$D$6,D19, $D$7)) -> - | D19: =IF(B19="","-",$D$4/12*H18) -> - | E19: =IF(B19="","-",SUM($D$18:D19)) -> - | F19: =IF(B19="","-",C19-D19) -> - | G19: =IF(B19="","-",SUM($F$18:F19)) -> - | H19: =IF(B19="","-",H18-F19) -> -
B20: =IF(B19>=$D$5*12+$D$6,"",B19+1) | C20: =IF(B20="","-",IF(B20<=$D$6,D20, $D$7)) -> - | D20: =IF(B20="","-",$D$4/12*H19) -> - | E20: =IF(B20="","-",SUM($D$18:D20)) -> - | F20: =IF(B20="","-",C20-D20) -> - | G20: =IF(B20="","-",SUM($F$18:F20)) -> - | H20: =IF(B20="","-",H19-F20) -> -
B21: =IF(B20>=$D$5*12+$D$6,"",B20+1) | C21: =IF(B21="","-",IF(B21<=$D$6,D21, $D$7)) -> - | D21: =IF(B21="","-",$D$4/12*H20) -> - | E21: =IF(B21="","-",SUM($D$18:D21)) -> - | F21: =IF(B21="","-",C21-D21) -> - | G21: =IF(B21="","-",SUM($F$18:F21)) -> - | H21: =IF(B21="","-",H20-F21) -> -
B22: =IF(B21>=$D$5*12+$D$6,"",B21+1) | C22: =IF(B22="","-",IF(B22<=$D$6,D22, $D$7)) -> - | D22: =IF(B22="","-",$D$4/12*H21) -> - | E22: =IF(B22="","-",SUM($D$18:D22)) -> - | F22: =IF(B22="","-",C22-D22) -> - | G22: =IF(B22="","-",SUM($F$18:F22)) -> - | H22: =IF(B22="","-",H21-F22) -> -
B23: =IF(B22>=$D$5*12+$D$6,"",B22+1) | C23: =IF(B23="","-",IF(B23<=$D$6,D23, $D$7)) -> - | D23: =IF(B23="","-",$D$4/12*H22) -> - | E23: =IF(B23="","-",SUM($D$18:D23)) -> - | F23: =IF(B23="","-",C23-D23) -> - | G23: =IF(B23="","-",SUM($F$18:F23)) -> - | H23: =IF(B23="","-",H22-F23) -> -
B24: =IF(B23>=$D$5*12+$D$6,"",B23+1) | C24: =IF(B24="","-",IF(B24<=$D$6,D24, $D$7)) -> - | D24: =IF(B24="","-",$D$4/12*H23) -> - | E24: =IF(B24="","-",SUM($D$18:D24)) -> - | F24: =IF(B24="","-",C24-D24) -> - | G24: =IF(B24="","-",SUM($F$18:F24)) -> - | H24: =IF(B24="","-",H23-F24) -> -
B25: =IF(B24>=$D$5*12+$D$6,"",B24+1) | C25: =IF(B25="","-",IF(B25<=$D$6,D25, $D$7)) -> - | D25: =IF(B25="","-",$D$4/12*H24) -> - | E25: =IF(B25="","-",SUM($D$18:D25)) -> - | F25: =IF(B25="","-",C25-D25) -> - | G25: =IF(B25="","-",SUM($F$18:F25)) -> - | H25: =IF(B25="","-",H24-F25) -> -
B26: =IF(B25>=$D$5*12+$D$6,"",B25+1) | C26: =IF(B26="","-",IF(B26<=$D$6,D26, $D$7)) -> - | D26: =IF(B26="","-",$D$4/12*H25) -> - | E26: =IF(B26="","-",SUM($D$18:D26)) -> - | F26: =IF(B26="","-",C26-D26) -> - | G26: =IF(B26="","-",SUM($F$18:F26)) -> - | H26: =IF(B26="","-",H25-F26) -> -
B27: =IF(B26>=$D$5*12+$D$6,"",B26+1) | C27: =IF(B27="","-",IF(B27<=$D$6,D27, $D$7)) -> - | D27: =IF(B27="","-",$D$4/12*H26) -> - | E27: =IF(B27="","-",SUM($D$18:D27)) -> - | F27: =IF(B27="","-",C27-D27) -> - | G27: =IF(B27="","-",SUM($F$18:F27)) -> - | H27: =IF(B27="","-",H26-F27) -> -
B28: =IF(B27>=$D$5*12+$D$6,"",B27+1) | C28: =IF(B28="","-",IF(B28<=$D$6,D28, $D$7)) -> - | D28: =IF(B28="","-",$D$4/12*H27) -> - | E28: =IF(B28="","-",SUM($D$18:D28)) -> - | F28: =IF(B28="","-",C28-D28) -> - | G28: =IF(B28="","-",SUM($F$18:F28)) -> - | H28: =IF(B28="","-",H27-F28) -> -
B29: =IF(B28>=$D$5*12+$D$6,"",B28+1) | C29: =IF(B29="","-",IF(B29<=$D$6,D29, $D$7)) -> - | D29: =IF(B29="","-",$D$4/12*H28) -> - | E29: =IF(B29="","-",SUM($D$18:D29)) -> - | F29: =IF(B29="","-",C29-D29) -> - | G29: =IF(B29="","-",SUM($F$18:F29)) -> - | H29: =IF(B29="","-",H28-F29) -> -
B30: =IF(B29>=$D$5*12,"",B29+1) | C30: =IF(B30="","-",IF(B30<=$D$6,D30, $D$7)) -> - | D30: =IF(B30="","-",$D$4/12*H29) -> - | E30: =IF(B30="","-",SUM($D$18:D30)) -> - | F30: =IF(B30="","-",C30-D30) -> - | G30: =IF(B30="","-",SUM($F$18:F30)) -> - | H30: =IF(B30="","-",H29-F30) -> -
B31: =IF(B30>=$D$5*12,"",B30+1) | C31: =IF(B31="","-",IF(B31<=$D$6,D31, $D$7)) -> - | D31: =IF(B31="","-",$D$4/12*H30) -> - | E31: =IF(B31="","-",SUM($D$18:D31)) -> - | F31: =IF(B31="","-",C31-D31) -> - | G31: =IF(B31="","-",SUM($F$18:F31)) -> - | H31: =IF(B31="","-",H30-F31) -> -
B32: =IF(B31>=$D$5*12,"",B31+1) | C32: =IF(B32="","-",IF(B32<=$D$6,D32, $D$7)) -> - | D32: =IF(B32="","-",$D$4/12*H31) -> - | E32: =IF(B32="","-",SUM($D$18:D32)) -> - | F32: =IF(B32="","-",C32-D32) -> - | G32: =IF(B32="","-",SUM($F$18:F32)) -> - | H32: =IF(B32="","-",H31-F32) -> -
B33: =IF(B32>=$D$5*12,"",B32+1) | C33: =IF(B33="","-",IF(B33<=$D$6,D33, $D$7)) -> - | D33: =IF(B33="","-",$D$4/12*H32) -> - | E33: =IF(B33="","-",SUM($D$18:D33)) -> - | F33: =IF(B33="","-",C33-D33) -> - | G33: =IF(B33="","-",SUM($F$18:F33)) -> - | H33: =IF(B33="","-",H32-F33) -> -
B34: =IF(B33>=$D$5*12,"",B33+1) | C34: =IF(B34="","-",IF(B34<=$D$6,D34, $D$7)) -> - | D34: =IF(B34="","-",$D$4/12*H33) -> - | E34: =IF(B34="","-",SUM($D$18:D34)) -> - | F34: =IF(B34="","-",C34-D34) -> - | G34: =IF(B34="","-",SUM($F$18:F34)) -> - | H34: =IF(B34="","-",H33-F34) -> -
B35: =IF(B34>=$D$5*12,"",B34+1) | C35: =IF(B35="","-",IF(B35<=$D$6,D35, $D$7)) -> - | D35: =IF(B35="","-",$D$4/12*H34) -> - | E35: =IF(B35="","-",SUM($D$18:D35)) -> - | F35: =IF(B35="","-",C35-D35) -> - | G35: =IF(B35="","-",SUM($F$18:F35)) -> - | H35: =IF(B35="","-",H34-F35) -> -
B36: =IF(B35>=$D$5*12,"",B35+1) | C36: =IF(B36="","-",IF(B36<=$D$6,D36, $D$7)) -> - | D36: =IF(B36="","-",$D$4/12*H35) -> - | E36: =IF(B36="","-",SUM($D$18:D36)) -> - | F36: =IF(B36="","-",C36-D36) -> - | G36: =IF(B36="","-",SUM($F$18:F36)) -> - | H36: =IF(B36="","-",H35-F36) -> -
B37: =IF(B36>=$D$5*12,"",B36+1) | C37: =IF(B37="","-",IF(B37<=$D$6,D37, $D$7)) -> - | D37: =IF(B37="","-",$D$4/12*H36) -> - | E37: =IF(B37="","-",SUM($D$18:D37)) -> - | F37: =IF(B37="","-",C37-D37) -> - | G37: =IF(B37="","-",SUM($F$18:F37)) -> - | H37: =IF(B37="","-",H36-F37) -> -
B38: =IF(B37>=$D$5*12,"",B37+1) | C38: =IF(B38="","-",IF(B38<=$D$6,D38, $D$7)) -> - | D38: =IF(B38="","-",$D$4/12*H37) -> - | E38: =IF(B38="","-",SUM($D$18:D38)) -> - | F38: =IF(B38="","-",C38-D38) -> - | G38: =IF(B38="","-",SUM($F$18:F38)) -> - | H38: =IF(B38="","-",H37-F38) -> -
B39: =IF(B38>=$D$5*12,"",B38+1) | C39: =IF(B39="","-",IF(B39<=$D$6,D39, $D$7)) -> - | D39: =IF(B39="","-",$D$4/12*H38) -> - | E39: =IF(B39="","-",SUM($D$18:D39)) -> - | F39: =IF(B39="","-",C39-D39) -> - | G39: =IF(B39="","-",SUM($F$18:F39)) -> - | H39: =IF(B39="","-",H38-F39) -> -
B40: =IF(B39>=$D$5*12,"",B39+1) | C40: =IF(B40="","-",IF(B40<=$D$6,D40, $D$7)) -> - | D40: =IF(B40="","-",$D$4/12*H39) -> - | E40: =IF(B40="","-",SUM($D$18:D40)) -> - | F40: =IF(B40="","-",C40-D40) -> - | G40: =IF(B40="","-",SUM($F$18:F40)) -> - | H40: =IF(B40="","-",H39-F40) -> -
B41: =IF(B40>=$D$5*12,"",B40+1) | C41: =IF(B41="","-",IF(B41<=$D$6,D41, $D$7)) -> - | D41: =IF(B41="","-",$D$4/12*H40) -> - | E41: =IF(B41="","-",SUM($D$18:D41)) -> - | F41: =IF(B41="","-",C41-D41) -> - | G41: =IF(B41="","-",SUM($F$18:F41)) -> - | H41: =IF(B41="","-",H40-F41) -> -
... B257: =IF(B256>=$D$5*12,"",B256+1) | C257: =IF(B257="","-",IF(B257<=$D$6,D257, $D$7)) -> - | D257: =IF(B257="","-",$D$4/12*H256) -> - | E257: =IF(B257="","-",SUM($D$18:D257)) -> - | F257: =IF(B257="","-",C257-D257) -> - | G257: =IF(B257="","-",SUM($F$18:F257)) -> - | H257: =IF(B257="","-",H256-F257) -> -
B258: =IF(B257>=$D$5*12,"",B257+1) | C258: =IF(B258="","-",$D$7) -> - | D258: =IF(B258="","-",$D$4/12*H257) -> - | E258: =IF(B258="","-",SUM($D$18:D258)) -> - | F258: =IF(B258="","-",C258-D258) -> - | G258: =IF(B258="","-",SUM($F$18:F258)) -> - | H258: =IF(B258="","-",H257-F258) -> -
B259: =IF(B258>=$D$5*12,"",B258+1) | C259: =IF(B259="","-",$D$7) -> - | D259: =IF(B259="","-",$D$4/12*H258) -> - | E259: =IF(B259="","-",SUM($D$18:D259)) -> - | F259: =IF(B259="","-",C259-D259) -> - | G259: =IF(B259="","-",SUM($F$18:F259)) -> - | H259: =IF(B259="","-",H258-F259) -> -
B260: =IF(B259>=$D$5*12,"",B259+1) | C260: =IF(B260="","-",$D$7) -> - | D260: =IF(B260="","-",$D$4/12*H259) -> - | E260: =IF(B260="","-",SUM($D$18:D260)) -> - | F260: =IF(B260="","-",C260-D260) -> - | G260: =IF(B260="","-",SUM($F$18:F260)) -> - | H260: =IF(B260="","-",H259-F260) -> -
B261: =IF(B260>=$D$5*12,"",B260+1) | C261: =IF(B261="","-",$D$7) -> - | D261: =IF(B261="","-",$D$4/12*H260) -> - | E261: =IF(B261="","-",SUM($D$18:D261)) -> - | F261: =IF(B261="","-",C261-D261) -> - | G261: =IF(B261="","-",SUM($F$18:F261)) -> - | H261: =IF(B261="","-",H260-F261) -> -
B262: =IF(B261>=$D$5*12,"",B261+1) | C262: =IF(B262="","-",$D$7) -> - | D262: =IF(B262="","-",$D$4/12*H261) -> - | E262: =IF(B262="","-",SUM($D$18:D262)) -> - | F262: =IF(B262="","-",C262-D262) -> - | G262: =IF(B262="","-",SUM($F$18:F262)) -> - | H262: =IF(B262="","-",H261-F262) -> -
B263: =IF(B262>=$D$5*12,"",B262+1) | C263: =IF(B263="","-",$D$7) -> - | D263: =IF(B263="","-",$D$4/12*H262) -> - | E263: =IF(B263="","-",SUM($D$18:D263)) -> - | F263: =IF(B263="","-",C263-D263) -> - | G263: =IF(B263="","-",SUM($F$18:F263)) -> - | H263: =IF(B263="","-",H262-F263) -> -
B264: =IF(B263>=$D$5*12,"",B263+1) | C264: =IF(B264="","-",$D$7) -> - | D264: =IF(B264="","-",$D$4/12*H263) -> - | E264: =IF(B264="","-",SUM($D$18:D264)) -> - | F264: =IF(B264="","-",C264-D264) -> - | G264: =IF(B264="","-",SUM($F$18:F264)) -> - | H264: =IF(B264="","-",H263-F264) -> -
B265: =IF(B264>=$D$5*12,"",B264+1) | C265: =IF(B265="","-",$D$7) -> - | D265: =IF(B265="","-",$D$4/12*H264) -> - | E265: =IF(B265="","-",SUM($D$18:D265)) -> - | F265: =IF(B265="","-",C265-D265) -> - | G265: =IF(B265="","-",SUM($F$18:F265)) -> - | H265: =IF(B265="","-",H264-F265) -> -
B266: =IF(B265>=$D$5*12,"",B265+1) | C266: =IF(B266="","-",$D$7) -> - | D266: =IF(B266="","-",$D$4/12*H265) -> - | E266: =IF(B266="","-",SUM($D$18:D266)) -> - | F266: =IF(B266="","-",C266-D266) -> - | G266: =IF(B266="","-",SUM($F$18:F266)) -> - | H266: =IF(B266="","-",H265-F266) -> -
B267: =IF(B266>=$D$5*12,"",B266+1) | C267: =IF(B267="","-",$D$7) -> - | D267: =IF(B267="","-",$D$4/12*H266) -> - | E267: =IF(B267="","-",SUM($D$18:D267)) -> - | F267: =IF(B267="","-",C267-D267) -> - | G267: =IF(B267="","-",SUM($F$18:F267)) -> - | H267: =IF(B267="","-",H266-F267) -> -
B268: =IF(B267>=$D$5*12,"",B267+1) | C268: =IF(B268="","-",$D$7) -> - | D268: =IF(B268="","-",$D$4/12*H267) -> - | E268: =IF(B268="","-",SUM($D$18:D268)) -> - | F268: =IF(B268="","-",C268-D268) -> - | G268: =IF(B268="","-",SUM($F$18:F268)) -> - | H268: =IF(B268="","-",H267-F268) -> -
B269: =IF(B268>=$D$5*12,"",B268+1) | C269: =IF(B269="","-",$D$7) -> - | D269: =IF(B269="","-",$D$4/12*H268) -> - | E269: =IF(B269="","-",SUM($D$18:D269)) -> - | F269: =IF(B269="","-",C269-D269) -> - | G269: =IF(B269="","-",SUM($F$18:F269)) -> - | H269: =IF(B269="","-",H268-F269) -> -
... B378: =IF(B377>=$D$5*12,"",B377+1) | C378: =IF(B378="","-",$D$7) -> - | D378: =IF(B378="","-",$D$4/12*H377) -> - | E378: =IF(B378="","-",SUM($D$18:D378)) -> - | F378: =IF(B378="","-",C378-D378) -> - | G378: =IF(B378="","-",SUM($F$18:F378)) -> - | H378: =IF(B378="","-",H377-F378) -> -
B381: =copyright -> Copyright © 2026 Michael Blank.
B382: The information herein is not guaranteed but believed to be accurate.

Sheet 1st Mortgage Re-Fi
A1: Simple Interest Loan Amortization Table - 1st Mortgage After Refi
B3: Loan Amount | D3: ='Exit Strategy'!D15 -> 0 | E3: Use drop down menu to | H3: Option 1
B4: Interest Rate | D4: ='Exit Strategy'!D12 -> 0 | E4: select option for amortization schedule | H4: Amortlization schedule based on full number of years, including any interest-only period
B5: Number of Years | D5: ='Exit Strategy'!D13 -> 25 | H5: Ex. 25 year tern, 2 years of I/O = 25-year amortization schedule
B6: Interest-Only (Months) | D6: ='Exit Strategy'!D14 -> 0 | F6: Option 1
B7: Monthly Payment | D7: =IF($F$6="Option 1",PMT(D4/12,(D5*12),-D3),PMT(D4/12,(D5*12)-D6,-D3)) -> 0 | H7: Option 2
B8: Total Interest Paid | D8: =SUM(D17:D378) -> 0 | H8: Amortlization schedule based on number of years after any interest-only period
B9: Annual Debt Service | D9: =SUM(C18:C29) -> 0 | H9: Ex. 25 year term, 2 years of I/O = 23-year amortization schedule
B11: End of Year | C11: 1 | D11: =C11+1 -> 2 | E11: =D11+1 -> 3 | F11: =E11+1 -> 4 | G11: =F11+1 -> 5 | H11: =G11+1 -> 6 | I11: =H11+1 -> 7 | J11: =I11+1 -> 8 | K11: =J11+1 -> 9 | L11: =K11+1 -> 10
B12: Principal | C12: =OFFSET($G$17,12*C11,0) -> 0 | D12: =OFFSET($G$17,12*D11,0)-C12 -> 0 | E12: =OFFSET($G$17,12*E11,0)-SUM(C12:D12) -> 0 | F12: =OFFSET($G$17,12*F11,0)-SUM(C12:E12) -> 0 | G12: =OFFSET($G$17,12*G11,0)-SUM(C12:F12) -> 0 | H12: =OFFSET($G$17,12*H11,0)-SUM(C12:G12) -> 0 | I12: =OFFSET($G$17,12*I11,0)-SUM(C12:H12) -> 0 | J12: =OFFSET($G$17,12*J11,0)-SUM(C12:I12) -> 0 | K12: =OFFSET($G$17,12*K11,0)-SUM(C12:J12) -> 0 | L12: =OFFSET($G$17,12*L11,0)-SUM(C12:K12) -> 0
B13: Interest | C13: =OFFSET($E$17,12*C11,0) -> 0 | D13: =OFFSET($E$17,12*D11,0)-C13 -> 0 | E13: =OFFSET($E$17,12*E11,0)-SUM(C13:D13) -> 0 | F13: =OFFSET($E$17,12*F11,0)-SUM(C13:E13) -> 0 | G13: =OFFSET($E$17,12*G11,0)-SUM(C13:F13) -> 0 | H13: =OFFSET($E$17,12*H11,0)-SUM(C13:G13) -> 0 | I13: =OFFSET($E$17,12*I11,0)-SUM(C13:H13) -> 0 | J13: =OFFSET($E$17,12*J11,0)-SUM(C13:I13) -> 0 | K13: =OFFSET($E$17,12*K11,0)-SUM(C13:J13) -> 0 | L13: =OFFSET($E$17,12*L11,0)-SUM(C13:K13) -> 0
B14: Balance | C14: =OFFSET($H$17,C11*12,0) -> 0 | D14: =OFFSET($H$17,D11*12,0) -> 0 | E14: =OFFSET($H$17,E11*12,0) -> 0 | F14: =OFFSET($H$17,F11*12,0) -> 0 | G14: =OFFSET($H$17,G11*12,0) -> 0 | H14: =OFFSET($H$17,H11*12,0) -> 0 | I14: =OFFSET($H$17,I11*12,0) -> 0 | J14: =OFFSET($H$17,J11*12,0) -> 0 | ... L14: =OFFSET($H$17,L11*12,0) -> 0
B16: Month | C16: Payment Amount | D16: Interest | E16: Cumulative Interest | F16: Principal | G16: Principal Paid | H16: Balance
H17: =D3 -> 0
B18: =IF(B17>=$D$5*12+$D$6,"",B17+1) -> 1 | C18: =IF(B18="","-",IF(B18<=$D$6,D18, $D$7)) -> 0 | D18: =IF(B18="","-",$D$4/12*H17) -> 0 | E18: =IF(B18="","-",SUM($D$18:D18)) -> 0 | F18: =IF(B18="","-",C18-D18) -> 0 | G18: =IF(B18="","-",SUM($F$18:F18)) -> 0 | H18: =IF(B18="","-",H17-F18) -> 0
B19: =IF(B18>=$D$5*12+$D$6,"",B18+1) -> 2 | C19: =IF(B19="","-",IF(B19<=$D$6,D19, $D$7)) -> 0 | D19: =IF(B19="","-",$D$4/12*H18) -> 0 | E19: =IF(B19="","-",SUM($D$18:D19)) -> 0 | F19: =IF(B19="","-",C19-D19) -> 0 | G19: =IF(B19="","-",SUM($F$18:F19)) -> 0 | H19: =IF(B19="","-",H18-F19) -> 0
B20: =IF(B19>=$D$5*12+$D$6,"",B19+1) -> 3 | C20: =IF(B20="","-",IF(B20<=$D$6,D20, $D$7)) -> 0 | D20: =IF(B20="","-",$D$4/12*H19) -> 0 | E20: =IF(B20="","-",SUM($D$18:D20)) -> 0 | F20: =IF(B20="","-",C20-D20) -> 0 | G20: =IF(B20="","-",SUM($F$18:F20)) -> 0 | H20: =IF(B20="","-",H19-F20) -> 0
B21: =IF(B20>=$D$5*12+$D$6,"",B20+1) -> 4 | C21: =IF(B21="","-",IF(B21<=$D$6,D21, $D$7)) -> 0 | D21: =IF(B21="","-",$D$4/12*H20) -> 0 | E21: =IF(B21="","-",SUM($D$18:D21)) -> 0 | F21: =IF(B21="","-",C21-D21) -> 0 | G21: =IF(B21="","-",SUM($F$18:F21)) -> 0 | H21: =IF(B21="","-",H20-F21) -> 0
B22: =IF(B21>=$D$5*12+$D$6,"",B21+1) -> 5 | C22: =IF(B22="","-",IF(B22<=$D$6,D22, $D$7)) -> 0 | D22: =IF(B22="","-",$D$4/12*H21) -> 0 | E22: =IF(B22="","-",SUM($D$18:D22)) -> 0 | F22: =IF(B22="","-",C22-D22) -> 0 | G22: =IF(B22="","-",SUM($F$18:F22)) -> 0 | H22: =IF(B22="","-",H21-F22) -> 0
B23: =IF(B22>=$D$5*12+$D$6,"",B22+1) -> 6 | C23: =IF(B23="","-",IF(B23<=$D$6,D23, $D$7)) -> 0 | D23: =IF(B23="","-",$D$4/12*H22) -> 0 | E23: =IF(B23="","-",SUM($D$18:D23)) -> 0 | F23: =IF(B23="","-",C23-D23) -> 0 | G23: =IF(B23="","-",SUM($F$18:F23)) -> 0 | H23: =IF(B23="","-",H22-F23) -> 0
B24: =IF(B23>=$D$5*12+$D$6,"",B23+1) -> 7 | C24: =IF(B24="","-",IF(B24<=$D$6,D24, $D$7)) -> 0 | D24: =IF(B24="","-",$D$4/12*H23) -> 0 | E24: =IF(B24="","-",SUM($D$18:D24)) -> 0 | F24: =IF(B24="","-",C24-D24) -> 0 | G24: =IF(B24="","-",SUM($F$18:F24)) -> 0 | H24: =IF(B24="","-",H23-F24) -> 0
B25: =IF(B24>=$D$5*12+$D$6,"",B24+1) -> 8 | C25: =IF(B25="","-",IF(B25<=$D$6,D25, $D$7)) -> 0 | D25: =IF(B25="","-",$D$4/12*H24) -> 0 | E25: =IF(B25="","-",SUM($D$18:D25)) -> 0 | F25: =IF(B25="","-",C25-D25) -> 0 | G25: =IF(B25="","-",SUM($F$18:F25)) -> 0 | H25: =IF(B25="","-",H24-F25) -> 0
B26: =IF(B25>=$D$5*12+$D$6,"",B25+1) -> 9 | C26: =IF(B26="","-",IF(B26<=$D$6,D26, $D$7)) -> 0 | D26: =IF(B26="","-",$D$4/12*H25) -> 0 | E26: =IF(B26="","-",SUM($D$18:D26)) -> 0 | F26: =IF(B26="","-",C26-D26) -> 0 | G26: =IF(B26="","-",SUM($F$18:F26)) -> 0 | H26: =IF(B26="","-",H25-F26) -> 0
B27: =IF(B26>=$D$5*12+$D$6,"",B26+1) -> 10 | C27: =IF(B27="","-",IF(B27<=$D$6,D27, $D$7)) -> 0 | D27: =IF(B27="","-",$D$4/12*H26) -> 0 | E27: =IF(B27="","-",SUM($D$18:D27)) -> 0 | F27: =IF(B27="","-",C27-D27) -> 0 | G27: =IF(B27="","-",SUM($F$18:F27)) -> 0 | H27: =IF(B27="","-",H26-F27) -> 0
B28: =IF(B27>=$D$5*12+$D$6,"",B27+1) -> 11 | C28: =IF(B28="","-",IF(B28<=$D$6,D28, $D$7)) -> 0 | D28: =IF(B28="","-",$D$4/12*H27) -> 0 | E28: =IF(B28="","-",SUM($D$18:D28)) -> 0 | F28: =IF(B28="","-",C28-D28) -> 0 | G28: =IF(B28="","-",SUM($F$18:F28)) -> 0 | H28: =IF(B28="","-",H27-F28) -> 0
B29: =IF(B28>=$D$5*12+$D$6,"",B28+1) -> 12 | C29: =IF(B29="","-",IF(B29<=$D$6,D29, $D$7)) -> 0 | D29: =IF(B29="","-",$D$4/12*H28) -> 0 | E29: =IF(B29="","-",SUM($D$18:D29)) -> 0 | F29: =IF(B29="","-",C29-D29) -> 0 | G29: =IF(B29="","-",SUM($F$18:F29)) -> 0 | H29: =IF(B29="","-",H28-F29) -> 0
B30: =IF(B29>=$D$5*12,"",B29+1) -> 13 | C30: =IF(B30="","-",IF(B30<=$D$6,D30, $D$7)) -> 0 | D30: =IF(B30="","-",$D$4/12*H29) -> 0 | E30: =IF(B30="","-",SUM($D$18:D30)) -> 0 | F30: =IF(B30="","-",C30-D30) -> 0 | G30: =IF(B30="","-",SUM($F$18:F30)) -> 0 | H30: =IF(B30="","-",H29-F30) -> 0
B31: =IF(B30>=$D$5*12,"",B30+1) -> 14 | C31: =IF(B31="","-",IF(B31<=$D$6,D31, $D$7)) -> 0 | D31: =IF(B31="","-",$D$4/12*H30) -> 0 | E31: =IF(B31="","-",SUM($D$18:D31)) -> 0 | F31: =IF(B31="","-",C31-D31) -> 0 | G31: =IF(B31="","-",SUM($F$18:F31)) -> 0 | H31: =IF(B31="","-",H30-F31) -> 0
B32: =IF(B31>=$D$5*12,"",B31+1) -> 15 | C32: =IF(B32="","-",IF(B32<=$D$6,D32, $D$7)) -> 0 | D32: =IF(B32="","-",$D$4/12*H31) -> 0 | E32: =IF(B32="","-",SUM($D$18:D32)) -> 0 | F32: =IF(B32="","-",C32-D32) -> 0 | G32: =IF(B32="","-",SUM($F$18:F32)) -> 0 | H32: =IF(B32="","-",H31-F32) -> 0
B33: =IF(B32>=$D$5*12,"",B32+1) -> 16 | C33: =IF(B33="","-",IF(B33<=$D$6,D33, $D$7)) -> 0 | D33: =IF(B33="","-",$D$4/12*H32) -> 0 | E33: =IF(B33="","-",SUM($D$18:D33)) -> 0 | F33: =IF(B33="","-",C33-D33) -> 0 | G33: =IF(B33="","-",SUM($F$18:F33)) -> 0 | H33: =IF(B33="","-",H32-F33) -> 0
B34: =IF(B33>=$D$5*12,"",B33+1) -> 17 | C34: =IF(B34="","-",IF(B34<=$D$6,D34, $D$7)) -> 0 | D34: =IF(B34="","-",$D$4/12*H33) -> 0 | E34: =IF(B34="","-",SUM($D$18:D34)) -> 0 | F34: =IF(B34="","-",C34-D34) -> 0 | G34: =IF(B34="","-",SUM($F$18:F34)) -> 0 | H34: =IF(B34="","-",H33-F34) -> 0
B35: =IF(B34>=$D$5*12,"",B34+1) -> 18 | C35: =IF(B35="","-",IF(B35<=$D$6,D35, $D$7)) -> 0 | D35: =IF(B35="","-",$D$4/12*H34) -> 0 | E35: =IF(B35="","-",SUM($D$18:D35)) -> 0 | F35: =IF(B35="","-",C35-D35) -> 0 | G35: =IF(B35="","-",SUM($F$18:F35)) -> 0 | H35: =IF(B35="","-",H34-F35) -> 0
B36: =IF(B35>=$D$5*12,"",B35+1) -> 19 | C36: =IF(B36="","-",IF(B36<=$D$6,D36, $D$7)) -> 0 | D36: =IF(B36="","-",$D$4/12*H35) -> 0 | E36: =IF(B36="","-",SUM($D$18:D36)) -> 0 | F36: =IF(B36="","-",C36-D36) -> 0 | G36: =IF(B36="","-",SUM($F$18:F36)) -> 0 | H36: =IF(B36="","-",H35-F36) -> 0
B37: =IF(B36>=$D$5*12,"",B36+1) -> 20 | C37: =IF(B37="","-",IF(B37<=$D$6,D37, $D$7)) -> 0 | D37: =IF(B37="","-",$D$4/12*H36) -> 0 | E37: =IF(B37="","-",SUM($D$18:D37)) -> 0 | F37: =IF(B37="","-",C37-D37) -> 0 | G37: =IF(B37="","-",SUM($F$18:F37)) -> 0 | H37: =IF(B37="","-",H36-F37) -> 0
B38: =IF(B37>=$D$5*12,"",B37+1) -> 21 | C38: =IF(B38="","-",IF(B38<=$D$6,D38, $D$7)) -> 0 | D38: =IF(B38="","-",$D$4/12*H37) -> 0 | E38: =IF(B38="","-",SUM($D$18:D38)) -> 0 | F38: =IF(B38="","-",C38-D38) -> 0 | G38: =IF(B38="","-",SUM($F$18:F38)) -> 0 | H38: =IF(B38="","-",H37-F38) -> 0
B39: =IF(B38>=$D$5*12,"",B38+1) -> 22 | C39: =IF(B39="","-",IF(B39<=$D$6,D39, $D$7)) -> 0 | D39: =IF(B39="","-",$D$4/12*H38) -> 0 | E39: =IF(B39="","-",SUM($D$18:D39)) -> 0 | F39: =IF(B39="","-",C39-D39) -> 0 | G39: =IF(B39="","-",SUM($F$18:F39)) -> 0 | H39: =IF(B39="","-",H38-F39) -> 0
B40: =IF(B39>=$D$5*12,"",B39+1) -> 23 | C40: =IF(B40="","-",IF(B40<=$D$6,D40, $D$7)) -> 0 | D40: =IF(B40="","-",$D$4/12*H39) -> 0 | E40: =IF(B40="","-",SUM($D$18:D40)) -> 0 | F40: =IF(B40="","-",C40-D40) -> 0 | G40: =IF(B40="","-",SUM($F$18:F40)) -> 0 | H40: =IF(B40="","-",H39-F40) -> 0
B41: =IF(B40>=$D$5*12,"",B40+1) -> 24 | C41: =IF(B41="","-",IF(B41<=$D$6,D41, $D$7)) -> 0 | D41: =IF(B41="","-",$D$4/12*H40) -> 0 | E41: =IF(B41="","-",SUM($D$18:D41)) -> 0 | F41: =IF(B41="","-",C41-D41) -> 0 | G41: =IF(B41="","-",SUM($F$18:F41)) -> 0 | H41: =IF(B41="","-",H40-F41) -> 0
... B257: =IF(B256>=$D$5*12,"",B256+1) -> 240 | C257: =IF(B257="","-",IF(B257<=$D$6,D257, $D$7)) -> 0 | D257: =IF(B257="","-",$D$4/12*H256) -> 0 | E257: =IF(B257="","-",SUM($D$18:D257)) -> 0 | F257: =IF(B257="","-",C257-D257) -> 0 | G257: =IF(B257="","-",SUM($F$18:F257)) -> 0 | H257: =IF(B257="","-",H256-F257) -> 0
B258: =IF(B257>=$D$5*12,"",B257+1) -> 241 | C258: =IF(B258="","-",$D$7) -> 0 | D258: =IF(B258="","-",$D$4/12*H257) -> 0 | E258: =IF(B258="","-",SUM($D$18:D258)) -> 0 | F258: =IF(B258="","-",C258-D258) -> 0 | G258: =IF(B258="","-",SUM($F$18:F258)) -> 0 | H258: =IF(B258="","-",H257-F258) -> 0
B259: =IF(B258>=$D$5*12,"",B258+1) -> 242 | C259: =IF(B259="","-",$D$7) -> 0 | D259: =IF(B259="","-",$D$4/12*H258) -> 0 | E259: =IF(B259="","-",SUM($D$18:D259)) -> 0 | F259: =IF(B259="","-",C259-D259) -> 0 | G259: =IF(B259="","-",SUM($F$18:F259)) -> 0 | H259: =IF(B259="","-",H258-F259) -> 0
B260: =IF(B259>=$D$5*12,"",B259+1) -> 243 | C260: =IF(B260="","-",$D$7) -> 0 | D260: =IF(B260="","-",$D$4/12*H259) -> 0 | E260: =IF(B260="","-",SUM($D$18:D260)) -> 0 | F260: =IF(B260="","-",C260-D260) -> 0 | G260: =IF(B260="","-",SUM($F$18:F260)) -> 0 | H260: =IF(B260="","-",H259-F260) -> 0
B261: =IF(B260>=$D$5*12,"",B260+1) -> 244 | C261: =IF(B261="","-",$D$7) -> 0 | D261: =IF(B261="","-",$D$4/12*H260) -> 0 | E261: =IF(B261="","-",SUM($D$18:D261)) -> 0 | F261: =IF(B261="","-",C261-D261) -> 0 | G261: =IF(B261="","-",SUM($F$18:F261)) -> 0 | H261: =IF(B261="","-",H260-F261) -> 0
B262: =IF(B261>=$D$5*12,"",B261+1) -> 245 | C262: =IF(B262="","-",$D$7) -> 0 | D262: =IF(B262="","-",$D$4/12*H261) -> 0 | E262: =IF(B262="","-",SUM($D$18:D262)) -> 0 | F262: =IF(B262="","-",C262-D262) -> 0 | G262: =IF(B262="","-",SUM($F$18:F262)) -> 0 | H262: =IF(B262="","-",H261-F262) -> 0
B263: =IF(B262>=$D$5*12,"",B262+1) -> 246 | C263: =IF(B263="","-",$D$7) -> 0 | D263: =IF(B263="","-",$D$4/12*H262) -> 0 | E263: =IF(B263="","-",SUM($D$18:D263)) -> 0 | F263: =IF(B263="","-",C263-D263) -> 0 | G263: =IF(B263="","-",SUM($F$18:F263)) -> 0 | H263: =IF(B263="","-",H262-F263) -> 0
B264: =IF(B263>=$D$5*12,"",B263+1) -> 247 | C264: =IF(B264="","-",$D$7) -> 0 | D264: =IF(B264="","-",$D$4/12*H263) -> 0 | E264: =IF(B264="","-",SUM($D$18:D264)) -> 0 | F264: =IF(B264="","-",C264-D264) -> 0 | G264: =IF(B264="","-",SUM($F$18:F264)) -> 0 | H264: =IF(B264="","-",H263-F264) -> 0
B265: =IF(B264>=$D$5*12,"",B264+1) -> 248 | C265: =IF(B265="","-",$D$7) -> 0 | D265: =IF(B265="","-",$D$4/12*H264) -> 0 | E265: =IF(B265="","-",SUM($D$18:D265)) -> 0 | F265: =IF(B265="","-",C265-D265) -> 0 | G265: =IF(B265="","-",SUM($F$18:F265)) -> 0 | H265: =IF(B265="","-",H264-F265) -> 0
B266: =IF(B265>=$D$5*12,"",B265+1) -> 249 | C266: =IF(B266="","-",$D$7) -> 0 | D266: =IF(B266="","-",$D$4/12*H265) -> 0 | E266: =IF(B266="","-",SUM($D$18:D266)) -> 0 | F266: =IF(B266="","-",C266-D266) -> 0 | G266: =IF(B266="","-",SUM($F$18:F266)) -> 0 | H266: =IF(B266="","-",H265-F266) -> 0
B267: =IF(B266>=$D$5*12,"",B266+1) -> 250 | C267: =IF(B267="","-",$D$7) -> 0 | D267: =IF(B267="","-",$D$4/12*H266) -> 0 | E267: =IF(B267="","-",SUM($D$18:D267)) -> 0 | F267: =IF(B267="","-",C267-D267) -> 0 | G267: =IF(B267="","-",SUM($F$18:F267)) -> 0 | H267: =IF(B267="","-",H266-F267) -> 0
B268: =IF(B267>=$D$5*12,"",B267+1) -> 251 | C268: =IF(B268="","-",$D$7) -> 0 | D268: =IF(B268="","-",$D$4/12*H267) -> 0 | E268: =IF(B268="","-",SUM($D$18:D268)) -> 0 | F268: =IF(B268="","-",C268-D268) -> 0 | G268: =IF(B268="","-",SUM($F$18:F268)) -> 0 | H268: =IF(B268="","-",H267-F268) -> 0
B269: =IF(B268>=$D$5*12,"",B268+1) -> 252 | C269: =IF(B269="","-",$D$7) -> 0 | D269: =IF(B269="","-",$D$4/12*H268) -> 0 | E269: =IF(B269="","-",SUM($D$18:D269)) -> 0 | F269: =IF(B269="","-",C269-D269) -> 0 | G269: =IF(B269="","-",SUM($F$18:F269)) -> 0 | H269: =IF(B269="","-",H268-F269) -> 0
... B378: =IF(B377>=$D$5*12,"",B377+1) | C378: =IF(B378="","-",$D$7) -> - | D378: =IF(B378="","-",$D$4/12*H377) -> - | E378: =IF(B378="","-",SUM($D$18:D378)) -> - | F378: =IF(B378="","-",C378-D378) -> - | G378: =IF(B378="","-",SUM($F$18:F378)) -> - | H378: =IF(B378="","-",H377-F378) -> -
B381: =copyright -> Copyright © 2026 Michael Blank.
B382: The information herein is not guaranteed but believed to be accurate.

Sheet Repairs
B1: Repairs
B3: Interior Improvements | C3: Cost | D3: # Units | E3: Total Expense | G3: Use the dropdown in cell C14 of the Scenarios tab to fill in the amount for Repairs calculated on this tab.
B4: Kitchen update | C4: 0 | D4: 0 | E4: =C4*D4 -> 0
B5: Flooring update | C5: 0 | D5: 0 | E5: =C5*D5 -> 0
B6: Bathroom vanity | C6: 0 | D6: 0 | E6: =C6*D6 -> 0
B7: Paint | C7: 0 | D7: 0 | E7: =C7*D7 -> 0
B8: Replace cabinets | C8: 0 | D8: 0 | E8: =C8*D8 -> 0
B9: Trim and sheetrock repair | C9: 0 | D9: 0 | E9: =C9*D9 -> 0
B10: Lighting fixtures | C10: 0 | D10: 0 | E10: =C10*D10 -> 0
B11: Accessories (blinds, pulls, outlets, door knobs etc.) | C11: 0 | D11: 0 | E11: =C11*D11 -> 0
B12: Other | C12: 0 | D12: 0 | E12: =C12*D12 -> 0
B13: Other | C13: 0 | D13: 0 | E13: =C13*D13 -> 0
B14: Other | C14: 0 | D14: 0 | E14: =C14*D14 -> 0
B15: Other | C15: 0 | D15: 0 | E15: =C15*D15 -> 0
B16: Other | C16: 0 | D16: 0 | E16: =C16*D16 -> 0
B17: Total Interior Unit Improvements | E17: =SUM(E4:E16) -> 0
B19: Exterior Improvements | C19: Cost | D19: # Units | E19: Total Expense
B20: Paint exterior | C20: 0 | D20: 0 | E20: =C20*D20 -> 0
B21: Replace Roofs | C21: 0 | D21: 0 | E21: =C21*D21 -> 0
B22: Landscaping | C22: 0 | D22: 0 | E22: =C22*D22 -> 0
B23: Lighting | C23: 0 | D23: 0 | E23: =C23*D23 -> 0
B24: Parking | C24: 0 | D24: 0 | E24: =C24*D24 -> 0
B25: Other | C25: 0 | D25: 0 | E25: =C25*D25 -> 0
B26: Other | C26: 0 | D26: 0 | E26: =C26*D26 -> 0
B27: Other | C27: 0 | D27: 0 | E27: =C27*D27 -> 0
B28: Other | C28: 0 | D28: 0 | E28: =C28*D28 -> 0
B29: Other | C29: 0 | D29: 0 | E29: =C29*D29 -> 0
B30: Total Exterior Improvements | E30: =SUM(E20:E29) -> 0
B32: Total Improvements
B33: Subtotal Renovation Expenses | E33: =E30+E17 -> 0
B34: Contingency Reserve | D34: 0.15 | E34: =E33*D34 -> 0
B35: Total Renovation Expense | E35: =SUM(E33:E34) -> 0
B38: =copyright -> Copyright © 2026 Michael Blank.
B39: The information herein is not guaranteed but believed to be accurate.

Sheet One Pager
B1: Investment Summary
B3: Deal Information
B4: Property Name | D4: [Enter Property Name] | H4: Purchase Price | L4: =Summary!D6 -> 0
B5: Location | D5: [Enter City, State] | H5: # Units | L5: =Summary!D4 -> 0
B6: Year Built | D6: 0 | H6: Price Per Unit | L6: =Summary!D7 -> 0
H7: Hold Period (Years) | L7: ='Exit Strategy'!D5 -> 5
B9: Returns
B10: LP (Member) Returns | H10: Key Indicators | K10: Year 1 | L10: Exit Yr
B11: Cash-on-Cash Return | F11: =IFERROR(Returns!N18,0) -> 0 | H11: NOI | K11: ='P&L'!D35 -> 0 | L11: ='Exit Strategy'!H8 -> 0
B12: IRR | F12: =IFERROR(Returns!N17,0) -> 0 | H12: Debt Service | K12: ='P&L'!D40 -> 0 | L12: =IFERROR(OFFSET('P&L'!D40,0,('Exit Strategy'!$D$5-1)*2),0) -> 0
B13: Equity Multiple | F13: =IFERROR(Returns!N19,0) -> 0 | H13: Cap Rate | K13: =Summary!D23 -> 0.07 | L13: ='Exit Strategy'!H9 -> 0.075
B14: Average Annual Return | F14: =IFERROR(Returns!N16,0) -> 0 | H14: DSCR | K14: ='P&L'!D62 -> 0 | L14: =IFERROR(OFFSET('P&L'!D62,0,('Exit Strategy'!$D$5-1)*2),0) -> 0
H15: Expense Ratio | K15: ='P&L'!E33 -> 0 | L15: =IFERROR(OFFSET('P&L'!E33,0,('Exit Strategy'!$D$5-1)*2),0) -> 0
B16: Project Returns | H16: Gross Rent Multiplier | K16: =IF('P&L'!D11=0,0,Summary!D6/'P&L'!D11) -> 0 | L16: =IFERROR(IF(OFFSET('P&L'!D11,0,('Exit Strategy'!$D$5-1)*2)=0,0,'Exit Strategy'!H12/OFFSET('P&L'!D11,0,('Exit Strategy'!$D$5-1)*2)),0) -> 0
B17: Cash-on-Cash Return | F17: =IFERROR(Returns!N88,0) -> 0 | H17: Cash-on-Cash Return | K17: =IFERROR(IF(Returns!C7="∞",0,Returns!C7),0) -> 0 | L17: =IFERROR(IF(OFFSET(Returns!C7,0,'Exit Strategy'!$D$5-1)="∞",0,OFFSET(Returns!C7,0,'Exit Strategy'!$D$5-1)),0) -> 0
B18: IRR | F18: =IFERROR(Returns!N87,0) -> 0 | H18: Breakeven Occupancy | K18: =IF('P&L'!D11=0,0,('P&L'!D33+'P&L'!D40)/'P&L'!D11) -> 0 | L18: =IFERROR(IF(OFFSET('P&L'!D11,0,('Exit Strategy'!$D$5-1)*2)=0,0,(OFFSET('P&L'!D33,0,('Exit Strategy'!$D$5-1)*2)+OFFSET('P&L'!D40,0,('Exit Strategy'!$D$5-1)*2))/OFFSET('P&L'!D11,0,('Exit Strategy'!$D$5-1)*2)),0) -> 0
B19: Equity Multiple | F19: =IFERROR(Returns!N89,0) -> 0
B20: Average Annual Return | F20: =IFERROR(Returns!N86,0) -> 0
B22: Purchase
B23: Purchase Information | H23: Renovation / Value-Add Budget
B24: Down Payment | F24: =Summary!D9 -> 0 | H24: Total Interior Improvements | L24: =IF(L27=0,0,Repairs!E17) -> 0
B25: Total Capital Required | F25: =Summary!D22 -> 0 | H25: Total Exterior Improvements | L25: =IF(L27=0,0,Repairs!E30) -> 0
H26: Contingency Reserve | L26: =IF(L27=0,0,Repairs!E34) -> 0
B27: Debt | D27: 1st Mort | E27: 2nd Mort | F27: Refinance | H27: Total Renovation Budget | L27: =Summary!D20 -> 0
B28: Loan Amount | D28: =Summary!D10 -> 0 | E28: =Summary!D14 -> 0 | F28: ='Exit Strategy'!D15 -> 0
B29: LTV | D29: =IF(Summary!D6=0,0,Summary!D10/Summary!D6) -> 0 | E29: =IF(Summary!D6=0,0,Summary!D14/Summary!D6) -> 0 | F29: ='Exit Strategy'!D11 -> 0.65 | H29: Exit Strategy
B30: Interest Rate | D30: =Summary!D11 -> 0.05 | E30: =Summary!D15 -> 0 | F30: ='Exit Strategy'!D12 -> 0 | H30: Year of Sale | L30: ='Exit Strategy'!H7 -> 5
B31: Term / Amort. (Yrs) | D31: =Summary!D12 -> 30 | E31: =Summary!D16 -> 0 | F31: ='Exit Strategy'!D13 -> 25 | H31: NOI at Sale | L31: ='Exit Strategy'!H8 -> 0
B32: I/O (mths) | D32: =Summary!D13 -> 0 | E32: =Summary!D17 -> 0 | F32: ='Exit Strategy'!D14 -> 0 | H32: Exit Cap Rate | L32: ='Exit Strategy'!H9 -> 0.075
H33: Projected Sale Price | L33: ='Exit Strategy'!H12 -> 0
H34: Net Proceeds from Sale | L34: ='Exit Strategy'!H20 -> 0
B36: Sources/Uses of Capital
B37: Uses | F37: % | H37: Sources | L37: %
B38: Purchase Price | E38: =Summary!D6 -> 0 | F38: =IF($E$43=0,0,E38/$E$43) -> 0 | H38: 1st Mortgage | K38: =Summary!D10 -> 0 | L38: =IF($K$41=0,0,K38/$K$41) -> 0
B39: Closing Costs | E39: =Summary!D18 -> 0 | F39: =IF($E$43=0,0,E39/$E$43) -> 0 | H39: 2nd Mortgage | K39: =Summary!D14 -> 0 | L39: =IF($K$41=0,0,K39/$K$41) -> 0
B40: Acquisition Fee | E40: =Summary!D19 -> 0 | F40: =IF($E$43=0,0,E40/$E$43) -> 0 | H40: Member Equity | K40: =Summary!D22 -> 0 | L40: =IF($K$41=0,0,K40/$K$41) -> 0
B41: Repairs | E41: =Summary!D20 -> 0 | F41: =IF($E$43=0,0,E41/$E$43) -> 0 | H41: Total Sources | K41: =SUM(K38:K40) -> 0 | L41: =IF($K$41=0,0,K41/$K$41) -> 0
B42: Operating Reserves | E42: =Summary!D21 -> 0 | F42: =IF($E$43=0,0,E42/$E$43) -> 0
B43: Total Uses | E43: =SUM(E38:E42) -> 0 | F43: =IF($E$43=0,0,E43/$E$43) -> 0
B46: =copyright -> Copyright © 2026 Michael Blank.
B47: The information herein is not guaranteed but believed to be accurate.

Sheet 2-Minute Analysis
B2: The 2-Minute Analysis
B4: Gross Potential Annual Income | C4: 0 | E4: Use info from the marketing package.
B5: - Economic & Physical Vacancy | C5: 0.1 | E5: Rule of thumb, consider carefully before changing.
B6: = Net Annual Income | C6: =C4*(1-C5) -> 0
B8: - Annual Expense Rate | C8: 0.5 | E8: Rule of thumb, carefully consider before changing.
B10: = Net Operating Income | C10: =C6*(1-C8) -> 0
B12: Market Cap Rate | C12: 0.07 | E12: Use cap rate from the marketing package or ask the broker.
B14: Valuation | C14: =C10/C12 -> 0
B16: =copyright -> Copyright © 2026 Michael Blank.
B17: The information herein is not guaranteed but believed to be accurate.

Sheet Legal Notices
B1: Legal Notices
B2: Copyright Notices and Limited Use Policy Copyright © 2014-2026. ALL RIGHTS RESERVED. Version 2.9.4. The spreadsheet is for your personal use only. You may use and access this spreadsheet on multiple devices but you may not share it with other users. You may customize this spreadsheet to suit your needs and re-use in other publications as long as you add "Reprinted with permission from Michael Blank, www.TheMichaelBlank.com, Copyright 2025". It may not be sold, distributed, or placed on a public server (i.e. the internet), without the written consent of the Author (Michael Blank). Requests for permission or further information should be addressed to: Michael Blank, 44050 Ashburn Shopping Plaza Suite 195-108, Ashburn, VA 20147, (844) 844-0678, www.TheMichaelBlank.com
B3: No Warranties THE SOFTWARE AND ANY RELATED DOCUMENTATION ARE PROVIDED TO YOU "AS IS." THE AUTHOR MAKES NO WARRANTIES, EXPRESS OR IMPLIED, AND EXPRESSLY DISCLAIMS ALL REPRESENTATIONS, ORAL OR WRITTEN, TERMS, CONDITIONS, AND WARRANTIES, INCLUDING BUT NOT LIMITED TO, IMPLIED WARRANTIES OF MERCHANTABILITY, FITNESS FOR A PARTICULAR PURPOSE, AND NONINFRINGEMENT. WITHOUT LIMITING THE ABOVE YOU ACCEPT THAT THE SOFTWARE MAY NOT MEET YOUR REQUIREMENTS, OPERATE ERROR FREE, OR IDENTIFY ANY OR ALL ERRORS OR PROBLEMS, OR DO SO ACCURATELY. This Agreement does not affect any statutory rights you may have as a consumer. Some states do not allow the limitation or exclusion of liability for incidental or consequential damages, so the above limitation may not apply to you.
B4: Limitation of Liability IN NO EVENT SHALL THE AUTHOR BE LIABLE TO YOU, FOR ANY DAMAGES, INCLUDING ANY LOST PROFITS, LOST SAVINGS, OR ANY OTHER DIRECT, INDIRECT, SPECIAL, INCIDENTAL, OR CONSEQUENTIAL DAMAGES ARISING FROM THE USE OR THE INABILITY TO USE THE SOFTWARE (EVEN IF WE OR AN AUTHORIZED DEALER OR DISTRIBUTOR HAS BEEN ADVISED OF THE POSSIBILITY OF THESE DAMAGES), OR ANY MISTAKES AND NEGLIGENCE IN DEVELOPING THIS SOFTWARE, OR FOR ANY CLAIM BY ANY OTHER PARTY. THE ORGANIZATION, BUSINESS, OR PERSON USING THIS SOFTWARE BEARS ALL RISKS AND RESPONSIBILITY FOR THE QUALITY AND PERFORMANCE OF THIS SOFTWARE. Some states do not allow the limitation or exclusion of liability for incidental or consequential damages, so the above limitation may not apply to you.

Sheet Change Log
B1: Change Log
B3: Version 2.9.4
B5: Additions:
B6: • Added 'One Pager' investment summary sheet
B8: Changes:
B9: • Escrow return year now self-clamps to the sale year, and same-year escrow returns are netted out of capital returned at sale/refi, eliminating the P&I escrow double-count. • Sale-year escrows (Exit H10) reduced to lender-held funds only. • Capital transaction fee fix (H19). • Equity Multiple includes the preferred-return deficiency paid at sale (Returns N19). • Year-1 escalation applied to Other Income and the expense override (P&L D15/D33). • Gas rule-of-thumb references its own row instead of Electric (Scenarios AF33). • Legal per-unit divides by unit count instead of income (Scenarios AE35). • IRR total row now includes the escrow column (IRR J114). • Vacancy/concessions inputs now reject positive entries (Scenarios).
B13: Version 2.9.3
B15: Additions:
B16: • Added Repairs module
B18: Changes:
B19: • Adding Member Equity Multiple to Returns and Summary tabs (Returns, Summary) • Fix to apply Annual Escalator percentages to year 1 in the P&L tab. Previously those numbers is cells D6 and D7 were not incorporated (P&L) • Formula fix to calculate Re-Finance Costs. Percentage now taken from refinance loan amount, rather than appraised value (Exit Strategy) • Added option to enter Interest Only months for refinance (Exit Strategy) • Moved Capital Transaction Fee and set a custom input for a Refinance Capital Transaction Fee to Mgr (Exit Strategy) • Capital Transaction Fee formula changed to pay up to the fee amount, rather than the prior all-or-nothing approach (Exit Strategy) • Adding Prepayment penalty to Sale option (Exit Strategy) • Adjusted Average Cash on Cash return to include 0% years (Returns) • Error fix on Member Returns Based On Specific $ Invested, % of ownership should remain the same through sale to properly distribute proceeds from sale (Returns) • Decoupled AAR and IRR after refinance as they are not the same (Returns) • Moved cap rate increase back to the Exit Strategy tab for easier customization (Exit Strategy) • Formula fix to properly calculate Average Annual Return to Date (Returns) • Fixed issued with IRR double counting Members Preferred Return Deficiency (IRR) • Giving Preferred Return Deficiency a line item as it should be separate from Cash on Cash return (Returns)
B22: Version 2.92
... B191: Fixed bug in the “Member Returns for $100,000 invested”: wasn’t working right when refinance
B193: =copyright -> Copyright © 2026 Michael Blank.
B194: The information herein is not guaranteed but believed to be accurate.

Sheet Variables
B1: Variables
B3: Variable | C3: Value-Add | D3: Stable | E3: Message if Under Minimum Target | F3: Message if Over Minimum Target
B4: DCR | C4: 1.25 | D4: 1.25 | E4: =CONCATENATE("The 'Debt Coverage Ratio' is low (Summary tab, Line 38). It should be at least ",About!C5," in the first year.") -> The 'Debt Coverage Ratio' is low (Summary tab, Line 38). It should be at least 1.25 in the first year. | F4: =CONCATENATE("Nice job! Since the Debt Coverage Ratio is at least ",About!C5," in the first year, you're more likely to qualify for financing.") -> Nice job! Since the Debt Coverage Ratio is at least 1.25 in the first year, you're more likely to qualify for financing.
B5: AAR | C5: 0.15 | D5: 0.13 | E5: =CONCATENATE(IF(F17="Yes","",""), "The AAR is low. It should be at least ", TEXT(About!C6,"0.0%")," or it will be tough to sell the deal to investors.") -> The AAR is low. It should be at least 15.0% or it will be tough to sell the deal to investors. | F5: =CONCATENATE(IF(F17="Yes","",""), "Your AAR looks great! Since it's at least ",TEXT(About!C6,"0.0%")," it will be a lot easier to sell to investors.") -> Your AAR looks great! Since it's at least 15.0% it will be a lot easier to sell to investors.
B6: IRR | C6: 0.14 | D6: 0.12 | E6: =CONCATENATE("The IRR is low. It should be at least ",TEXT(About!C7,"0.0%"),".") -> The IRR is low. It should be at least 14.0%. | F6: =CONCATENATE("This is a solid IRR since it's at least ",TEXT(About!C7,"0.0%"),".") -> This is a solid IRR since it's at least 14.0%.
B7: Expense percentage | C7: 0.5 | D7: 0.5 | E7: =CONCATENATE("The expenses appear low. They should be at least ",TEXT(About!C8,"0%")," of Total Net Income.") -> The expenses appear low. They should be at least 50% of Total Net Income. | F7: =CONCATENATE("Good job with the expenses! They're conservative since they're at least ",TEXT(About!C8,"0%")," of Total Net Income.") -> Good job with the expenses! They're conservative since they're at least 50% of Total Net Income.
B8: Return of Cap % | C8: 0.6 | D8: 0.6 | E8: =CONCATENATE("The capital returned to the investors is low. You should return at least ",TEXT(About!C9,"0%"), " or it's not really worth refinancing.") -> The capital returned to the investors is low. You should return at least 60% or it's not really worth refinancing. | F8: =CONCATENATE("This looks like a pretty good refinance since you're returning at least ",TEXT(About!C9,"0%"), " of the investor capital. They'll be pleased!") -> This looks like a pretty good refinance since you're returning at least 60% of the investor capital. They'll be pleased!
B9: Avg. CoC | C9: 0.07 | D9: 0.07 | E9: =CONCATENATE("The average Cash on Cash Return ", IF(Variables!F18="Yes"," (Before Refinance)",""), " is low. It should be at least ",TEXT(About!C10,"0.0%")," over the life of the investment.") -> The average Cash on Cash Return is low. It should be at least 7.0% over the life of the investment. | F9: =CONCATENATE("The average Cash on Cash Return ",IF(Variables!F18="Yes","(Before Refinance) ",""),"looks good since it's at least ",TEXT(About!C10,"0.0%"),IF(Variables!F18="Yes"," before the Refinance.",CONCATENATE(" over the ",year_sale," years of the investment."))) -> The average Cash on Cash Return looks good since it's at least 7.0% over the 5 years of the investment.
B10: Reserves/unit/yr | C10: =250*Summary!D4 -> 0 | D10: =250*Summary!D4 -> 0 | E10: =CONCATENATE("You should have at least $250/unit/year (",TEXT(About!C11,"$0"),") in Replacement Reserves in the P&L Tab") -> You should have at least $250/unit/year ($0) in Replacement Reserves in the P&L Tab | F10: =CONCATENATE("Nice job putting at least $250/unit/year (",TEXT(About!D11,"$0"),") in Replacement Reserves in the P&L Tab") -> Nice job putting at least $250/unit/year ($0) in Replacement Reserves in the P&L Tab
B11: Total Reserves | C11: =(Summary!D4*1000) -> 0 | D11: =(Summary!D4*1000) -> 0 | E11: =CONCATENATE("Reserves should include at least $1,000/unit (or ",TEXT(Summary!D4*1000,"$0"),")") -> Reserves should include at least $1,000/unit (or $0) | F11: Nice job!
B12: Sale Year 5 | C12: Yes | D12: Yes | E12: Investors want their money back after 5 years, so the deal has GOT to work with a sale in Year 5. Otherwise it may be difficult to get the investors on board. | F12: Nice job making the deal work with a sale in Year 5!
B13: Total loan | C13: 1000000 | D13: 1000000 | E13: The loan balance is under $1M and is less likely to qualify for a non-recourse loan. Who wants to personally guarantee a loan? | F13: Nice job keeping the loan balance above $1M; there's a good chance you'll be able to get a non-recourse loan (good).
E16: Internal Use
E17: Refinance? | F17: =IF(NOT(year_refi="NA"),"Yes","No") -> No
E18: Refinance AND Return All Capital? | F18: =IF(AND(NOT(year_refi="NA"),'Exit Strategy'!$D$22=0),"Yes","No") -> No
F20: No Verbal Agreement Yet | G20: Verbal Agreement | H20: LOI Submitted | I20: LOI Ratified | J20: Contract Submitted | K20: Contract Received | L20: Contract Ratified
E21: Click to Select | F21: If you're considering submitting the deal to the Deal Desk, then you need at least a verbal agreement around a number that makes sense before proceeding. | G21: Nicely done! Time to submit an LOI and/or to submit the deal to the Deal Desk! | H21: Exciting … fingers crossed! | I21: Well done … the contract is next. If you haven't submitted the deal to the Deal Desk, now is the time to do it. | J21: Nicely done! | K21: Rockin ..! | L21: AWESOME! Let's get busy with due diligence!
F23: Not a big deal, just asking :) It's not a requirement before getting it under contract, but it's a nice-to-have.
E24: Great initiative!
F25: Not a big deal, just asking :)
E26: Nice job! What terms did you get? Overwrite this cell with the answer. | F26: Value-Add | G26: Stable
E27: Click to Select | F27: A Stable deal can have slightly lower returns than a Value-Add deal. The Minimum Criteria in the Deal Readiness Dashboard were updated accordingly.
E28: A Value-Add deal requires a slightly higher return than a stable deal. The Minimum Criteria in the Deal Readiness Dashboard were updated accordingly. | F28: Yes | G28: No
E29: Click to Select
F30: Cool, just asking. If you'd like partner with Michael on this deal and learn more about the Deal Desk, please visit www.TheMichaelBlank.com/dealdesk.
E31: Fantastic! Please visit www.TheMichaelBlank.com/dealdesk for the most current Deal Desk process.
